Workbook

Sheet MF_Summary
F1: UNITS | G1: NAV | K1: birla | L1: 818919 | M1: 1017159 | N1: =M1-L1 -> 198240 | Q1: Sahana | U1: PPF
K2: franklin | L2: 572784 | M2: 611678 | N2: =M2-L2 -> 38894 | Q2: 40452 | R2: 1 | S2: 32 | U2: 2012-13 | V2: 1 | Y2: 29129 | Z2: 1
A3: 3 | B3: Canara Robeco Equity Debt Allocation Direct-G | D3: 174000 | F3: 1038.993 | G3: 168.22 | H3: =F3*G3 -> 174779.4 | I3: =H3-D3 -> 779.40246 | K3: HDFC | L3: 941985 | M3: 1029630 | N3: =M3-L3 -> 87645 | Q3: 40817 | R3: 2 | S3: 33 | U3: 2013-14 | V3: 2 | Y3: 29495 | Z3: 2
A4: 13 | B4: Tata Hybrid Equity Fund | D4: 113500 | F4: 755.928 | G4: 185.1145 | H4: =F4*G4 -> 139933.23 | I4: =H4-D4 -> 26433.234 | K4: icici | L4: 535261 | M4: 573274 | N4: =M4-L4 -> 38013 | Q4: 41183 | R4: 3 | S4: 34 | U4: 2014-15 | V4: 3 | Y4: 29860 | Z4: 3
A5: 44244 | B5: HDFC Hybrid Equity Fund | D5: 198500 | F5: 3850.105 | G5: 73.193 | H5: =F5*G5 -> 281800.74 | I5: =H5-D5 -> 83300.735 | J5: Done | K5: mirae | L5: 495351 | M5: 563037 | N5: =M5-L5 -> 67686 | Q5: 41548 | R5: 4 | S5: 35 | U5: 2015-16 | V5: 4 | Y5: 30225 | Z5: 4
A6: 44244 | B6: Aditya Birla Sun Life Balanced 95 Fund | D6: 124000 | F6: 181.16 | G6: 996.8 | H6: =F6*G6 -> 180580.29 | I6: =H6-D6 -> 56580.288 | J6: Done | K6: quantum | L6: 1561475 | M6: 1737734 | N6: =M6-L6 -> 176259 | Q6: 41913 | R6: 5 | S6: 36 | U6: 2016-17 | V6: 5 | Y6: 30590 | Z6: 5
A7: 44244 | B7: Mirae Asset Hybrid Equity Direct-G | D7: 100000 | F7: 5884.776 | G7: 21.125 | H7: =F7*G7 -> 124315.89 | I7: =H7-D7 -> 24315.893 | K7: Parag | L7: 1000000 | M7: 1008339 | N7: =M7-L7 -> 8339 | P7: 1618.538 | Q7: 42278 | R7: 6 | S7: 37 | U7: 2017-18 | V7: 6 | Y7: 30956 | Z7: 6
A8: transfer6 | B8: Franklin India Equity Hybrid Fund | D8: 59000 | F8: 482.22 | G8: 165.79 | H8: =F8*G8 -> 79947.254 | I8: =H8-D8 -> 20947.254 | L8: =SUM(L1:L7) -> 5925775 | M8: =SUM(M1:M7) -> 6540851 | P8: -453.662 | Q8: 42644 | R8: 7 | S8: 38 | U8: 2018-19 | V8: 7 | Y8: 31321 | Z8: 7
J9: nav | K9: =SUM(I6:I27) -> 3022122.5 | M9: =M8-L8 -> 615076 | P9: =SUM(P7:P8) -> 1164.876 | Q9: 43009 | R9: 8 | S9: 39 | U9: 2019-20 | V9: 8 | Y9: 31686 | Z9: 8
A10: Redeem2 | B10: BNP Paribas Substantial Equity Hybrid Fund | D10: 100000 | F10: 7072.486 | G10: 16.85 | H10: =F10*G10 -> 119171.39 | I10: =H10-D10 -> 19171.389 | J10: nav | Q10: 43374 | R10: 9 | S10: 40 | U10: 2020-21 | V10: 9 | Y10: 32051 | Z10: 9
A11: Redeem5 | B11: DSPBR Equity & Bond Direct-G | D11: 100000 | F11: 544.04 | G11: 215.013 | H11: =F11*G11 -> 116975.67 | I11: =H11-D11 -> 16975.673 | L11: 572784 | N11: 54.8058 | O11: 453.662 | P11: =N11*O11 -> 24863.309 | Q11: 43739 | R11: 10 | S11: 41 | U11: 2021-22 | V11: 10 | Y11: 32417 | Z11: 10
A12: Redeem3 | B12: L&T Hybrid Equity Fund | D12: 10000 | F12: 363.187 | G12: 34.743 | H12: =F12*G12 -> 12618.206 | I12: =H12-D12 -> 2618.2059 | J12: nav | P12: 6 | Q12: 44105 | R12: 11 | S12: 42 | U12: 2022-23 | V12: 11 | Y12: 32782 | Z12: 11
A13: Redeem7 | B13: Principal Hybrid Equity Direct-G | D13: 35000 | F13: 440.904 | G13: 101.72 | H13: =F13*G13 -> 44848.755 | I13: =H13-D13 -> 9848.7549 | J13: nav | M13: 1540907 | P13: 7 | Q13: 44470 | R13: 12 | S13: 43 | U13: 2023 | V13: 12 | Y13: 33147 | Z13: 12
A14: Redeem4 | B14: Reliance Equity Hybrid Fund | D14: 117070 | F14: 2498.411 | G14: 60.607 | H14: =F14*G14 -> 151421.2 | I14: =H14-D14 -> 34351.195 | J14: nav | K14: 24530 | L14: 4578993 | M14: =SUM(H5:H7) -> 586696.92 | P14: 8 | Q14: 44835 | R14: 13 | S14: 44 | U14: 2024 | V14: 13 | Y14: 33512 | Z14: 13
A15: Redeem8 | B15: SBI Equity Hybrid Fund | D15: 50000 | F15: 315.371 | G15: 183.9539 | H15: =F15*G15 -> 58013.725 | I15: =H15-D15 -> 8013.7254 | J15: nav | L15: =SUM(H6:H19) -> 1158845.2 | M15: =SUM(M13:M14) -> 2127603.9 | P15: 9 | Q15: 45200 | R15: 14 | S15: 45 | U15: 2025 | V15: 14 | Y15: 33878 | Z15: 14
A16: Redeem9 | B16: Axis | D16: 60000 | F16: 5107.195 | G16: 13.48 | H16: =F16*G16 -> 68844.989 | I16: =H16-D16 -> 8844.9886 | J16: nav | L16: 660000 | P16: 10 | Q16: 45566 | R16: 15 | S16: 46 | U16: 2026 | V16: 15 | Y16: 34243 | Z16: 15
A17: Redeem1 | B17: Kotak | D17: 60000 | F17: 2035.16 | G17: 36.842 | H17: =F17*G17 -> 74979.365 | I17: =H17-D17 -> 14979.365 | J17: nav | K17: 43302 | N17: -120000 | P17: 1st | Q17: 45931 | R17: 16 | S17: 47 | Y17: 34608 | Z17: 16
A18: Redeem11 | B18: Motilal | D18: 60000 | F18: 4927.11 | G18: 14.15 | H18: =F18*G18 -> 69718.606 | I18: =H18-D18 -> 9718.6065 | J18: nav | M18: 887919 | P18: 2nd | Q18: 46296 | R18: 17 | S18: 48 | Y18: 34973 | Z18: 17
A19: Redeem10 | B19: Sundaram | D19: 50000 | F19: 477.58 | G19: 120.21 | H19: =F19*G19 -> 57409.892 | I19: =H19-D19 -> 7409.8918 | J19: nav | P19: 13 | Q19: 46661 | R19: 18 | S19: 49 | Y19: 35339 | Z19: 18
B20: ICICI Equity Arbitrage | D20: 630000 | F20: 23883.519 | G20: 27.9222 | H20: =F20*G20 -> 666880.39 | I20: =H20-D20 -> 36880.394 | P20: 14 | Q20: 47027 | R20: 19
B21: HDFC mid-cap opportunity fund | C21: midcap | D21: 144000 | F21: 2441.841 | G21: 60.255 | H21: =F21*G21 -> 147133.13 | I21: =H21-D21 -> 3133.1295 | P21: 15 | Q21: 47392 | R21: 20
A22: 1 | B22: Franklin India Prima Fund | C22: midcap | D22: 139353 | F22: 136.131 | G22: 1043.0163 | H22: =F22*G22 -> 141986.85 | I22: =H22-D22 -> 2633.8519 | J22: mid-cap | P22: 16 | Q22: 47757 | R22: 21
A23: 2 | J23: mid-cap | Q23: 48122 | R23: 22 | S23: 50 | Y23: 35704 | Z23: 19
D24: =SUM(D6:D20) -> 1555070 | H24: =SUM(H6:H20) -> 1825725.6 | I24: =SUM(I10:I20) -> 168812.19 | Q24: 48488 | R24: 23 | S24: 51 | Y24: 36069 | Z24: 20
J25: 122242 | K25: 39000 | L25: 30000 | Q25: 48853 | R25: 24 | S25: 52 | Y25: 36434 | Z25: 21
D26: 630000 | E26: =SUM(D24:D26) -> 2185070 | G26: =I26-E26 -> 290757.62 | H26: 650102 | I26: =SUM(H24:H26) -> 2475827.6 | S26: 53 | Y26: 36800 | Z26: 22
A27: 14 | B27: Birla FoF - Aggressive | D27: 111900 | F27: 9038.287 | G27: 23.562 | H27: =F27*G27 -> 212960.12 | I27: =H27-D27 -> 101060.12 | K27: 42937 | L27: withdraw | M27: 212960.11 | S27: 54 | Y27: 37165 | Z27: 23
K28: 225255 | N28: 1017.7453 | S28: 55 | Y28: 37530 | Z28: 24
K29: 286854 | Y29: 37895 | Z29: 25
A30: 3 | B30: SUNDARAM MID CAP FUND DIRECT GROWTH | D30: 135000 | F30: 288.166 | G30: 475.0881 | H30: =F30*G30 -> 136904.24 | I30: =H30-D30 -> 1904.2374 | J30: mid-cap | N30: debt | O30: =SUM(H27,K28,K29) -> 725069.12 | Y30: 38261 | Z30: 26
A31: 4 | B31: Motilal Oswal Most Focused multicap 35 Fund | D31: 263398 | F31: 10301.416 | G31: 27.8889 | H31: =F31*G31 -> 287295.16 | I31: =H31-D31 -> 23897.161 | J31: multicap | L31: withdraw | M31: 287292.29 | N31: cash | O31: =SUM(K14,K32,K33,K34,M33) -> 2069734 | Y31: 38626 | Z31: 27
A32: 5 | B32: Mirae Asset India Equity Fund | C32: Multicap' | D32: 135000 | F32: 2766.363 | G32: 53.926 | H32: =F32*G32 -> 149178.89 | I32: =H32-D32 -> 14178.891 | J32: largecap | K32: 281087 | L32: transfer | M32: 151083.41 | Y32: 38991 | Z32: 28
A33: 6 | B33: QLTE | C33: Multicap' | D33: 177000 | F33: 3352.179 | G33: 52.953 | H33: =F33*G33 -> 177507.93 | I33: =H33-D33 -> 507.93459 | J33: largecap | K33: 1595402 | N33: 982035 | Y33: 39356 | Z33: 29
A34: 7 | B34: Aditya birla frontline equity fund | C34: largecap | D34: 120000 | F34: 652.04 | G34: 225.46 | H34: =F34*G34 -> 147008.94 | I34: =H34-D34 -> 27008.938 | J34: largecap | K34: 168715 | L34: transfer | M34: 154935.48 | N34: 400000 | O34: 154935.48 | Y34: 39722 | Z34: 30
A35: 8 | B35: Franklin india bluechip fund | C35: largecap | D35: 15000 | F35: 32.558 | G35: 472.5081 | H35: =F35*G35 -> 15383.919 | I35: =H35-D35 -> 383.91872 | J35: largecap | L35: withdraw | M35: 15383.92 | N35: =SUM(N33:N34) -> 1382035 | Y35: 40087 | Z35: 31
I36: =SUM(I2:I35) -> 3200517 | X36: 1 | Y36: 40452 | Z36: 32
K37: =SUM(D21:D35) -> 3425721 | N37: 5000000 | O37: =SUM(H38,K34,K33,K32,K29,K28,K14,O14) -> 8895268.8 | P37: =N37-O37 -> -3895268.8 | X37: 2 | Y37: 40817 | Z37: 33
D38: =SUM(D6:D35) -> 4980791 | H38: =SUM(H2:H35) -> 6313425.8 | X38: 3 | Y38: 41183 | Z38: 34
X39: 4 | Y39: 41548 | Z39: 35
A40: 8 | B40: ICICI Prudential Equity Income Fund Direct Plan Cumulative | D40: 10000 | F40: 795.861 | G40: 13.3 | H40: =F40*G40 -> 10584.951 | I40: =H40-D40 -> 584.9513 | L40: date of purchase | N40: date of sale | X40: 5 | Y40: 41913 | Z40: 36
A41: 2 | B41: Canara Robeco Emerging Equities | D41: 65000 | F41: 663.951 | G41: 100.34 | H41: =F41*G41 -> 66620.843 | I41: =H41-D41 -> 1620.8433 | J41: mid-cap | L41: ditch | X41: 6 | Y41: 42278 | Z41: 37
A42: 6 | B42: L&T India Special Situations Fund | D42: 174305 | F42: 3898.266 | G42: 52.804 | H42: =F42*G42 -> 205844.04 | I42: =H42-D42 -> 31539.038 | J42: multicap | K42: 47597 | L42: ditch | X42: 7 | Y42: 42644 | Z42: 38
B43: Edelweiss Mid and Small Cap Fund | C43: regular | D43: 118000 | F43: 6217.802 | G43: 28.7 | H43: =F43*G43 -> 178450.92 | I43: =H43-D43 -> 60450.917 | X43: 8 | Y43: 43009 | Z43: 39
A44: invested | B44: Reliance regular savings fund-balanced | C44: regular | D44: 50000 | F44: 1164.88 | G44: 55.31 | H44: =F44*G44 -> 64429.513 | I44: =H44-D44 -> 14429.513 | J44: invested in sundaram midcap | X44: 9 | Y44: 43374 | Z44: 40
B45: Aditya Birla Sun Life Balanced 95 Fund | C45: regular | D45: 41000 | F45: 66.965 | G45: 770.18 | H45: =F45*G45 -> 51575.104 | I45: =H45-D45 -> 10575.104 | X45: 10 | Y45: 43739 | Z45: 41
A46: moved | B46: Tata Retirement Savings Fund | C46: regular | D46: 8000 | F46: 394.175 | G46: 30.1496 | H46: =F46*G46 -> 11884.219 | I46: =H46-D46 -> 3884.2186 | N46: 154935.48 | X46: 11 | Y46: 44105 | Z46: 42 | AA46: 1 | AB46: ravi
B47: BNP paribas balanced fund | C47: regular | D47: 60168 | F47: 6016.8 | G47: 10.9497 | H47: =F47*G47 -> 65882.155 | I47: =H47-D47 -> 5714.155 | N47: =N46/F34 -> 237.61653 | X47: 12 | Y47: 44470 | Z47: 43 | AA47: 2 | AB47: ravi
A48: 7 | B48: hdfc prudence fund | D48: 99000 | F48: 195.004 | G48: 518.153 | H48: =F48*G48 -> 101041.91 | I48: =H48-D48 -> 2041.9076 | X48: 13 | Y48: 44835 | Z48: 44 | AA48: 3 | AB48: ravi
B49: Aditya Birla Sun Life Balanced 95 Fund | C49: regular | D49: 6000 | F49: 8.969 | G49: 751.44 | H49: =F49*G49 -> 6739.6654 | I49: =H49-D49 -> 739.66536 | X49: 14 | Y49: 45200 | Z49: 45 | AA49: 4 | AB49: moon
B50: birla front line | X50: 15 | Y50: 45566 | Z50: 46 | AA50: 5 | AB50: moon
X51: 16 | Y51: 45931 | Z51: 47 | AA51: 6 | AB51: moon
B52: Franklin India Bluechip Fund Direct Plan Growth Optio | K52: 115118 | X52: 17 | Y52: 46296 | Z52: 48 | AA52: 7 | AB52: moon
J53: pf | K53: 13398 | X53: 18 | Y53: 46661 | Z53: 49 | AA53: 8 | AB53: moon
J54: eps | K54: 1250 | X54: 19 | Y54: 47027 | Z54: 50 | AA54: 9 | AB54: moon
X55: 20 | Y55: 47392 | Z55: 51 | AA55: 10 | AB55: moon
X56: 21 | Y56: 47757 | Z56: 52 | AA56: 11 | AB56: moon
X57: 22 | Y57: 48122 | Z57: 53 | AA57: 12 | AB57: moon
X58: 23 | Y58: 48488 | Z58: 54 | AA58: 13 | AB58: moon
X59: 24 | Y59: 48853 | Z59: 55 | AA59: 14 | AB59: mars
X60: 25 | Y60: 49218 | Z60: 56 | AA60: 15 | AB60: mars
X61: 26 | Y61: 49583 | Z61: 57 | AA61: 16 | AB61: mars
Y62: 49949
Y63: 50314
Y64: 50679
Y65: 51044

Sheet Balanced
A1: birla balanced 95 fund | L1: dsp | M1: 59558.08 | O1: 24438.61
B2: inves | C2: nav | D2: units | E2: cur.Nav | F2: cur.Value | L2: BNP | M2: 82292.98
A3: 24/05/2017 | B3: 1000 | C3: 711.77 | D3: 1.405 | E3: =MF_Summary!G6 -> 996.8 | F3: =D3*E3 -> 1400.504 | G3: =F3-B3 -> 400.504 | H3: 44244 | L3: Mirae | M3: 59952.31 | N3: 60558
A4: 16/06/2017 | B4: 10000 | C4: 740.76 | D4: 13.5 | E4: =MF_Summary!G6 -> 996.8 | F4: =D4*E4 -> 13456.8 | G4: =F4-B4 -> 3456.8 | H4: 44244 | L4: SBI | M4: 173965.45
A5: 20/07/2017 | B5: 47348.12 | C5: 755.84 | D5: 62.642 | E5: =MF_Summary!G6 -> 996.8 | F5: =D5*E5 -> 62441.546 | G5: =F5-B5 -> 15093.426 | H5: 44244 | L5: canara | M5: 71119.8
A6: 28/07/2017 | B6: 5000 | C6: 762.06 | D6: 6.561 | E6: =MF_Summary!G6 -> 996.8 | F6: =D6*E6 -> 6540.0048 | G6: =F6-B6 -> 1540.0048 | H6: 44244
A7: 03/08/2017 | B7: 10454.28 | C7: 763.31 | D7: 13.696 | E7: =MF_Summary!G6 -> 996.8 | F7: =D7*E7 -> 13652.173 | G7: =F7-B7 -> 3197.8928 | H7: 44244 | L7: 6233000
A8: 03/08/2017 | B8: 20000 | C8: 763.31 | D8: 26.202 | E8: =MF_Summary!G6 -> 996.8 | F8: =D8*E8 -> 26118.154 | G8: =F8-B8 -> 6118.1536 | H8: 44244 | I8: 2390921 | J8: 1500000 | K8: 1370000 | L8: 4145909 | M8: =SUM(M1:M6) -> 446888.62 | N8: 650000 | O8: 680000
A9: 18/08/2017 | B9: 1143.39 | C9: 760.29 | D9: 1.504 | E9: =MF_Summary!G6 -> 996.8 | F9: =D9*E9 -> 1499.1872 | G9: =F9-B9 -> 355.7972 | H9: 44244
A10: 04/09/2017 | B10: 10410.92 | C10: 769.53 | D10: 13.529 | E10: =MF_Summary!G6 -> 996.8 | F10: =D10*E10 -> 13485.707 | G10: =F10-B10 -> 3074.7872 | H10: 44244
A11: 21/09/2017 | B11: 11556.43 | C11: 783.29 | D11: 14.754 | E11: =MF_Summary!G6 -> 996.8 | F11: =D11*E11 -> 14706.787 | G11: =F11-B11 -> 3150.3572 | H11: 44244
A12: 02/02/2018 | B12: 10000 | C12: 795.35 | D12: 12.573 | E12: =MF_Summary!G6 -> 996.8 | F12: =D12*E12 -> 12532.766 | G12: =F12-B12 -> 2532.7664 | H12: 44244 | I12: ICICI Prudential Equity Arbitrage Fund | T12: 3961000
A13: 05/02/2018 | B13: 5000 | C13: 791.24 | D13: 6.319 | E13: =MF_Summary!G6 -> 996.8 | F13: =D13*E13 -> 6298.7792 | G13: =F13-B13 -> 1298.7792 | H13: 44244 | J13: inves | K13: nav | L13: units | M13: cur.Nav | N13: cur.Value | T13: =SUM(N23,L36) -> 660837.86
C14: =AVERAGE(C3:C13) -> 763.34091 | I14: 43776 | J14: 140000 | K14: 26.3479 | L14: 5313.516 | M14: 27.6692 | N14: =L14*M14 -> 147020.74 | T14: 1370000
B15: =SUM(B3:B13) -> 131913.14 | D15: =SUM(D3:D13) -> 172.685 | F15: =SUM(F3:F13) -> 172132.41 | G15: =F15-B15 -> 40219.268 | I15: 43782 | J15: 100000 | K15: 26.3746 | L15: 3791.527 | M15: 27.6692 | N15: =L15*M15 -> 104908.52 | T15: 1400000
I16: 43783 | J16: 100000 | K16: 26.3683 | L16: 3792.433 | M16: 27.6692 | N16: =L16*M16 -> 104933.59 | T16: 200000
A17: Axis equity hybrid | I17: 43784 | J17: 150000 | K17: 26.3593 | L17: 5690.591 | M17: 27.6692 | N17: =L17*M17 -> 157454.1 | T17: 2459566
B18: inves | C18: nav | D18: units | E18: cur.Nav | F18: cur.Value | I18: 43798 | J18: 110000 | K18: 26.4225 | L18: 4163.119 | M18: 27.6692 | N18: =L18*M18 -> 115190.17
A19: 43878 | B19: 50000 | C19: 11.77 | D19: 4248.088 | E19: 13.48 | F19: =E19*D19 -> 57264.226 | G19: =F19-B19 -> 7264.2262 | H19: 44253 | I19: 43822 | J19: 10000 | K19: 26.4955 | L19: 377.423 | M19: 27.6692 | N19: =L19*M19 -> 10442.992 | T19: =SUM(T12:T17) -> 10051404
A20: 43885 | B20: 10000 | C20: 11.64 | D20: 859.107 | E20: 13.48 | F20: =E20*D20 -> 11580.762 | G20: =F20-B20 -> 1580.7624 | H20: 44253 | I20: 43823 | J20: 10000 | K20: 26.487 | L20: 377.544 | M20: 27.6692 | N20: =L20*M20 -> 10446.34
I21: 43825 | J21: 10000 | K21: 26.4995 | L21: 377.366 | M21: 27.6692 | N21: =L21*M21 -> 10441.415
A22: BNP paribas balanced fund
B23: inves | C23: nav | D23: units | E23: cur.Nav | F23: cur.Value | H23: redemption dt | J23: =SUM(J14:J21) -> 630000 | N23: =SUM(N14:N21) -> 660837.86
A24: 42909 | B24: 5000 | C24: 10.3508 | D24: 483.054 | E24: 12.507 | F24: =D24*E24 -> 6041.5564 | G24: =F24-B24 -> 1041.5564 | H24: 43984
A25: 42929 | B25: 29000 | C25: 10.5898 | D25: 2738.484 | E25: 12.507 | F25: =D25*E25 -> 34250.219 | G25: =F25-B25 -> 5250.2194 | H25: 43984
A26: 42958 | B26: 5241 | C26: 10.4175 | D26: 503.1 | E26: 12.507 | F26: =D26*E26 -> 6292.2717 | G26: =F26-B26 -> 1051.2717 | H26: 43984 | J26: =SUM(F24:F29) -> 82293.796
A27: 42965 | B27: 5000 | C27: 10.5296 | D27: 474.852 | E27: 12.507 | F27: =D27*E27 -> 5938.974 | G27: =F27-B27 -> 938.97396 | H27: 43984
A28: 43004 | B28: 4681.75 | C28: 10.5715 | D28: 442.865 | E28: 12.507 | F28: =D28*E28 -> 5538.9126 | G28: =F28-B28 -> 857.16255 | H28: 43984 | O28: =SUM(N23,O38) -> 976659.36
A29: 43031 | B29: 20963.75 | C29: 10.8202 | D29: 1937.464 | E29: 12.507 | F29: =D29*E29 -> 24231.862 | G29: =F29-B29 -> 3268.1122 | H29: 43984 | O29: 680000
A30: 43874 | B30: 100000 | C30: 14.1393 | D30: 7072.486 | E30: 16.8471 | F30: =E30*D30 -> 119150.88 | G30: =F30-B30 -> 19150.879 | H30: 44253
A33: Canara Robeco Balance
B34: inves | C34: nav | D34: units | E34: cur.Nav | F34: cur.Value | H34: redemption dt
A35: 42905 | B35: 5000 | C35: 141.94 | D35: 35.226 | E35: 167.44 | F35: =D35*E35 -> 5898.2414 | G35: =F35-B35 -> 898.24144 | H35: 43984
A36: 42944 | B36: 5000 | C36: 145.27 | D36: 34.419 | E36: 167.44 | F36: =D36*E36 -> 5763.1174 | G36: =F36-B36 -> 763.11736 | H36: 43984
A37: 42950 | B37: 10000 | C37: 145.62 | D37: 68.672 | E37: 167.44 | F37: =D37*E37 -> 11498.44 | G37: =F37-B37 -> 1498.4397 | H37: 43984
A38: 42965 | B38: 5000 | C38: 144.95 | D38: 34.495 | E38: 167.44 | F38: =D38*E38 -> 5775.8428 | G38: =F38-B38 -> 775.8428 | H38: 43984 | O38: =SUM(J26,J40,J63) -> 315821.49
A39: 42982 | B39: 5000 | C39: 146.13 | D39: 34.216 | E39: 167.44 | F39: =D39*E39 -> 5729.127 | G39: =F39-B39 -> 729.12704 | H39: 43984
A40: 42999 | B40: 5000 | C40: 148.37 | D40: 33.7 | E40: 167.44 | F40: =D40*E40 -> 5642.728 | G40: =F40-B40 -> 642.728 | H40: 43984 | J40: =SUM(F35:F49) -> 173968.99
A41: 43000 | B41: 5000 | C41: 146.34 | D41: 34.167 | E41: 167.44 | F41: =D41*E41 -> 5720.9225 | G41: =F41-B41 -> 720.92248 | H41: 43984
A42: 43003 | B42: 5000 | C42: 145.19 | D42: 34.438 | E42: 167.44 | F42: =D42*E42 -> 5766.2987 | G42: =F42-B42 -> 766.29872 | H42: 43984
A43: 43046 | B43: 5000 | C43: 149.36 | D43: 33.476 | E43: 167.44 | F43: =D43*E43 -> 5605.2214 | G43: =F43-B43 -> 605.22144 | H43: 43984
A44: 43052 | B44: 5000 | C44: 148.6 | D44: 33.647 | E44: 167.44 | F44: =D44*E44 -> 5633.8537 | G44: =F44-B44 -> 633.85368 | H44: 43984
A45: 43066 | B45: 2000 | C45: 151.08 | D45: 13.238 | E45: 167.44 | F45: =D45*E45 -> 2216.5707 | G45: =F45-B45 -> 216.57072 | H45: 43984
A46: 43069 | B46: 5000 | C46: 150.32 | D46: 33.262 | E46: 167.44 | F46: =D46*E46 -> 5569.3893 | G46: =F46-B46 -> 569.38928 | H46: 43984
A47: 43075 | B47: 2000 | C47: 148.41 | D47: 13.476 | E47: 167.44 | F47: =D47*E47 -> 2256.4214 | G47: =F47-B47 -> 256.42144 | H47: 43984
A48: 43133 | B48: 10000 | C48: 152.93 | D48: 65.389 | E48: 167.44 | F48: =D48*E48 -> 10948.734 | G48: =F48-B48 -> 948.73416 | H48: 43984
A49: 43875 | B49: 100000 | C49: 186.16 | D49: 537.172 | E49: 167.44 | F49: =D49*E49 -> 89944.08 | G49: =F49-B49 -> -10055.92 | H49: 43984
B51: =SUM(B35:B49) -> 174000 | C51: =AVERAGE(C35:C49) -> 150.04467 | D51: =SUM(D35:D49) -> 1038.993 | F51: =SUM(F35:F49) -> 173968.99
A53: HDFC hybrid Equity Fund
B54: inves | C54: nav | D54: units | E54: cur.Nav | F54: cur.Value | M54: =SUM(J26,J40,J63,J78,J101,J143,J193) -> 580358.69
A55: 43252 | B55: 203724.43 | C55: 52.914 | D55: 3850.11 | E55: =MF_Summary!G5 -> 73.193 | F55: =E55*D55 -> 281801.1 | G55: =F55-B55 -> 78076.671 | H55: 44244
A57: DSP blackrock Balance
B58: inves | C58: nav | D58: units | E58: cur.Nav | F58: cur.Value | H58: redemption dt
A59: 42905 | B59: 1000 | C59: 142.36 | D59: 7.024 | E59: 157.604 | F59: =E59*D59 -> 1107.0105 | G59: =F59-B59 -> 107.0105 | H59: 43984
A60: 42909 | B60: 4000 | C60: 140.825 | D60: 28.404 | E60: 157.604 | F60: =E60*D60 -> 4476.584 | G60: =F60-B60 -> 476.58402 | H60: 43984
A61: 42944 | B61: 5000 | C61: 145.479 | D61: 34.369 | E61: 157.604 | F61: =E61*D61 -> 5416.6919 | G61: =F61-B61 -> 416.69188 | H61: 43984
A62: 42955 | B62: 5000 | C62: 145.618 | D62: 34.336 | E62: 157.604 | F62: =E62*D62 -> 5411.4909 | G62: =F62-B62 -> 411.49094 | H62: 43984
A63: 42958 | B63: 5000 | C63: 141.531 | D63: 35.328 | E63: 157.604 | F63: =E63*D63 -> 5567.8341 | G63: =F63-B63 -> 567.83411 | H63: 43984 | J63: =SUM(F59:F69) -> 59558.709
A64: 42965 | B64: 5000 | C64: 144.062 | D64: 34.707 | E64: 157.604 | F64: =E64*D64 -> 5469.962 | G64: =F64-B64 -> 469.96203 | H64: 43984
A65: 42982 | B65: 5000 | C65: 146.176 | D65: 34.205 | E65: 157.604 | F65: =E65*D65 -> 5390.8448 | G65: =F65-B65 -> 390.84482 | H65: 43984
A66: 43000 | B66: 10000 | C66: 146.135 | D66: 68.43 | E66: 157.604 | F66: =E66*D66 -> 10784.842 | G66: =F66-B66 -> 784.84172 | H66: 43984
A67: 43003 | B67: 5000 | C67: 144.597 | D67: 34.579 | E67: 157.604 | F67: =E67*D67 -> 5449.7887 | G67: =F67-B67 -> 449.78872 | H67: 43984
A68: 43046 | B68: 5000 | C68: 150.745 | D68: 33.169 | E68: 157.604 | F68: =E68*D68 -> 5227.5671 | G68: =F68-B68 -> 227.56708 | H68: 43984
A69: 43052 | B69: 5000 | C69: 149.925 | D69: 33.35 | E69: 157.604 | F69: =E69*D69 -> 5256.0934 | G69: =F69-B69 -> 256.0934 | H69: 43984
A70: 43875 | B70: 100000 | C70: 183.81 | D70: 544.04 | E70: 215.013 | F70: =D70*E70 -> 116975.67 | G70: =F70-B70 -> 16975.673 | H70: 44253
A74: franklin balanced fund
B75: inves | C75: nav | D75: units | E75: cur.Nav | F75: cur.Value | G75: switch date
A76: 42902 | B76: 10000 | C76: 113.3405 | D76: 88.23 | E76: 117.7839 | F76: =E76*D76 -> 10392.073 | G76: 43985
A77: 42944 | B77: 5000 | C77: 116.4696 | D77: 42.93 | E77: 117.7839 | F77: =E77*D77 -> 5056.4628 | G77: 43985
A78: 42950 | B78: 10000 | C78: 117.0027 | D78: 85.468 | E78: 117.7839 | F78: =E78*D78 -> 10066.754 | G78: 43985 | J78: =SUM(F76:F82) -> 50856.615
A79: 42958 | B79: 5000 | C79: 114.6505 | D79: 43.611 | E79: 117.7839 | F79: =E79*D79 -> 5136.6737 | G79: 43985
A80: 42965 | B80: 5000 | C80: 115.8291 | D80: 43.167 | E80: 117.7839 | F80: =E80*D80 -> 5084.3776 | G80: 43985
A81: 42982 | B81: 5000 | C81: 116.5207 | D81: 42.911 | E81: 117.7839 | F81: =E81*D81 -> 5054.2249 | G81: 43985
A82: 43000 | B82: 10000 | C82: 117.0105 | D82: 85.462 | E82: 117.7839 | F82: =E82*D82 -> 10066.048 | G82: 43985
A83: 43046 | B83: 5000 | C83: 120.5479 | D83: 41.477 | E83: =MF_Summary!G8 -> 165.79 | F83: =D83*E83 -> 6876.4718 | G83: =F83-B83 -> 1876.4718
A84: 43048 | B84: 2000 | C84: 120.6773 | D84: 16.573 | E84: =MF_Summary!G8 -> 165.79 | F84: =D84*E84 -> 2747.6377 | G84: =F84-B84 -> 747.63767
A85: 43052 | B85: 5000 | C85: 120.8166 | D85: 41.385 | E85: =MF_Summary!G8 -> 165.79 | F85: =D85*E85 -> 6861.2191 | G85: =F85-B85 -> 1861.2191
A86: 43066 | B86: 5000 | C86: 122.343 | D86: 40.869 | E86: =MF_Summary!G8 -> 165.79 | F86: =D86*E86 -> 6775.6715 | G86: =F86-B86 -> 1775.6715
A87: 43069 | B87: 5000 | C87: 121.0098 | D87: 41.319 | E87: =MF_Summary!G8 -> 165.79 | F87: =D87*E87 -> 6850.277 | G87: =F87-B87 -> 1850.277
A88: 43075 | B88: 2000 | C88: 119.4965 | D88: 16.737 | E88: =MF_Summary!G8 -> 165.79 | F88: =D88*E88 -> 2774.8272 | G88: =F88-B88 -> 774.82723
A89: 43081 | B89: 5000 | C89: 121.1919 | D89: 41.257 | E89: =MF_Summary!G8 -> 165.79 | F89: =D89*E89 -> 6839.998 | G89: =F89-B89 -> 1839.998
A90: 43110 | B90: 10000 | C90: 124.057 | D90: 80.608 | E90: =MF_Summary!G8 -> 165.79 | F90: =D90*E90 -> 13364 | G90: =F90-B90 -> 3364.0003
A91: 43125 | B91: 5000 | C91: 125.1107 | D91: 39.965 | E91: =MF_Summary!G8 -> 165.79 | F91: =D91*E91 -> 6625.7973 | G91: =F91-B91 -> 1625.7973
A92: 43130 | B92: 5000 | C92: 124.6312 | D92: 40.118 | E92: =MF_Summary!G8 -> 165.79 | F92: =D92*E92 -> 6651.1632 | G92: =F92-B92 -> 1651.1632
A93: 43133 | B93: 10000 | C93: 122.0818 | D93: 81.912 | E93: =MF_Summary!G8 -> 165.79 | F93: =D93*E93 -> 13580.19 | G93: =F93-B93 -> 3580.1905
C94: =AVERAGE(C83:C93) -> 121.9967
B95: =SUM(B76:B93) -> 109000 | F95: =SUM(F76:F93) -> 130803.87 | G95: =SUM(G83:G93) -> 20947.254
A97: icici balanced fund
B98: inves | C98: nav | D98: units | E98: cur.Nav | F98: cur.Value
A99: 42898 | B99: 1000 | C99: 123.54 | D99: 8.1 | E99: 129.81 | F99: =D99*E99 -> 1051.461 | G99: 43984
A100: 42907 | B100: 5000 | C100: 124.04 | D100: 40.31 | E100: 129.81 | F100: =D100*E100 -> 5232.6411 | G100: 43984
A101: 42937 | B101: 50000 | C101: 127.75 | D101: 391.39 | E101: 129.81 | F101: =D101*E101 -> 50806.336 | G101: 43984 | J101: =SUM(F99:F105) -> 82607.19
A102: 42958 | B102: 5000 | C102: 124.68 | D102: 40.1 | E102: 129.81 | F102: =D102*E102 -> 5205.381 | G102: 43984
A103: 42965 | B103: 5000 | C103: 126.56 | D103: 39.51 | E103: 129.81 | F103: =D103*E103 -> 5128.7931 | G103: 43984
A104: 42982 | B104: 5000 | C104: 127.03 | D104: 39.36 | E104: 129.81 | F104: =D104*E104 -> 5109.3216 | G104: 43984
A105: 42999 | B105: 10000 | C105: 128.87 | D105: 77.6 | E105: 129.81 | F105: =D105*E105 -> 10073.256 | G105: 43984
A106: 43272 | B106: 10584.83 | C106: 132.98 | D106: 79.597 | E106: 135.05 | F106: =D106*E106 -> 10749.575 | G106: 44015
C107: =AVERAGE(C105:C106) -> 130.925
B108: =SUM(B99:B106) -> 91584.83 | D108: =SUM(D99:D106) -> 715.967 | F108: =SUM(F99:F106) -> 93356.765 | I108: 149.65
A110: ICICI Prudential Equity Arbitrage Fund - 60954963
...

Sheet Midcap
A1: HDFC mid-cap oppertunities direct fund | K1: Sundaram Select mid-cap
B2: inves | C2: nav | D2: units | E2: cur.Nav | F2: cur.Value | L2: Invest | M2: nav | N2: units | O2: cur.Nav | P2: cur.Value
A3: 42999 | B3: 10000 | C3: 56.989 | D3: 172.472 | E3: 59.282 | F3: =D3*E3 -> 10224.485 | G3: =F3-B3 -> 224.4851 | H3: =D3 -> 172.472 | K3: 43039 | L3: 24886.99 | M3: 520.2144 | N3: 47.84 | O3: 475.0881 | P3: =N3*O3 -> 22728.215
A4: 43000 | B4: 5000 | C4: 55.677 | D4: 89.804 | E4: 59.282 | F4: =D4*E4 -> 5323.7607 | G4: =F4-B4 -> 323.76073 | H4: =D3+D4 -> 262.276 | K4: 43066 | L4: 2000 | M4: 538.77 | N4: 3.712 | O4: 475.0881 | P4: =N4*O4 -> 1763.527
A5: 43003 | B5: 5000 | C5: 55.086 | D5: 90.767 | E5: 59.282 | F5: =D5*E5 -> 5380.8493 | G5: =F5-B5 -> 380.84929 | K5: 43069 | L5: 5000 | M5: 538.0955 | N5: 9.292 | O5: 475.0881 | P5: =N5*O5 -> 4414.5186
A6: 43048 | B6: 5000 | C6: 59.276 | D6: 84.351 | E6: 59.282 | F6: =D6*E6 -> 5000.496 | G6: =F6-B6 -> 0.495982 | K6: 43096 | L6: 64428 | M6: 557.3003 | N6: 115.607 | O6: 475.0881 | P6: =N6*O6 -> 54923.51
A7: 43052 | B7: 5000 | C7: 59.097 | D7: 84.607 | E7: 59.282 | F7: =D7*E7 -> 5015.6722 | G7: =F7-B7 -> 15.672174 | K7: 43125 | L7: 10000 | M7: 553.9582 | N7: 18.052 | O7: 475.0881 | P7: =N7*O7 -> 8576.2904
A8: 43054 | B8: 2000 | C8: 58.314 | D8: 34.297 | E8: 59.282 | F8: =D8*E8 -> 2033.1948 | G8: =F8-B8 -> 33.194754 | K8: 43133 | L8: 10000 | M8: 525.7504 | N8: 19.02 | O8: 475.0881 | P8: =N8*O8 -> 9036.1757
A9: 43066 | B9: 2000 | C9: 60.281 | D9: 33.178 | E9: 59.282 | F9: =D9*E9 -> 1966.8582 | G9: =F9-B9 -> -33.141804 | K9: 43153 | L9: 3000 | M9: 519.5599 | N9: 5.774 | O9: 475.0881 | P9: =N9*O9 -> 2743.1587
A10: 43069 | B10: 10000 | C10: 59.875 | D10: 167.015 | E10: 59.282 | F10: =D10*E10 -> 9900.9832 | G10: =F10-B10 -> -99.01677 | K10: 43164 | L10: 5000 | M10: 524.7461 | N10: 9.528 | O10: 475.0881 | P10: =N10*O10 -> 4526.6394
A11: 43075 | B11: 2000 | C11: 58.935 | D11: 33.936 | E11: 59.282 | F11: =D11*E11 -> 2011.794 | G11: =F11-B11 -> 11.793952 | K11: 43182 | L11: 5000 | M11: 503.2336 | N11: 9.9357 | O11: 475.0881 | P11: =N11*O11 -> 4720.3328
A12: 43081 | B12: 5000 | C12: 59.753 | D12: 83.678 | E12: 59.282 | F12: =D12*E12 -> 4960.5992 | G12: =F12-B12 -> -39.400804 | K12: 43224 | L12: 10000 | M12: 538.9554 | N12: 19.468 | O12: 475.0881 | P12: =N12*O12 -> 9249.0151
A13: 43110 | B13: 10000 | C13: 63.748 | D13: 156.868 | E13: 59.282 | F13: =D13*E13 -> 9299.4488 | G13: =F13-B13 -> -700.55122 | K13: 43256 | L13: 5000 | M13: 508.8307 | N13: 9.826 | O13: 475.0881 | P13: =N13*O13 -> 4668.2157
A14: 43125 | B14: 10000 | C14: 62.716 | D14: 159.449 | E14: 59.282 | F14: =D14*E14 -> 9452.4556 | G14: =F14-B14 -> -547.54438 | K14: 43278 | L14: 10000 | M14: 497.2493 | N14: 20.111 | O14: 475.0881 | P14: =N14*O14 -> 9554.4968
A15: 43130 | B15: 5000 | C15: 61.687 | D15: 81.054 | E15: 59.282 | F15: =D15*E15 -> 4805.0432 | G15: =F15-B15 -> -194.95677
A16: 43133 | B16: 10000 | C16: 59.106 | D16: 169.188 | E16: 59.282 | F16: =D16*E16 -> 10029.803 | G16: =F16-B16 -> 29.803016 | M16: =SUM(M3:M15) -> 6326.6638
A17: 43136 | B17: 10000 | C17: 58.9 | D17: 169.779 | E17: 59.282 | F17: =D17*E17 -> 10064.839 | G17: =F17-B17 -> 64.838678 | L17: =SUM(L3:L14) -> 154314.99 | N17: =SUM(N3:N14) -> 288.1657 | P17: =SUM(P3:P14) -> 136904.09
A18: 43139 | B18: 10000 | C18: 59.397 | D18: 168.359 | E18: 59.282 | F18: =D18*E18 -> 9980.6582 | G18: =F18-B18 -> -19.341762
A19: 43151 | B19: 5000 | C19: 58.618 | D19: 85.298 | E19: 59.282 | F19: =D19*E19 -> 5056.636 | G19: =F19-B19 -> 56.636036
A20: 43153 | B20: 3000 | C20: 58.562 | D20: 51.228 | E20: 59.282 | F20: =D20*E20 -> 3036.8983 | G20: =F20-B20 -> 36.898296
A21: 43164 | B21: 5000 | C21: 59.025 | D21: 84.71 | E21: 59.282 | F21: =D21*E21 -> 5021.7782 | G21: =F21-B21 -> 21.77822
A22: 43182 | B22: 10000 | C22: 57.068 | D22: 175.23 | E22: 59.282 | F22: =D22*E22 -> 10387.985 | G22: =F22-B22 -> 387.98486
A23: 43256 | B23: 5000 | C23: 57.753 | D23: 86.576 | E23: 59.282 | F23: =D23*E23 -> 5132.3984 | G23: =F23-B23 -> 132.39843
A24: 43279 | B24: 10000 | C24: 56.498 | D24: 176.997 | E24: 59.282 | F24: =D24*E24 -> 10492.736 | G24: =F24-B24 -> 492.73615
C26: =AVERAGE(C3:C24) -> 58.9255
A30: Canara Robeco Emerging Equities | K30: Franklin India Prima Fund
C31: nav | D31: units | E31: cur.Nav | F31: cur.Value | M31: nav | N31: units | O31: cur.Nav | P31: cur.Value
A32: 43003 | B32: 5000 | C32: 91.08 | D32: 54.897 | E32: 97.79 | F32: =D32*E32 -> 5368.3776 | K32: 43005 | L32: 355.7107 | M32: 941.0336 | N32: 0.378 | O32: 1038.0962 | P32: =N32*O32 -> 392.40036 | Q32: =P32-L32 -> 36.689664
A33: 43046 | B33: 5000 | C33: 96.67 | D33: 51.722 | E33: 97.79 | F33: =D33*E33 -> 5057.8944 | K33: 43046 | L33: 5000 | M33: 1001.5664 | N33: 4.992 | O33: 1038.0962 | P33: =N33*O33 -> 5182.1762 | Q33: =P33-L33 -> 182.17623
A34: 43052 | B34: 5000 | C34: 95.63 | D34: 52.285 | E34: 97.79 | F34: =D34*E34 -> 5112.9501 | K34: 43048 | L34: 2000 | M34: 1003.763 | N34: 1.993 | O34: 1038.0962 | P34: =N34*O34 -> 2068.9257 | Q34: =P34-L34 -> 68.925727
A35: 43054 | B35: 2000 | C35: 94.94 | D35: 21.066 | E35: 97.79 | F35: =D35*E35 -> 2060.0441 | K35: 43052 | L35: 5000 | M35: 1003.9989 | N35: 4.98 | O35: 1038.0962 | P35: =N35*O35 -> 5169.7191 | Q35: =P35-L35 -> 169.71908
A36: 43066 | B36: 3000 | C36: 98.69 | D36: 30.398 | E36: 97.79 | F36: =D36*E36 -> 2972.6204 | K36: 43054 | L36: 2000 | M36: 994.8978 | N36: 2.01 | O36: 1038.0962 | P36: =N36*O36 -> 2086.5734 | Q36: =P36-L36 -> 86.573362
A37: 43069 | B37: 10000 | C37: 98.73 | D37: 101.286 | E37: 97.79 | F37: =D37*E37 -> 9904.7579 | K37: 43066 | L37: 5000 | M37: 1028.183 | N37: 4.863 | O37: 1038.0962 | P37: =N37*O37 -> 5048.2618 | Q37: =P37-L37 -> 48.261821
A38: 43075 | B38: 2000 | C38: 96.72 | D38: 20.678 | E38: 97.79 | F38: =D38*E38 -> 2022.1016 | K38: 43069 | L38: 10000 | M38: 1030.3098 | N38: 9.706 | O38: 1038.0962 | P38: =N38*O38 -> 10075.762 | Q38: =P38-L38 -> 75.761717
A39: 43125 | B39: 10000 | C39: 102.85 | D39: 97.229 | E39: 97.79 | F39: =D39*E39 -> 9508.0239 | K39: 43075 | L39: 2000 | M39: 1013.7329 | N39: 1.973 | O39: 1038.0962 | P39: =N39*O39 -> 2048.1638 | Q39: =P39-L39 -> 48.163803
A40: 43133 | B40: 10000 | C40: 98.43 | D40: 101.595 | E40: 97.79 | F40: =D40*E40 -> 9934.9751 | K40: 43081 | L40: 5000 | M40: 1023.3169 | N40: 4.886 | O40: 1038.0962 | P40: =N40*O40 -> 5072.138 | Q40: =P40-L40 -> 72.138033
A41: 43136 | B41: 10000 | C41: 98.03 | D41: 102.01 | E41: 97.79 | F41: =D41*E41 -> 9975.5579 | K41: 43110 | L41: 10000 | M41: 1091.6542 | N41: 9.16 | O41: 1038.0962 | P41: =N41*O41 -> 9508.9612 | Q41: =P41-L41 -> -491.03881
A42: 43153 | B42: 3000 | C42: 97.45 | D42: 30.785 | E42: 97.79 | F42: =D42*E42 -> 3010.4651 | K42: 43125 | L42: 10000 | M42: 1079.4029 | N42: 9.264 | O42: 1038.0962 | P42: =N42*O42 -> 9616.9232 | Q42: =P42-L42 -> -383.0768
C43: =AVERAGE(C32:C42) -> 97.201818 | D43: =SUM(D32:D42) -> 663.951 | K43: 43130 | L43: 5000 | M43: 1067.2102 | N43: 4.685 | O43: 1038.0962 | P43: =N43*O43 -> 4863.4807 | Q43: =P43-L43 -> -136.5193
B44: =SUM(B32:B42) -> 65000 | K44: 43133 | L44: 10000 | M44: 1036.682 | N44: 9.646 | O44: 1038.0962 | P44: =N44*O44 -> 10013.476 | Q44: =P44-L44 -> 13.475945
K45: 43136 | L45: 5000 | M45: 1030.2784 | N45: 4.853 | O45: 1038.0962 | P45: =N45*O45 -> 5037.8809 | Q45: =P45-L45 -> 37.880859
D46: =C43*D43 -> 64537.244 | K46: 43139 | L46: 10000 | M46: 1033.2192 | N46: 9.678 | O46: 1038.0962 | P46: =N46*O46 -> 10046.695 | Q46: =P46-L46 -> 46.695024
K47: 43151 | L47: 5000 | M47: 1024.5016 | N47: 4.88 | O47: 1038.0962 | P47: =N47*O47 -> 5065.9095 | Q47: =P47-L47 -> 65.909456
K48: 43153 | L48: 3000 | M48: 1015.4613 | N48: 2.954 | O48: 1038.0962 | P48: =N48*O48 -> 3066.5362 | Q48: =P48-L48 -> 66.536175
K49: 43164 | L49: 5000 | M49: 1024.7197 | N49: 4.879 | O49: 1038.0962 | P49: =N49*O49 -> 5064.8714 | Q49: =P49-L49 -> 64.87136
K50: 43178 | L50: 5000 | M50: 999.1256 | N50: 5.004 | O50: 1038.0962 | P50: =N50*O50 -> 5194.6334 | Q50: =P50-L50 -> 194.63338
K51: 43182 | L51: 5000 | M51: 987.066 | N51: 5.066 | O51: 1038.0962 | P51: =N51*O51 -> 5258.9953 | Q51: =P51-L51 -> 258.99535
K52: 43256 | L52: 5000 | M52: 1013.9548 | N52: 4.931 | O52: 1038.0962 | P52: =N52*O52 -> 5118.8524 | Q52: =P52-L52 -> 118.85236
K53: 43276 | L53: 5000 | M53: 1000.3568 | N53: 4.998 | O53: 1038.0962 | P53: =N53*O53 -> 5188.4048 | Q53: =P53-L53 -> 188.40481
K54: 43278 | L54: 10000 | M54: 989.6463 | N54: 10.105 | O54: 1038.0962 | P54: =N54*O54 -> 10489.962 | Q54: =P54-L54 -> 489.9621
K55: 43279 | L55: 10000 | M55: 975.9282 | N55: 10.247 | O55: 1038.0962 | P55: =N55*O55 -> 10637.372 | Q55: =P55-L55 -> 637.37176
M56: =AVERAGE(M32:M55) -> 1017.0837
L57: =SUM(L32:L55) -> 139355.71 | P57: =SUM(P32:P55) -> 141317.07

Sheet Largecap
A1: Mirae Asset India Equity Fund | I1: Quantum Long Term Equity | Q1: Aditya birla frontline equity fund
C2: nav | D2: units | E2: cur.Nav | F2: cur.Value | K2: nav | L2: units | M2: cur.Nav | N2: cur.Value | S2: nav | T2: units | U2: cur.Nav | V2: cur.Value
A3: 42965 | B3: 5000 | C3: 45.815 | D3: 109.135 | E3: 54.615 | F3: =D3*E3 -> 5960.408 | G3: =F3-B3 -> 960.40803 | I3: 42897 | J3: 1000 | K3: 53.73 | L3: 18.612 | M3: 53.43 | N3: =L3*M3 -> 994.43916 | Q3: 14/11/2017 | R3: 66775.47 | S3: 224.39 | T3: 297.588 | U3: 237.62 | V3: =T3*U3 -> 70712.861
A4: 42999 | B4: 10000 | C4: 47.745 | D4: 209.446 | E4: 54.615 | F4: =D4*E4 -> 11438.893 | G4: =F4-B4 -> 1438.8933 | I4: 42958 | J4: 5000 | K4: 52.62 | L4: 95.021 | M4: 53.43 | N4: =L4*M4 -> 5076.972 | Q4: 30/11/2017 | R4: 10000 | S4: 225.24 | T4: 44.397 | U4: 237.62 | V4: =T4*U4 -> 10549.615
A5: 43000 | B5: 10000 | C5: 46.712 | D5: 214.078 | E5: 54.615 | F5: =D5*E5 -> 11691.87 | G5: =F5-B5 -> 1691.87 | I5: 43052 | J5: 5000 | K5: 52.56 | L5: 95.129 | M5: 53.43 | N5: =L5*M5 -> 5082.7425 | Q5: 42898 | R5: 3000 | S5: 221.02 | T5: 13.573 | U5: 237.62 | V5: =T5*U5 -> 3225.2163
A6: 43003 | B6: 5000 | C6: 46.155 | D6: 108.331 | E6: 54.615 | F6: =D6*E6 -> 5916.4976 | G6: =F6-B6 -> 916.49757 | I6: 43054 | J6: 5000 | K6: 52.11 | L6: 95.951 | M6: 53.43 | N6: =L6*M6 -> 5126.6619 | Q6: 43081 | R6: 5000 | S6: 225.65 | T6: 22.158 | U6: 237.62 | V6: =T6*U6 -> 5265.184
A7: 43047 | B7: 5000 | C7: 48.656 | D7: 102.762 | E7: 54.615 | F7: =D7*E7 -> 5612.3466 | G7: =F7-B7 -> 612.34663 | I7: 43066 | J7: 5000 | K7: 53.34 | L7: 93.738 | M7: 53.43 | N7: =L7*M7 -> 5008.4213 | Q7: 43374 | R7: 10000 | S7: 235.12 | T7: 42.531 | U7: 237.62 | V7: =T7*U7 -> 10106.216
A8: 43054 | B8: 5000 | C8: 47.968 | D8: 104.236 | E8: 54.615 | F8: =D8*E8 -> 5692.8491 | G8: =F8-B8 -> 692.84914 | I8: 43073 | J8: 10000 | K8: 52.21 | L8: 191.534 | M8: 53.43 | N8: =L8*M8 -> 10233.662 | Q8: 25/01/2018 | R8: 10000 | S8: 239.29 | T8: 41.79 | U8: 237.62 | V8: =T8*U8 -> 9930.1398
A9: 43066 | B9: 5000 | C9: 49.541 | D9: 7464764 | E9: 54.615 | F9: =D9*E9 -> 4.0768809e+08 | G9: =F9-B9 -> 4.0768309e+08 | I9: 43075 | J9: 3000 | K9: 51.62 | L9: 58.117 | M9: 53.43 | N9: =L9*M9 -> 3105.1913 | Q9: 43133 | R9: 10000 | S9: 231.43 | T9: 43.21 | U9: 237.62 | V9: =T9*U9 -> 10267.56
A10: 43073 | B10: 10000 | C10: 48.295 | D10: 767585 | E10: 54.615 | F10: =D10*E10 -> 41921655 | G10: =F10-B10 -> 41911655 | I10: 43081 | J10: 10000 | K10: 52.37 | L10: 190.949 | M10: 53.43 | N10: =L10*M10 -> 10202.405 | Q10: 43222 | R10: 10000 | S10: 230.24 | T10: 43.433 | U10: 237.62 | V10: =T10*U10 -> 10320.549
A11: 43075 | B11: 2000 | C11: 47.859 | D11: 41.789 | E11: 54.615 | F11: =D11*E11 -> 2282.3062 | G11: =F11-B11 -> 282.30624 | I11: 43110 | J11: 10000 | K11: 54.5 | L11: 183.486 | M11: 53.43 | N11: =L11*M11 -> 9803.657 | Q11: 43153 | R11: 3000 | S11: 223.47 | T11: 13.425 | U11: 237.62 | V11: =T11*U11 -> 3190.0485
A12: 43081 | B12: 10000 | C12: 48.975 | D12: 204.186 | E12: 54.615 | F12: =D12*E12 -> 11151.618 | G12: =F12-B12 -> 1151.6184 | I12: 43129 | J12: 10000 | K12: 55.83 | L12: 179.115 | M12: 53.43 | N12: =L12*M12 -> 9570.1145 | Q12: 43162 | R12: 5000 | S12: 223.27 | T12: 22.394 | U12: 237.62 | V12: =T12*U12 -> 5321.2623
A13: 43110 | B13: 10000 | C13: 51.021 | D13: 195.998 | E13: 54.615 | F13: =D13*E13 -> 10704.431 | G13: =F13-B13 -> 704.43077 | I13: 43130 | J13: 5000 | K13: 55.59 | L13: 89.944 | M13: 53.43 | N13: =L13*M13 -> 4805.7079 | Q13: 43167 | R13: 10000 | S13: 220.81 | T13: 45.287 | U13: 237.62 | V13: =T13*U13 -> 10761.097
A14: 43129 | B14: 10000 | C14: 52.433 | D14: 190.72 | E14: 54.615 | F14: =D14*E14 -> 10416.173 | G14: =F14-B14 -> 416.1728 | I14: 43136 | J14: 20000 | K14: 53.56 | L14: 373.413 | M14: 53.43 | N14: =L14*M14 -> 19951.457 | T14: =SUM(T3:T13) -> 629.786
A15: 43130 | B15: 5000 | C15: 52.072 | D15: 96.021 | E15: 54.615 | F15: =D15*E15 -> 5244.1869 | G15: =F15-B15 -> 244.18692 | I15: 43136 | J15: 10000 | K15: 53.56 | L15: 186.706 | M15: 53.43 | N15: =L15*M15 -> 9975.7016
A16: 43136 | B16: 10000 | C16: 49.738 | D16: 201.054 | E16: 54.615 | F16: =D16*E16 -> 10980.564 | G16: =F16-B16 -> 980.56421 | I16: 43153 | J16: 3000 | K16: 52.47 | L16: 57.176 | M16: 53.43 | N16: =L16*M16 -> 3054.9137
A17: 43136 | B17: 10000 | C17: 49.738 | D17: 201.054 | E17: 54.615 | F17: =D17*E17 -> 10980.564 | G17: =F17-B17 -> 980.56421 | I17: 43158 | J17: 10000 | K17: 53.09 | L17: 188.3594 | M17: 53.43 | N17: =L17*M17 -> 10064.043 | R17: =R10+R13 -> 20000 | S17: =(S10+S13)/2 -> 225.525 | T17: =T10+T13 -> 88.72
A18: 43153 | B18: 3000 | C18: 48.331 | D18: 62.072 | E18: 54.615 | F18: =D18*E18 -> 3390.0623 | G18: =F18-B18 -> 390.06228 | I18: 43159 | J18: 5000 | K18: 52.98 | L18: 94.37 | M18: 53.43 | N18: =L18*M18 -> 5042.1891 | S18: =S17*T17 -> 20008.578
A19: 43162 | B19: 5000 | C19: 48.34 | D19: 103.434 | E19: 54.615 | F19: =D19*E19 -> 5649.0479 | G19: =F19-B19 -> 649.04791 | I19: 43162 | J19: 5000 | K19: 52.25 | L19: 95.694 | M19: 53.43 | N19: =L19*M19 -> 5112.9304
A20: 43182 | B20: 5000 | C20: 46.956 | D20: 106.483 | E20: 54.615 | F20: =D20*E20 -> 5815.569 | G20: =F20-B20 -> 815.56905 | I20: 43167 | J20: 10000 | K20: 51.71 | L20: 193.386 | M20: 53.43 | N20: =L20*M20 -> 10332.614
A21: 43241 | B21: 5000 | C21: 47.91 | D21: 104.362 | E21: 54.615 | F21: =D21*E21 -> 5699.7306 | G21: =F21-B21 -> 699.73063 | I21: 43178 | J21: 10000 | K21: 50.99 | L21: 196.117 | M21: 53.43 | N21: =L21*M21 -> 10478.531
A22: 43256 | B22: 5000 | C22: 48.443 | D22: 103.214 | E22: 54.615 | F22: =D22*E22 -> 5637.0326 | G22: =F22-B22 -> 637.03261 | I22: 43182 | J22: 5000 | K22: 50.74 | L22: 98.542 | M22: 53.43 | N22: =L22*M22 -> 5265.0991
I23: 43237 | J23: 10000 | K23: 52.62 | L23: 190.042 | M23: 53.43 | N23: =L23*M23 -> 10153.944
I24: 43240 | J24: 5000 | K24: 51.67 | L24: 96.768 | M24: 53.43 | N24: =L24*M24 -> 5170.3142
I25: 43241 | J25: 5000 | K25: 51.67 | L25: 96.768 | M25: 53.43 | N25: =L25*M25 -> 5170.3142
I26: 43256 | J26: 5000 | K26: 51.86 | L26: 96.413 | M26: 53.43 | N26: =L26*M26 -> 5151.3466
I27: 43279 | J27: 5000 | K27: 51.64 | L27: 96.824 | M27: 53.43 | N27: =L27*M27 -> 5173.3063
B28: =SUM(B3:B27) -> 135000 | C28: =AVERAGE(C3:C27) -> 48.63515 | F28: =SUM(F3:F27) -> 4.49744e+08
K29: =AVERAGE(K3:K27) -> 52.6916
J30: =SUM(J3:J27) -> 177000 | N30: =SUM(N3:N27) -> 179106.68
A34: Franklin india bluechip fund
C35: nav | D35: units | E35: cur.Nav | F35: cur.Value
A36: 43237 | B36: 5000 | C36: 465.2674 | D36: 10.747 | E36: 472.5081 | F36: =D36*E36 -> 5078.0446
A37: 43238 | B37: 5000 | C37: 460.6376 | D37: 10.855 | E37: 472.5081 | F37: =D37*E37 -> 5129.0754
A38: 43241 | B38: 5000 | C38: 456.3792 | D38: 10.956 | E38: 472.5081 | F38: =D38*E38 -> 5176.7987

Sheet Diversified
A1: Motilal Oswal Most Focused multicap 35 Fund | L1: L&T India Special Situations Fund
C2: nav | D2: units | E2: cur.Nav | F2: cur.Value | N2: nav | O2: units | P2: cur.Nav | Q2: cur.Value
A3: 42936 | B3: 119023 | C3: 25.5291 | D3: 4662.271 | E3: 27.8889 | F3: =D3*E3 -> 130025.61 | L3: 42940 | M3: 72901.15 | N3: 48.142 | O3: 1514.295 | P3: 51.69 | Q3: =O3*P3 -> 78273.909
A4: 42940 | B4: 99559.86 | C4: 25.4474 | D4: 3912.378 | E4: 27.8889 | F4: =D4*E4 -> 109111.92 | L4: 42958 | M4: 12226.96 | N4: 46.175 | O4: 264.796 | P4: 51.69 | Q4: =O4*P4 -> 13687.305
A5: 42958 | B5: 4312.43 | C5: 25.6902 | D5: 167.863 | E5: 27.8889 | F5: =D5*E5 -> 4681.5144 | L5: 42999 | M5: 12942.69 | N5: 49.592 | O5: 260.983 | P5: 51.69 | Q5: =O5*P5 -> 13490.211
A6: 42999 | B6: 4502.58 | C6: 27.3059 | D6: 164.894 | E6: 27.8889 | F6: =D6*E6 -> 4598.7123 | L6: 43019 | M6: 12234.24 | N6: 48.848 | O6: 250.455 | P6: 51.69 | Q6: =O6*P6 -> 12946.019
A7: 43031 | B7: 17943.77 | C7: 26.9007 | D7: 667.037 | E7: 27.8889 | F7: =D7*E7 -> 18602.928 | L7: 43031 | M7: 38429.78 | N7: 50.03 | O7: 768.135 | P7: 51.69 | Q7: =O7*P7 -> 39704.898
A8: 43069 | B8: 10000 | C8: 27.14 | D8: 368.46 | E8: 27.8889 | F8: =D8*E8 -> 10275.944 | L8: 43069 | M8: 10000 | N8: 51.31 | O8: 194.894 | P8: 51.69 | Q8: =O8*P8 -> 10074.071
A9: 43081 | B9: 5000 | C9: 27.4795 | D9: 181.954 | E9: 27.8889 | F9: =D9*E9 -> 5074.4969 | L9: 43081 | M9: 4000 | N9: 51.075 | O9: 78.316 | P9: 51.69 | Q9: =O9*P9 -> 4048.154
A10: 43130 | B10: 5000 | C10: 28.3192 | D10: 176.559 | E10: 27.8889 | F10: =D10*E10 -> 4924.0363 | L10: 43125 | M10: 10000 | N10: 54.466 | O10: 183.601 | P10: 51.69 | Q10: =O10*P10 -> 9490.3357
C11: =AVERAGE(C3:C10) -> 26.7265 | L11: 43130 | M11: 5000 | N11: 53.779 | O11: 92.973 | P11: 51.69 | Q11: =O11*P11 -> 4805.7744
L12: 43133 | M12: 10000 | N12: 51.765 | O12: 193.181 | P12: 51.69 | Q12: =O12*P12 -> 9985.5259
B13: =SUM(B3:B10) -> 265341.64 | D13: =SUM(D3:D10) -> 10301.416 | F13: =SUM(F3:F10) -> 287295.16 | L13: 43136 | M13: 5000 | N13: 51.74 | O13: 96.637 | P13: 51.69 | Q13: =O13*P13 -> 4995.1665
N14: =AVERAGE(N3:N13) -> 50.629273
M15: =SUM(M3:M13) -> 192734.82 | O15: =SUM(O3:O14) -> 3898.266 | Q15: =SUM(Q3:Q13) -> 201501.37
A18: Edelweiss liquid | I18: Motilal Oswal liquid | Q18: canara robecco
A20: 45342 | C20: 190000 | I20: 45343 | K20: 190000 | Q20: 45343 | S20: 10000
A21: 45345 | C21: 200000 | I21: 45350 | K21: 200000 | Q21: 45344 | S21: 200000
A22: 45348 | C22: 200000 | I22: 45357 | K22: 200000 | Q22: 45349 | S22: 200000
A23: 45351 | C23: 200000 | I23: 45365 | K23: 200000 | Q23: 45365 | S23: 200000
A24: 45356 | C24: 200000

Sheet 2019-20
A1: Sundaram Select mid-cap | I1: Mirae Asset India Equity Fund | Q1: Quantum Long Term Equity | Y1: Aditya birla frontline equity fund
B2: Invest | C2: nav | D2: units | E2: cur.Nav | F2: cur.Value | K2: nav | L2: units | M2: cur.Nav | N2: cur.Value | S2: nav | T2: units | U2: cur.Nav | V2: cur.Value | AA2: nav | AB2: units | AC2: cur.Nav | AD2: cur.Value
A3: 43039 | B3: 24886.99 | C3: 520.2144 | D3: 47.84 | E3: 475.0881 | F3: =D3*E3 -> 22728.215 | I3: 42965 | J3: 5000 | K3: 45.815 | L3: 109.135 | M3: 54.615 | N3: =L3*M3 -> 5960.408 | O3: =N3-J3 -> 960.40803 | Q3: 42897 | R3: 1000 | S3: 53.73 | T3: 18.612 | U3: 53.43 | V3: =T3*U3 -> 994.43916 | Y3: 14/11/2017 | Z3: 66775.47 | AA3: 224.39 | AB3: 297.588 | AC3: 237.62 | AD3: =AB3*AC3 -> 70712.861
A4: 43066 | B4: 2000 | C4: 538.77 | D4: 3.712 | E4: 475.0881 | F4: =D4*E4 -> 1763.527 | I4: 42999 | J4: 10000 | K4: 47.745 | L4: 209.446 | M4: 54.615 | N4: =L4*M4 -> 11438.893 | O4: =N4-J4 -> 1438.8933 | Q4: 42958 | R4: 5000 | S4: 52.62 | T4: 95.021 | U4: 53.43 | V4: =T4*U4 -> 5076.972 | Y4: 30/11/2017 | Z4: 10000 | AA4: 225.24 | AB4: 44.397 | AC4: 237.62 | AD4: =AB4*AC4 -> 10549.615
A5: 43069 | B5: 5000 | C5: 538.0955 | D5: 9.292 | E5: 475.0881 | F5: =D5*E5 -> 4414.5186 | I5: 43000 | J5: 10000 | K5: 46.712 | L5: 214.078 | M5: 54.615 | N5: =L5*M5 -> 11691.87 | O5: =N5-J5 -> 1691.87 | Q5: 43052 | R5: 5000 | S5: 52.56 | T5: 95.129 | U5: 53.43 | V5: =T5*U5 -> 5082.7425 | Y5: 42898 | Z5: 3000 | AA5: 221.02 | AB5: 13.573 | AC5: 237.62 | AD5: =AB5*AC5 -> 3225.2163
A6: 43096 | B6: 64428 | C6: 557.3003 | D6: 115.607 | E6: 475.0881 | F6: =D6*E6 -> 54923.51 | I6: 43003 | J6: 5000 | K6: 46.155 | L6: 108.331 | M6: 54.615 | N6: =L6*M6 -> 5916.4976 | O6: =N6-J6 -> 916.49757 | Q6: 43054 | R6: 5000 | S6: 52.11 | T6: 95.951 | U6: 53.43 | V6: =T6*U6 -> 5126.6619 | Y6: 43081 | Z6: 5000 | AA6: 225.65 | AB6: 22.158 | AC6: 237.62 | AD6: =AB6*AC6 -> 5265.184
A7: 43125 | B7: 10000 | C7: 553.9582 | D7: 18.052 | E7: 475.0881 | F7: =D7*E7 -> 8576.2904 | I7: 43047 | J7: 5000 | K7: 48.656 | L7: 102.762 | M7: 54.615 | N7: =L7*M7 -> 5612.3466 | O7: =N7-J7 -> 612.34663 | Q7: 43066 | R7: 5000 | S7: 53.34 | T7: 93.738 | U7: 53.43 | V7: =T7*U7 -> 5008.4213 | Y7: 43374 | Z7: 10000 | AA7: 235.12 | AB7: 42.531 | AC7: 237.62 | AD7: =AB7*AC7 -> 10106.216
A8: 43133 | B8: 10000 | C8: 525.7504 | D8: 19.02 | E8: 475.0881 | F8: =D8*E8 -> 9036.1757 | I8: 43054 | J8: 5000 | K8: 47.968 | L8: 104.236 | M8: 54.615 | N8: =L8*M8 -> 5692.8491 | O8: =N8-J8 -> 692.84914 | Q8: 43073 | R8: 10000 | S8: 52.21 | T8: 191.534 | U8: 53.43 | V8: =T8*U8 -> 10233.662 | Y8: 25/01/2018 | Z8: 10000 | AA8: 239.29 | AB8: 41.79 | AC8: 237.62 | AD8: =AB8*AC8 -> 9930.1398
A9: 43153 | B9: 3000 | C9: 519.5599 | D9: 5.774 | E9: 475.0881 | F9: =D9*E9 -> 2743.1587 | I9: 43066 | J9: 5000 | K9: 49.541 | L9: 100.927 | M9: 54.615 | N9: =L9*M9 -> 5512.1281 | O9: =N9-J9 -> 512.12811 | Q9: 43075 | R9: 3000 | S9: 51.62 | T9: 58.117 | U9: 53.43 | V9: =T9*U9 -> 3105.1913 | Y9: 43133 | Z9: 10000 | AA9: 231.43 | AB9: 43.21 | AC9: 237.62 | AD9: =AB9*AC9 -> 10267.56
A10: 43164 | B10: 5000 | C10: 524.7461 | D10: 9.528 | E10: 475.0881 | F10: =D10*E10 -> 4526.6394 | I10: 43073 | J10: 10000 | K10: 48.295 | L10: 207.061 | M10: 54.615 | N10: =L10*M10 -> 11308.637 | O10: =N10-J10 -> 1308.6365 | Q10: 43081 | R10: 10000 | S10: 52.37 | T10: 190.949 | U10: 53.43 | V10: =T10*U10 -> 10202.405 | Y10: 43222 | Z10: 10000 | AA10: 230.24 | AB10: 43.433 | AC10: 237.62 | AD10: =AB10*AC10 -> 10320.549
A11: 43182 | B11: 5000 | C11: 503.2336 | D11: 9.9357 | E11: 475.0881 | F11: =D11*E11 -> 4720.3328 | I11: 43075 | J11: 2000 | K11: 47.859 | L11: 41.789 | M11: 54.615 | N11: =L11*M11 -> 2282.3062 | O11: =N11-J11 -> 282.30624 | Q11: 43110 | R11: 10000 | S11: 54.5 | T11: 183.486 | U11: 53.43 | V11: =T11*U11 -> 9803.657 | Y11: 43153 | Z11: 3000 | AA11: 223.47 | AB11: 13.425 | AC11: 237.62 | AD11: =AB11*AC11 -> 3190.0485
A12: 43224 | B12: 10000 | C12: 538.9554 | D12: 19.468 | E12: 475.0881 | F12: =D12*E12 -> 9249.0151 | I12: 43081 | J12: 10000 | K12: 48.975 | L12: 204.186 | M12: 54.615 | N12: =L12*M12 -> 11151.618 | O12: =N12-J12 -> 1151.6184 | Q12: 43129 | R12: 10000 | S12: 55.83 | T12: 179.115 | U12: 53.43 | V12: =T12*U12 -> 9570.1145 | Y12: 43162 | Z12: 5000 | AA12: 223.27 | AB12: 22.394 | AC12: 237.62 | AD12: =AB12*AC12 -> 5321.2623
A13: 43256 | B13: 5000 | C13: 508.8307 | D13: 9.826 | E13: 475.0881 | F13: =D13*E13 -> 4668.2157 | I13: 43110 | J13: 10000 | K13: 51.021 | L13: 195.998 | M13: 54.615 | N13: =L13*M13 -> 10704.431 | O13: =N13-J13 -> 704.43077 | Q13: 43130 | R13: 5000 | S13: 55.59 | T13: 89.944 | U13: 53.43 | V13: =T13*U13 -> 4805.7079 | Y13: 43167 | Z13: 10000 | AA13: 220.81 | AB13: 45.287 | AC13: 237.62 | AD13: =AB13*AC13 -> 10761.097
A14: 43278 | B14: 10000 | C14: 497.2493 | D14: 20.111 | E14: 475.0881 | F14: =D14*E14 -> 9554.4968 | I14: 43129 | J14: 10000 | K14: 52.433 | L14: 190.72 | M14: 54.615 | N14: =L14*M14 -> 10416.173 | O14: =N14-J14 -> 416.1728 | Q14: 43136 | R14: 20000 | S14: 53.56 | T14: 373.413 | U14: 53.43 | V14: =T14*U14 -> 19951.457 | AB14: =SUM(AB3:AB13) -> 629.786
I15: 43130 | J15: 5000 | K15: 52.072 | L15: 96.021 | M15: 54.615 | N15: =L15*M15 -> 5244.1869 | O15: =N15-J15 -> 244.18692 | Q15: 43136 | R15: 10000 | S15: 53.56 | T15: 186.706 | U15: 53.43 | V15: =T15*U15 -> 9975.7016
C16: =SUM(C3:C15) -> 6326.6638 | I16: 43136 | J16: 10000 | K16: 49.738 | L16: 201.054 | M16: 54.615 | N16: =L16*M16 -> 10980.564 | O16: =N16-J16 -> 980.56421 | Q16: 43153 | R16: 3000 | S16: 52.47 | T16: 57.176 | U16: 53.43 | V16: =T16*U16 -> 3054.9137
B17: =SUM(B3:B14) -> 154314.99 | D17: =SUM(D3:D14) -> 288.1657 | F17: =SUM(F3:F14) -> 136904.09 | I17: 43136 | J17: 10000 | K17: 49.738 | L17: 201.054 | M17: 54.615 | N17: =L17*M17 -> 10980.564 | O17: =N17-J17 -> 980.56421 | Q17: 43158 | R17: 10000 | S17: 53.09 | T17: 188.3594 | U17: 53.43 | V17: =T17*U17 -> 10064.043 | Z17: =Z10+Z13 -> 20000 | AA17: =(AA10+AA13)/2 -> 225.525 | AB17: =AB10+AB13 -> 88.72
I18: 43153 | J18: 3000 | K18: 48.331 | L18: 62.072 | M18: 54.615 | N18: =L18*M18 -> 3390.0623 | O18: =N18-J18 -> 390.06228 | Q18: 43159 | R18: 5000 | S18: 52.98 | T18: 94.37 | U18: 53.43 | V18: =T18*U18 -> 5042.1891 | AA18: =AA17*AB17 -> 20008.578
A19: Motilal Oswal Most Focused multicap 35 Fund | I19: 43162 | J19: 5000 | K19: 48.34 | L19: 103.434 | M19: 54.615 | N19: =L19*M19 -> 5649.0479 | O19: =N19-J19 -> 649.04791 | Q19: 43162 | R19: 5000 | S19: 52.25 | T19: 95.694 | U19: 53.43 | V19: =T19*U19 -> 5112.9304
B20: Invest | C20: nav | D20: units | E20: cur.Nav | F20: cur.Value | I20: 43182 | J20: 5000 | K20: 46.956 | L20: 106.483 | M20: 54.615 | N20: =L20*M20 -> 5815.569 | O20: =N20-J20 -> 815.56905 | Q20: 43167 | R20: 10000 | S20: 51.71 | T20: 193.386 | U20: 53.43 | V20: =T20*U20 -> 10332.614
A21: 42936 | B21: 119023 | C21: 25.5291 | D21: 4662.271 | E21: 27.8889 | F21: =D21*E21 -> 130025.61 | I21: 43241 | J21: 5000 | K21: 47.91 | L21: 104.362 | M21: 54.615 | N21: =L21*M21 -> 5699.7306 | O21: =N21-J21 -> 699.73063 | Q21: 43178 | R21: 10000 | S21: 50.99 | T21: 196.117 | U21: 53.43 | V21: =T21*U21 -> 10478.531
A22: 42940 | B22: 99559.86 | C22: 25.4474 | D22: 3912.378 | E22: 27.8889 | F22: =D22*E22 -> 109111.92 | I22: 43256 | J22: 5000 | K22: 48.443 | L22: 103.214 | M22: 54.615 | N22: =L22*M22 -> 5637.0326 | O22: =N22-J22 -> 637.03261 | Q22: 43182 | R22: 5000 | S22: 50.74 | T22: 98.542 | U22: 53.43 | V22: =T22*U22 -> 5265.0991
A23: 42958 | B23: 4312.43 | C23: 25.6902 | D23: 167.863 | E23: 27.8889 | F23: =D23*E23 -> 4681.5144 | Q23: 43237 | R23: 10000 | S23: 52.62 | T23: 190.042 | U23: 53.43 | V23: =T23*U23 -> 10153.944
A24: 42999 | B24: 4502.58 | C24: 27.3059 | D24: 164.894 | E24: 27.8889 | F24: =D24*E24 -> 4598.7123 | Q24: 43240 | R24: 5000 | S24: 51.67 | T24: 96.768 | U24: 53.43 | V24: =T24*U24 -> 5170.3142
A25: 43031 | B25: 17943.77 | C25: 26.9007 | D25: 667.037 | E25: 27.8889 | F25: =D25*E25 -> 18602.928 | Q25: 43241 | R25: 5000 | S25: 51.67 | T25: 96.768 | U25: 53.43 | V25: =T25*U25 -> 5170.3142
A26: 43069 | B26: 10000 | C26: 27.14 | D26: 368.46 | E26: 27.8889 | F26: =D26*E26 -> 10275.944 | Q26: 43256 | R26: 5000 | S26: 51.86 | T26: 96.413 | U26: 53.43 | V26: =T26*U26 -> 5151.3466
A27: 43081 | B27: 5000 | C27: 27.4795 | D27: 181.954 | E27: 27.8889 | F27: =D27*E27 -> 5074.4969 | Q27: 43279 | R27: 5000 | S27: 51.64 | T27: 96.824 | U27: 53.43 | V27: =T27*U27 -> 5173.3063
A28: 43130 | B28: 5000 | C28: 28.3192 | D28: 176.559 | E28: 27.8889 | F28: =D28*E28 -> 4924.0363 | J28: =SUM(J3:J27) -> 135000 | K28: =AVERAGE(K3:K27) -> 48.63515 | N28: =SUM(N3:N27) -> 151084.92
C29: =AVERAGE(C21:C28) -> 26.7265 | S29: =AVERAGE(S3:S27) -> 52.6916
R30: =SUM(R3:R27) -> 177000 | V30: =SUM(V3:V27) -> 179106.68
B31: =SUM(B21:B28) -> 265341.64 | D31: =SUM(D21:D28) -> 10301.416 | F31: =SUM(F21:F28) -> 287295.16
A34: Franklin india bluechip fund
B35: Invest | C35: nav | D35: units | E35: cur.Nav | F35: cur.Value
A36: 43237 | B36: 5000 | C36: 465.2674 | D36: 10.747 | E36: 472.5081 | F36: =D36*E36 -> 5078.0446
A37: 43238 | B37: 5000 | C37: 460.6376 | D37: 10.855 | E37: 472.5081 | F37: =D37*E37 -> 5129.0754
A38: 43241 | B38: 5000 | C38: 456.3792 | D38: 10.956 | E38: 472.5081 | F38: =D38*E38 -> 5176.7987
A43: ICICI Prudential Liquid Fund
B44: Invest | C44: nav | D44: units | E44: cur.Nav | F44: cur.Value
A45: 43534 | B45: 200000 | C45: 285.8594 | D45: 699.645 | E45: 291.4046 | F45: =E45*D45 -> 203879.77
A46: 43626 | B46: 100000 | C46: 286.0093 | D46: 349.639 | E46: 291.4046 | F46: =E46*D46 -> 101886.41

Sheet Networth
A1: 29135 | C1: EPS | D1: -113841 | X1: ppf | Y1: sahana
A2: 29501 | F2: =SUM(D29) -> 30447182 | J2: 40360 | K2: 541 | W2: 2012-13 | X2: 1
A3: 29866 | C3: pf int | F3: 1040000 | J3: 40391 | K3: 541 | M3: 100000 | N3: FD001577 | O3: 44520 | P3: 46346 | Q3: 0.1 | R3: =(M3*Q3)/12 -> 833.33333 | W3: 2013-14 | X3: 2 | Y3: LKG
A4: 30231 | C4: gratuity | F4: 1070806 | J4: 40422 | K4: 541 | M4: 100000 | N4: FD001576 | O4: 44517 | P4: 46343 | Q4: 0.1 | R4: =(M4*Q4)/12 -> 833.33333 | W4: 2014-15 | X4: 3 | Y4: UKG
A5: 30596 | C5: ppf | D5: 2761925 | E5: =D5*0.071 -> 196096.67 | J5: 40452 | K5: 541 | M5: 100000 | N5: FD001578 | O5: 44521 | P5: 46347 | Q5: 0.1 | R5: =(M5*Q5)/12 -> 833.33333 | W5: 2015-16 | X5: 4 | Y5: 1
A6: 30962 | C6: PF | D6: 3957500 | J6: 40483 | K6: 541 | M6: 100000 | N6: FD001579 | O6: 44523 | P6: 46349 | Q6: 0.1 | R6: =(M6*Q6)/12 -> 833.33333 | W6: 2016-17 | X6: 5 | Y6: 2
A7: 31327 | C7: VPF | D7: 552684 | J7: 40513 | K7: 541 | M7: 60000 | N7: FD001654 | O7: 44664 | P7: 46489 | Q7: 0.1 | R7: =(M7*Q7)/12 -> 500 | W7: 2017-18 | X7: 6 | Y7: 3
A8: 31692 | C8: unnati | D8: 1030000 | J8: 40544 | K8: 541 | M8: 60000 | N8: FD001652 | O8: 44664 | P8: 46489 | Q8: 0.1 | R8: =(M8*Q8)/12 -> 500 | W8: 2018-19 | X8: 7 | Y8: 4
A9: 32057 | C9: MF-debt | D9: 104503 | J9: 40575 | K9: 541 | M9: 60000 | N9: FD001651 | O9: 44664 | P9: 46489 | Q9: 0.1 | R9: =(M9*Q9)/12 -> 500 | W9: 2019-20 | X9: 8 | Y9: 5
A10: 32423 | C10: MF-cash | D10: 17881536 | J10: 40603 | K10: 541 | M10: 30000 | N10: FD001650 | O10: 44664 | P10: 46489 | Q10: 0.1 | R10: =(M10*Q10)/12 -> 250 | W10: 2020-21 | X10: 9 | Y10: 6
A11: 32788 | C11: MF-eq | D11: 927683 | J11: 40634 | K11: 541 | M11: 60000 | N11: FD001660 | O11: 44672 | P11: 46498 | Q11: 0.1 | R11: =(M11*Q11)/12 -> 500 | W11: 2021-22 | X11: 10 | Y11: 7
A12: 33153 | C12: axis | D12: 105298 | J12: 40664 | K12: 541 | M12: 60000 | N12: FD001661 | O12: 44672 | P12: 46498 | Q12: 0.1 | R12: =(M12*Q12)/12 -> 500 | W12: 2022-23 | X12: 11 | Y12: 8
A13: 33518 | C13: nirCanara | D13: 154340 | J13: 40695 | K13: 541 | M13: 60000 | N13: FD001662 | O13: 44672 | P13: 46498 | Q13: 0.1 | R13: =(M13*Q13)/12 -> 500 | W13: 2023-24 | X13: 12 | Y13: 9
A14: 33884 | C14: citizen | D14: 24000 | J14: 40725 | K14: 541 | M14: 60000 | N14: FD001689 | O14: 44717 | P14: 46572 | Q14: 0.1 | R14: =(M14*Q14)/12 -> 500 | W14: 2024-25 | X14: 13 | Y14: 10
A15: 34249 | C15: nirSBI | D15: 32470 | J15: 40756 | K15: 541 | M15: 30000 | N15: FD001709 | O15: 44766 | P15: 46591 | Q15: 0.1 | R15: =(M15*Q15)/12 -> 250 | W15: 2025-26 | X15: 14 | Y15: 11
A16: 34614 | C16: Shares | D16: 2500000 | J16: 40787 | K16: 541 | M16: 60000 | N16: FD001727 | O16: 44785 | P16: 46611 | Q16: 0.1 | R16: =(M16*Q16)/12 -> 500 | W16: 2026-27 | X16: 15 | Y16: 12
A17: 34979 | C17: Mom | D17: -1733.71 | J17: 40817 | K17: 541 | M17: 90000 | N17: FD001917 | O17: 45330 | P17: 47156 | Q17: =10/100 -> 0.1 | R17: =(M17*Q17)/12 -> 750 | W17: 2027-28 | X17: 16 | Y17: 13
A18: 35345 | C18: advance | D18: -340000 | J18: 40848 | K18: 541 | W18: 2028-29 | X18: 17 | Y18: 14
A19: 35710 | C19: lathaFD | D19: 550000 | J19: 40878 | K19: 541 | M19: =SUM(M1:M17) -> 1030000 | R19: =SUM(R1:R17) -> 8583.3333 | W19: 2029-30 | X19: 18 | Y19: 15
A20: 36075 | C20: lataCiti | D20: 0 | J20: 40909 | K20: 541 | W20: 2030-31 | X20: 19 | Y20: 16
A21: 36440 | C21: cc1 | D21: -51023 | J21: 40940 | K21: 541 | W21: 2031-32
A22: 36806 | D22: 48000 | J22: 40969 | K22: 541 | O22: 45702 | W22: 2032-33
A23: 37171 | C23: may | D23: 210000 | J23: 41000 | K23: 541 | O23: 444 | W23: 2033-34
A24: 37536 | J24: 41030 | K24: 541 | O24: =SUM(O22:O23) -> 46146 | W24: 2034-35
A25: 37901 | J25: 41061 | K25: 541
A26: 38267 | J26: 41091 | K26: 541
A27: 38632 | J27: 41122 | K27: 541
A28: 38997 | J28: 41153 | K28: 541
A29: 39362 | D29: =SUM(D2:D28) -> 30447182 | F29: =SUM(F2:F26) -> 32557988 | J29: 41183 | K29: 541
A30: 39728 | F30: 2915380 | J30: 41214 | K30: 541
A31: 40093 | F31: =SUM(F29:F30) -> 35473368 | J31: 41244 | K31: 541
A32: 40458 | J32: 41275 | K32: 541 | M32: Latha | S32: 46113 | T32: 46143 | U32: 46174 | V32: 46204 | W32: 46235 | X32: 46266 | Y32: 46296 | Z32: 46327 | AA32: 46357 | AB32: 46388 | AC32: 46419 | AD32: 46447 | AE32: 46478 | AF32: 46508 | AG32: 46539 | AH32: 46569 | AI32: 46600 | AJ32: 46631 | AK32: 46661 | AL32: 46692 | AM32: 46722 | AN32: 46753 | AO32: 46784 | AP32: 46813 | AQ32: 46844 | AR32: 46874 | AS32: 46905 | AT32: 46935 | AU32: 46966 | AV32: 46997
A33: 40823 | J33: 41306 | K33: 541 | M33: 200000 | N33: 120374 | O33: 46053 | P33: 46783 | Q33: 0.08 | R33: =(M33*Q33)/12 -> 1333.3333 | S33: 1333 | T33: 1333 | U33: 1333 | V33: 1333 | W33: 1333 | X33: 1333 | Y33: 1333 | Z33: 1333 | AA33: 1333 | AB33: 1333 | AC33: 1333 | AD33: 1333 | AE33: 1333 | AF33: 1333 | AG33: 1333 | AH33: 1333 | AI33: 1333 | AJ33: 1333 | AK33: 1333 | AL33: 1333 | AM33: 1333 | AN33: 1333
A34: 41189 | J34: 41334 | K34: 541 | M34: 100000 | N34: 120381 | O34: 46055 | P34: 46783 | Q34: 0.08 | R34: =(M34*Q34)/12 -> 666.66667 | S34: 667 | T34: 667 | U34: 667 | V34: 667 | W34: 667 | X34: 667 | Y34: 667 | Z34: 667 | AA34: 667 | AB34: 667 | AC34: 667 | AD34: 667 | AE34: 667 | AF34: 667 | AG34: 667 | AH34: 667 | AI34: 667 | AJ34: 667 | AK34: 667 | AL34: 667 | AM34: 667 | AN34: 667 | AO34: 667
A35: 41554 | J35: 41365 | K35: 541 | M35: 50000 | N35: 120391 | O35: 46065 | P35: 46795 | Q35: 0.08 | R35: =(M35*Q35)/12 -> 333.33333 | S35: 333 | T35: 333 | U35: 333 | V35: 333 | W35: 333 | X35: 333 | Y35: 333 | Z35: 333 | AA35: 333 | AB35: 333 | AC35: 333 | AD35: 333 | AE35: 333 | AF35: 333 | AG35: 333 | AH35: 333 | AI35: 333 | AJ35: 333 | AK35: 333 | AL35: 333 | AM35: 333 | AN35: 333 | AO35: 333
A36: 41919 | J36: 41395 | K36: 541 | M36: 50000 | N36: 120431 | O36: 46093 | P36: 46824 | Q36: 0.0055555556 | R36: 333.3333 | S36: 333 | T36: 333 | U36: 333 | V36: 333 | W36: 333 | X36: 333 | Y36: 333 | Z36: 333 | AA36: 333 | AB36: 333 | AC36: 333 | AD36: 333 | AE36: 333 | AF36: 333 | AG36: 333 | AH36: 333 | AI36: 333 | AJ36: 333 | AK36: 333 | AL36: 333 | AM36: 333 | AN36: 333 | AO36: 333 | AP36: 333
A37: 42284 | J37: 41426 | K37: 541 | M37: 50000 | N37: 120475 | O37: 46125 | P37: 46856 | Q37: 0.0055555556 | R37: 333.3333 | T37: 333 | U37: 333 | V37: 333 | W37: 333 | X37: 333 | Y37: 333 | Z37: 333 | AA37: 333 | AB37: 333 | AC37: 333 | AD37: 333 | AE37: 333 | AF37: 333 | AG37: 333 | AH37: 333 | AI37: 333 | AJ37: 333 | AK37: 333 | AL37: 333 | AM37: 333 | AN37: 333 | AO37: 333 | AP37: 333 | AQ37: 333
A38: 42650 | J38: 41456 | K38: 541 | M38: 50000 | N38: 120492 | O38: 46133 | P38: 46864 | Q38: 0.0055555556 | T38: 333 | U38: 333 | V38: 333 | W38: 333 | X38: 333 | Y38: 333 | Z38: 333 | AA38: 333 | AB38: 333 | AC38: 333 | AD38: 333 | AE38: 333 | AF38: 333 | AG38: 333 | AH38: 333 | AI38: 333 | AJ38: 333 | AK38: 333 | AL38: 333 | AM38: 333 | AN38: 333 | AO38: 333 | AP38: 333 | AQ38: 333
A39: 43015 | J39: 41487 | K39: 541 | M39: 50000 | N39: 120499 | O39: 46136 | P39: 46867 | Q39: 0.0055555556 | T39: 333 | U39: 333 | V39: 333 | W39: 333 | X39: 333 | Y39: 333 | Z39: 333 | AA39: 333 | AB39: 333 | AC39: 333 | AD39: 333 | AE39: 333 | AF39: 333 | AG39: 333 | AH39: 333 | AI39: 333 | AJ39: 333 | AK39: 333 | AL39: 333 | AM39: 333 | AN39: 333 | AO39: 333 | AP39: 333 | AQ39: 333
A40: 43380 | J40: 41518 | K40: 541
A41: 43745 | J41: 41548 | K41: 541
A42: 44111 | J42: 41579 | K42: 541
A43: 44476 | J43: 41609 | K43: 541
A44: 44841 | J44: 41640 | K44: 541
A45: 45206 | J45: 41671 | K45: 541
A46: 45572 | J46: 41699 | K46: 541
A47: 45937 | J47: 41730 | K47: 541
A48: 46302 | J48: 41760 | K48: 541
A49: 46667 | J49: 41791 | K49: 541
A50: 47033 | J50: 41821 | K50: 541
A51: 47398 | J51: 41852 | K51: 541
J52: 41883 | K52: 541
J53: 41913 | K53: 1250
J54: 41944 | K54: 1250
J55: 41974 | K55: 1250
J56: 42005 | K56: 1250
J57: 42036 | K57: 1250
J58: 42064 | K58: 1250
J59: 42095 | K59: 1250
J60: 42125 | K60: 1250
J61: 42156 | K61: 1250
J62: 42186 | K62: 1250
J63: 42217 | K63: 1250
... J80: 42736 | K80: 1250
J81: 42767 | K81: 1250 | V81: 209951
J82: 42795 | K82: 1250
J83: 42826 | K83: 1250
J84: 42856 | K84: 1250
J85: 42887 | K85: 1250
J86: 42917 | K86: 1250
J87: 42948 | K87: 1250
J88: 42979 | K88: 1250
J89: 43009 | K89: 1250 | W89: 96960
J90: 43040 | K90: 1250 | W90: 96928
J91: 43070 | K91: 1250 | W91: 98062
J92: 43101 | K92: 1250
J93: 43132 | K93: 1250
J94: 43160 | K94: 1250
J95: 43191 | K95: 1250
J96: 43221 | K96: 1250
J97: 43252 | K97: 1250
J98: 43282 | K98: 1250
J99: 43313 | K99: 1250
J100: 43344 | K100: 1250
J101: 43374 | K101: 1250
J102: 43405 | K102: 1250
J103: 43435 | K103: 1250
... J190: 46082 | K190: 1250
K192: =SUM(K2:K191) -> 200091

Sheet PF-VPF
A1: PF | B1: 2640218 | C1: Including Mar2022 contribution | V1: 40360 | W1: 38333 | X1: 1844 | Z1: 2640218 | AA1: 3631920 | AC1: 8.15
A2: VPF | B2: 512265 | C2: Including Mar2022 contribution | M2: 2432138 | V2: 40391 | W2: 38333 | X2: 1844 | Z2: 512265
A3: Wage Month | B3: PF | C3: compPF | D3: EPS | E3: gratuity | F3: vpf | H3: PF | I3: VPF | S3: Jan | V3: 40422 | W3: 38333 | X3: 1844 | Z3: Wage Month | AA3: PF | AB3: compPF | AC3: vpf | AD3: Balance
A4: 44652 | B4: 9729 | C4: 8479 | D4: 1250 | E4: 3900 | F4: 2619 | H4: =SUM(B1,B4,C4) -> 2658426 | I4: =SUM(B2,F4) -> 514884 | K4: 3.1 | L4: =SUM(B4:C4,E4:F4) -> 24727 | O4: 20827 | Q4: 202679 | S4: feb | V4: 40452 | W4: 38333 | X4: 1844 | Z4: 45017 | AA4: 10701 | AB4: 9451 | AC4: 2880 | AD4: =SUM(AA4:AC4,AA1) -> 3654952 | AE4: =(8.15*AA1)/1200 -> 24666.79
A5: 44682 | B5: 9729 | C5: 8479 | D5: 1250 | E5: 3900 | F5: 2619 | H5: =SUM(H4,B5,C5) -> 2676634 | I5: =SUM(I4,F5) -> 517503 | K5: 3.4 | L5: 143187 | O5: 155992 | Q5: -28980 | S5: mar | T5: carInsur | V5: 40483 | W5: 38333 | X5: 1844 | Z5: 45047 | AA5: 10701 | AB5: 9451 | AC5: 669 | AD5: =SUM(AA5:AC5,AD4) -> 3675773 | AE5: =(8.15*AD4)/1200 -> 24823.216
A6: 44713 | B6: 9729 | C6: 8479 | D6: 1250 | E6: 3900 | F6: 2619 | H6: =SUM(H5,B6,C6) -> 2694842 | I6: =SUM(I5,F6) -> 520122 | K6: 3.7 | L6: 2200 | O6: =SUM(O4:O5) -> 176819 | Q6: =SUM(Q4:Q5) -> 173699 | S6: apr | T6: propTax | U6: Fees | V6: 40513 | W6: 38333 | X6: 1844 | Z6: 45078 | AA6: 10701 | AB6: 9451 | AC6: 669 | AD6: =SUM(AA6:AC6,AD5) -> 3696594 | AE6: =(8.15*AD5)/1200 -> 24964.625
A7: 44743 | B7: 9729 | C7: 8479 | D7: 1250 | E7: 3900 | F7: 2619 | H7: =SUM(H6,B7,C7) -> 2713050 | I7: =SUM(I6,F7) -> 522741 | L7: =SUM(L4:L6) -> 170114 | O7: =2600000/O6 -> 14.704302 | S7: May | T7: Dress | U7: books | V7: 40544 | W7: 38333 | X7: 1844 | Z7: 45108 | AA7: 10701 | AB7: 9451 | AC7: 669 | AD7: =SUM(AA7:AC7,AD6) -> 3717415 | AE7: =(8.15*AD6)/1200 -> 25106.034
A8: 44774 | B8: 9729 | C8: 8479 | D8: 1250 | E8: 3900 | F8: 2619 | H8: =SUM(H7,B8,C8) -> 2731258 | I8: =SUM(I7,F8) -> 525360 | L8: 16500 | S8: June | V8: 40575 | W8: 38333 | X8: 1844 | Z8: 45139 | AA8: 10701 | AB8: 9451 | AC8: 669 | AD8: =SUM(AA8:AC8,AD7) -> 3738236 | AE8: =(8.15*AD7)/1200 -> 25247.444
A9: 44805 | B9: 9729 | C9: 8479 | D9: 1250 | E9: 3900 | F9: 2619 | H9: =SUM(H8,B9,C9) -> 2749466 | I9: =SUM(I8,F9) -> 527979 | L9: =SUM(L7:L8) -> 186614 | M9: =L9*12 -> 2239368 | S9: july | T9: tax | V9: 40603 | W9: 38333 | X9: 1844 | Z9: 45170 | AA9: 10701 | AB9: 9451 | AC9: 669 | AD9: =SUM(AA9:AC9,AD8) -> 3759057 | AE9: =(8.15*AD8)/1200 -> 25388.853
A10: 44835 | B10: 9729 | C10: 8479 | D10: 1250 | E10: 3900 | F10: 2619 | H10: =H9+B10+C10 -> 2767674 | I10: =SUM(I9,F10) -> 530598 | P10: =SUM(P11:P20) -> 172450 | S10: aug | V10: 40634 | W10: 38333 | X10: 1844 | Z10: 45200 | AA10: 10701 | AB10: 9451 | AC10: 669 | AD10: =SUM(AA10:AC10,AD9) -> 3779878 | AE10: =(8.15*AD9)/1200 -> 25530.262
A11: 44866 | B11: 9729 | C11: 8479 | D11: 1250 | E11: 3900 | F11: 2619 | H11: =SUM(H10,B11,C11) -> 2785882 | I11: =SUM(I10,F11) -> 533217 | N11: Nir | O11: latha | P11: 145523 | S11: Sep | V11: 40664 | W11: 38333 | X11: 1844 | Z11: 45231 | AA11: 10701 | AB11: 9451 | AC11: 669 | AD11: =SUM(AA11:AC11,AD10) -> 3800699 | AE11: =(8.15*AD10)/1200 -> 25671.671
A12: 44896 | B12: 9729 | C12: 8479 | D12: 1250 | E12: 3900 | F12: 2619 | H12: =SUM(H11,B12,C12) -> 2804090 | I12: =SUM(I11,F12) -> 535836 | M12: axis | P12: 9729 | S12: Oct | T12: Fees | U12: lic | V12: 40695 | W12: 38333 | X12: 1844 | Z12: 45261 | AA12: 10701 | AB12: 9451 | AC12: 669 | AD12: =SUM(AA12:AC12,AD11) -> 3821520 | AE12: =(8.15*AD11)/1200 -> 25813.081
A13: 44927 | B13: 10701 | C13: 9451 | D13: 1250 | E13: 4289 | F13: 2880 | H13: =SUM(H12,B13,C13) -> 2824242 | I13: =SUM(I12,F13) -> 538716 | M13: 45839 | N13: 2473 | P13: 2619 | S13: Nov | V13: 40725 | W13: 38333 | X13: 1844 | Z13: 45292 | AA13: 10701 | AB13: 9451 | AC13: 669 | AD13: =SUM(AA13:AC13,AD12) -> 3842341 | AE13: =(8.15*AD12)/1200 -> 25954.49
A14: 44958 | B14: 10701 | C14: 9451 | D14: 1250 | E14: 4289 | F14: 2880 | H14: =SUM(H13,B14,C14) -> 2844394 | I14: =SUM(I13,F14) -> 541596 | M14: 45931 | N14: 2828 | P14: 9729 | S14: Dec | V14: 40756 | W14: 38333 | X14: 1844 | Z14: 45323 | AA14: 11665 | AB14: 10415 | AC14: 729 | AD14: =SUM(AA14:AC14,AD13) -> 3865150 | AE14: =(8.15*AD13)/1200 -> 26095.899
A15: Int | H15: 245930 | M15: 46023 | N15: 2275 | P15: -1250 | V15: 40787 | W15: 38333 | X15: 1844 | Z15: 45352 | AA15: 11665 | AB15: 10415 | AC15: 729 | AD15: =SUM(AA15:AC15,AD14) -> 3887959 | AE15: =(8.15*AD14)/1200 -> 26250.81
A16: 44986 | B16: 10701 | C16: 9451 | D16: 1250 | E16: 4289 | F16: 2880 | H16: =SUM(H14:H15,B16,C16) -> 3110476 | I16: =SUM(I14,F16) -> 544476 | K16: =20152*12 -> 241824 | M16: 46112 | N16: 2357 | P16: 3900 | V16: 40817 | W16: 38333 | X16: 1844 | AE16: =SUM(AE4:AE15) -> 305513.18
A17: 45017 | B17: 10701 | C17: 9451 | D17: 1250 | E17: 4289 | F17: 669 | H17: =SUM(H16,B17,C17) -> 3130628 | I17: =SUM(I16,F17) -> 545145 | K17: =669*12 -> 8028 | M17: Canara | P17: 2200 | R17: 365 | S17: remaining | V17: 40848 | W17: 38333 | X17: 1844
A18: 45047 | B18: 10701 | C18: 9451 | D18: 1250 | E18: 4289 | F18: 669 | H18: =SUM(H17,B18,C18) -> 3150780 | I18: =SUM(I17,F18) -> 545814 | M18: 45836 | N18: 723 | O18: 1660 | S18: 9 | V18: 40878 | W18: 38333 | X18: 1844 | AD18: 3673696
A19: 45078 | B19: 10701 | C19: 9451 | D19: 1250 | E19: 4289 | F19: 669 | H19: =SUM(H18,B19,C19) -> 3170932 | I19: =SUM(I18,F19) -> 546483 | K19: =10701*2 -> 21402 | M19: 45927 | N19: 297 | O19: 798 | S19: 20 | V19: 40909 | W19: 38333 | X19: 1844 | AD19: 20821
A20: 45108 | B20: 10701 | C20: 9451 | D20: 1250 | E20: 4289 | F20: 669 | H20: =SUM(H19,B20,C20) -> 3191084 | I20: =SUM(I19,F20) -> 547152 | K20: 669 | M20: 46018 | N20: 499 | O20: 254 | V20: 40940 | W20: 42167 | X20: 2028 | AD20: =SUM(AD18:AD19) -> 3694517
A21: 45139 | B21: 10701 | C21: 9451 | D21: 1250 | E21: 4289 | F21: 669 | H21: =SUM(H20,B21,C21) -> 3211236 | I21: =SUM(I20,F21) -> 547821 | K21: =SUM(K19:K20) -> 22071 | N21: 468 | O21: 655 | P21: 162634 | Q21: =P21*2 -> 325268 | R21: =20821*2 -> 41642 | V21: 40969 | W21: 42167 | X21: 2028
A22: 45170 | B22: 10701 | C22: 9451 | D22: 1250 | E22: 4289 | F22: 669 | H22: =SUM(H21,B22,C22) -> 3231388 | I22: =SUM(I21,F22) -> 548490 | K22: -1250 | P22: 20152 | V22: 41000 | W22: 42167 | X22: 2028
A23: 45200 | B23: 10701 | C23: 9451 | D23: 1250 | E23: 4289 | F23: 669 | H23: =SUM(H22,B23,C23) -> 3251540 | I23: =SUM(I22,F23) -> 549159 | K23: =SUM(K21:K22) -> 20821 | M23: Citizen | P23: 669 | V23: 41030 | W23: 42167 | X23: 2028 | Z23: 375912 | AB23: pf | AC23: 266924
A24: 45231 | B24: 10701 | C24: 9451 | D24: 1250 | E24: 4289 | F24: 669 | H24: =SUM(H23,B24,C24) -> 3271692 | I24: =SUM(I23,F24) -> 549828 | M24: 45565 | N24: 674 | P24: 16300 | R24: =29/6 -> 4.8333333 | S24: 155000 | V24: 41061 | W24: 42167 | X24: 2028 | Z24: 16470 | AB24: ppf | AC24: 113051
A25: 45261 | B25: 10701 | C25: 9451 | D25: 1250 | E25: 4289 | F25: 669 | H25: =SUM(H24,B25,C25) -> 3291844 | I25: =SUM(I24,F25) -> 550497 | M25: 45747 | N25: 350 | P25: 2200 | S25: 23032 | V25: 41091 | W25: 42167 | X25: 2028 | Z25: =SUM(Z23:Z24) -> 392382 | AC25: 1806536
A26: 45292 | B26: 11665 | C26: 10415 | D26: 1250 | E26: 4675 | F26: 729 | H26: =SUM(H25,B26,C26) -> 3313924 | I26: =SUM(I25,F26) -> 551226 | M26: SBI | S26: 16300 | V26: 41122 | W26: 42167 | X26: 2028 | Z26: =SUM(AC23:AC24) -> 379975 | AB26: pf | AC26: 119664
A27: 45323 | B27: 11665 | C27: 10415 | D27: 1250 | E27: 4675 | F27: 729 | H27: =SUM(H26,B27,C27) -> 3336004 | I27: =SUM(I26,F27) -> 551955 | K27: =SUM(H27:I27) -> 3887959 | M27: 45468 | N27: 180 | Q27: 81071 | R27: =Q27*0.4 -> 32428.4 | S27: 2200 | V27: 41153 | W27: 42167 | X27: 2028 | Z27: =Z25-Z26 -> 12407 | AC27: 32211
A28: int | H28: 0 | K28: =K27*0.0825 -> 320756.62 | M28: 45560 | N28: 128 | R28: =Q27*0.5 -> 40535.5 | S28: =SUM(S24:S27) -> 196532 | V28: 41183 | W28: 42167 | X28: 2028 | AC28: -15000
A29: 45352 | B29: 11665 | C29: 10415 | D29: 1250 | E29: 4675 | F29: 729 | H29: =SUM(H27,B29,C29) -> 3358084 | I29: =SUM(I27,F29) -> 552684 | M29: 45651 | N29: 712 | V29: 41214 | W29: 42167 | X29: 2028 | AC29: 119664
A30: 45383 | B30: 11665 | C30: 10415 | D30: 1250 | E30: 4675 | F30: 0 | H30: =SUM(H29,B30,C30) -> 3380164 | I30: =SUM(I29,F30) -> 552684 | M30: 45741 | N30: 198 | V30: 41244 | W30: 42167 | X30: 2028 | AC30: =2200*12 -> 26400
A31: 45413 | B31: 11665 | C31: 10415 | D31: 1250 | E31: 4675 | F31: 0 | H31: =SUM(H30,B31,C31) -> 3402244 | I31: =SUM(I30,F31) -> 552684 | N31: =SUM(N13:N16,N18:N21,N24:N25,N27:N30) -> 14162 | Q31: 28979 | R31: =Q31*12 -> 347748 | V31: 41275 | W31: 42167 | X31: 2028 | AC31: =SUM(AC23:AC30) -> 2469450
A32: 45444 | B32: 11665 | C32: 10415 | D32: 1250 | E32: 4675 | F32: 0 | H32: =SUM(H31,B32,C32) -> 3424324 | I32: =SUM(I31,F32) -> 552684 | V32: 41306 | W32: 44275 | X32: 2130
A33: 45474 | B33: 11665 | C33: 10415 | D33: 1250 | E33: 4675 | F33: 0 | H33: =SUM(H32,B33,C33) -> 3446404 | I33: =SUM(I31,F33) -> 552684 | M33: kothari Products | O33: sold on | P33: 45300 | V33: 41334 | W33: 44275 | X33: 2130
A34: 45505 | B34: 11665 | C34: 10415 | D34: 1250 | E34: 4675 | F34: 0 | H34: =SUM(H33,B34,C34) -> 3468484 | I34: =SUM(I33,F34) -> 552684 | V34: 41365 | W34: 44275 | X34: 2130
A35: 45536 | B35: 11665 | C35: 10415 | D35: 1250 | E35: 4675 | F35: 0 | H35: =SUM(H34,B35,C35) -> 3490564 | I35: =SUM(I33,F35) -> 552684 | M35: =SUM(O18:O20) -> 2712 | V35: 41395 | W35: 44275 | X35: 2130
A36: 45566 | B36: 11665 | C36: 10415 | D36: 1250 | E36: 4675 | F36: 0 | H36: =SUM(H35,B36,C36) -> 3512644 | I36: =SUM(I35,F36) -> 552684 | L36: latha | M36: int frm FD | V36: 41426 | W36: 44275 | X36: 2130
A37: 45597 | B37: 11665 | C37: 10415 | D37: 1250 | E37: 4675 | F37: 0 | H37: =SUM(H36,B37,C37) -> 3534724 | I37: =SUM(I36,F37) -> 552684 | L37: 45788 | M37: 884 | V37: 41456 | W37: 44275 | X37: 2130
A38: 45627 | B38: 11665 | C38: 10415 | D38: 1250 | E38: 4675 | F38: 0 | H38: =SUM(H37,B38,C38) -> 3556804 | I38: =SUM(I37,F38) -> 552684 | L38: 45880 | M38: 914 | V38: 41487 | W38: 44275 | X38: 2130
A39: 45658 | B39: 12889 | C39: 11639 | D39: 1250 | E39: 5166 | F39: 0 | H39: =SUM(H38,B39,C39) -> 3581332 | I39: 552684 | L39: 45972 | M39: 914 | V39: 41518 | W39: 44275 | X39: 2130
A40: 45689 | B40: 12889 | C40: 11639 | D40: 1250 | E40: 5166 | F40: 0 | H40: =SUM(H39,B40,C40) -> 3605860 | I40: 552684 | L40: 46051 | M40: 785 | V40: 41548 | W40: 44275 | X40: 2130
A41: 45717 | B41: 12889 | C41: 11639 | D41: 1250 | E41: 5166 | F41: 0 | H41: =SUM(H40,B41,C41) -> 3630388 | I41: 552684 | K41: frm Deepak | L41: 45990 | M41: 40000 | V41: 41579 | W41: 44275 | X41: 2130
A42: 45748 | B42: 12889 | C42: 11639 | D42: 1250 | E42: 5166 | F42: 0 | H42: =SUM(H41,B42,C42) -> 3654916 | I42: =SUM(I41,F42) -> 552684 | K42: frm Deepak | L42: 46002 | M42: 30000 | V42: 41609 | W42: 44275 | X42: 2130
A43: 45778 | B43: 12889 | C43: 11639 | D43: 1250 | E43: 5166 | F43: 0 | H43: =SUM(H42,B43,C43) -> 3679444 | I43: 552684 | K43: frm Renuka | L43: 46002 | M43: 20000 | V43: 41640 | W43: 44275 | X43: 2130
A44: 45809 | B44: 12889 | C44: 11639 | D44: 1250 | E44: 5166 | F44: 0 | H44: =SUM(H43,B44,C44) -> 3703972 | I44: =SUM(I42,F44) -> 552684 | K44: csh deposit | L44: 46002 | M44: 49900 | V44: 41671 | W44: 44275 | X44: 2130
A45: 45839 | B45: 12889 | C45: 11639 | D45: 1250 | E45: 5166 | F45: 0 | H45: =SUM(H44,B45,C45) -> 3728500 | I45: 552684 | K45: csh deposit | L45: 46007 | M45: 49900 | V45: 41699 | W45: 44275 | X45: 2130
A46: 45870 | B46: 12889 | C46: 11639 | D46: 1250 | E46: 5166 | F46: 0 | H46: =SUM(H45,B46,C46) -> 3753028 | I46: 552684 | K46: csh deposit | L46: 45669 | M46: 49900 | V46: 41730 | W46: 44275 | X46: 2130
A47: 45901 | B47: 12889 | C47: 11639 | D47: 1250 | E47: 5166 | F47: 0 | H47: =SUM(H46,B47,C47) -> 3777556 | I47: 552684 | K47: csh deposit | L47: 45673 | M47: 49900 | V47: 41760 | W47: 44275 | X47: 2130
A48: 45931 | B48: 12889 | C48: 11639 | D48: 1250 | E48: 5166 | F48: 0 | H48: =SUM(H47,B48,C48) -> 3802084 | I48: 552684 | K48: csh deposit | L48: 45674 | M48: 49900 | V48: 41791 | W48: 44275 | X48: 2130
A49: 45962 | B49: 12889 | C49: 11639 | D49: 1250 | E49: 5166 | F49: 0 | H49: =SUM(H48,B49,C49) -> 3826612 | I49: 552684 | V49: 41821 | W49: 44275 | X49: 2130
A50: 45992 | B50: 12889 | C50: 11639 | D50: 1250 | E50: 5166 | F50: 0 | H50: =SUM(H49,B50,C50) -> 3851140 | I50: 552684 | P50: 13920 | V50: 41852 | W50: 44275 | X50: 2130
A51: 46023 | B51: 13920 | C51: 12670 | D51: 1250 | E51: 5166 | F51: 0 | H51: =SUM(H50,B51,C51) -> 3877730 | I51: 552684 | P51: -1250 | V51: 41883 | W51: 44275 | X51: 2130
A52: 46054 | B52: 13920 | C52: 12670 | D52: 1250 | E52: 5166 | F52: 0 | H52: =SUM(H51,B52,C52) -> 3904320 | I52: 552684 | P52: =SUM(P50:P51) -> 12670 | V52: 41913 | W52: 44275 | X52: 2130
A53: 46082 | B53: 13920 | C53: 12670 | D53: 1250 | E53: 5166 | F53: 0 | H53: =SUM(H52,B53,C53) -> 3930910 | I53: 552684 | L53: 9508 | V53: 41944 | W53: 44275 | X53: 2130
A54: 46113 | B54: 13920 | C54: 12670 | D54: 1250 | E54: 5166 | F54: 0 | H54: =SUM(H53,B54,C54) -> 3957500 | I54: 552684 | L54: 8077 | V54: 41974 | W54: 44275 | X54: 2130
A55: 46143 | B55: 13920 | C55: 12670 | D55: 1250 | E55: 5166 | H55: =SUM(H54,B55,C55) -> 3984090 | I55: 552684 | L55: 3415 | V55: 42005 | W55: 44275 | X55: 2130
L56: =SUM(L53:L55) -> 21000 | V56: 42036 | W56: 46931 | X56: 2257
L57: 118538 | V57: 42064 | W57: 46931 | X57: 2257
L58: 74158 | V58: 42095 | W58: 46931 | X58: 2257
L59: 32573 | V59: 42125 | W59: 46931 | X59: 2257
L60: 20661 | V60: 42156 | W60: 46931 | X60: 2257
L61: =SUM(L53:L60) -> 287930 | M61: 310000 | N61: 340000 | O61: 370000 | V61: 42186 | W61: 46931 | X61: 2257
V62: 42217 | W62: 46931 | X62: 2257
V63: 42248 | W63: 46931 | X63: 2257
V64: 42278 | W64: 46931 | X64: 2257
V65: 42309 | W65: 46931 | X65: 2257
V66: 42339 | W66: 46931 | X66: 2257
V67: 42370 | W67: 46931 | X67: 2257
V68: 42401 | W68: 52329 | X68: 2517
V69: 42430 | W69: 52329 | X69: 2517
V70: 42461 | W70: 52329 | X70: 2517
V71: 42491 | W71: 52329 | X71: 2517
V72: 42522 | W72: 52329 | X72: 2517
V73: 42552 | W73: 52329 | X73: 2517
... V138: 44531 | W138: 74720 | X138: 3594
V139: 44562 | X139: 3900
V140: 44593 | X140: 3900
V141: 44621 | X141: 3900
V142: 44652 | X142: 3900
V143: 44682 | X143: 3900
V144: 44713 | X144: 3900
V145: 44743 | X145: 3900
V146: 44774 | X146: 3900
V147: 44805 | X147: 3900
V148: 44835 | X148: 3900
V149: 44866 | X149: 3900
V150: 44896 | X150: 3900
... V164: 45323 | X164: 4675
V165: 45352
V166: 45383
V167: 45413
V168: 45444
V169: 45474
V170: 45505
V171: 45536
X172: =SUM(X1:X171) -> 459569

Sheet car
B1: =SUM(B2:B6) -> 149024 | I1: 2241601 | J1: =I1*0.085 -> 190536.09 | K1: =I1+J1 -> 2432137.1 | L1: =K1*(1.68/100) -> 40859.903 | P1: basic | Q1: 81071 | R1: =Q1*0.4 -> 32428.4 | T1: 81071 | W1: 2432136 | Z1: 2675350 | AA1: =Z1*0.08 -> 214028 | AD1: 3480113 | AE1: 0.1 | AF1: 0.09 | AG1: 0.08 | AH1: 0.07 | AI1: 0.06 | AJ1: 0.05 | AP1: Unnati
B2: -2983 | C2: 815128 | D2: =C2/12 -> 67927.333 | E2: 67927 | F2: =E2*0.12 -> 8151.24 | I2: 6793 | J2: 8151 | K2: -1250 | P2: HRA | Q2: 40536 | R2: fixed | T2: 40536 | W2: =W1/12 -> 202678 | Z2: -400000 | AA2: =Z1*0.09 -> 240781.5 | AB2: =Z1+AA2 -> 2916131.5 | AE2: =AD1*AE1 -> 348011.3 | AF2: =AD1*AF1 -> 313210.17 | AG2: =AD1*AG1 -> 278409.04 | AH2: =AD1*AH1 -> 243607.91 | AI2: =AD1*AI1 -> 208806.78 | AJ2: =AD1*AJ1 -> 174005.65 | AM2: 42005 | AO2: 42736 | AP2: 13000 | AQ2: 43466 | AR2: 14500 | AS2: 44197 | AT2: 14900 | AU2: 44927 | AV2: 16300 | AY2: 41368267950 | AZ2: 98000
B3: -27114 | C3: 1085664 | D3: 89072 | E3: =C3/12 -> 90472 | F3: =SUM(D8:D12) -> 40800 | G3: =E3-F3 -> 49672 | I3: 111455 | J3: =SUM(I2:K2) -> 13694 | K3: 17661 | L3: 2000 | M3: 3267 | N3: 2000 | O3: 1400 | P3: bonus | Q3: 1400 | R3: fixed | T3: 1400 | W3: -30000 | X3: =W1*0.1 -> 243213.6 | Y3: =W1+X3 -> 2675349.6 | Z3: =SUM(Z1:Z2) -> 2275350 | AA3: =Z1*0.1 -> 267535 | AE3: =SUM(AD1,AE2) -> 3828124.3 | AF3: =SUM(AF2,AD1) -> 3793323.2 | AG3: =SUM(AG2,AD1) -> 3758522 | AH3: =SUM(AH2,AD1) -> 3723720.9 | AM3: 42036 | AO3: 42767 | AQ3: 43497 | AR3: 14800 | AS3: 44228 | AT3: 16000 | AU3: 44958 | AV3: 16300 | AY3: 42446106429 | AZ3: 49000
B4: -200 | C4: 137020 | D4: 1400 | O4: 35000 | P4: convey | Q4: 5000 | R4: fixed | T4: 5000 | W4: =SUM(W2:W3) -> 172678 | Z4: -400000 | AA4: =Z1*0.11 -> 294288.5 | AC4: =AB2*0.105 -> 306193.81 | AD4: =AB2+AC4 -> 3222325.3 | AE4: 34900 | AM4: 42064 | AO4: 42795 | AQ4: 43525 | AR4: 15000 | AS4: 44256 | AU4: 44986 | AV4: 16300 | AY4: 41720198767 | AZ4: 49000
B5: -9729 | C5: 97815 | D5: =C5/12 -> 8151.25 | H5: 6299 | I5: 67927 | J5: 45236 | K5: =(I5+J5)/30 -> 3772.1 | L5: =K5*38 -> 143339.8 | O5: 200 | P5: LTA | Q5: 4167 | R5: fixed | T5: 4167 | Z5: =SUM(Z3:Z4) -> 1875350 | AA5: =Z1*0.12 -> 321042 | AM5: 42095 | AN5: 7000 | AO5: 42826 | AQ5: 43556 | AR5: 14000 | AS5: 44287 | AT5: 16000 | AU5: 45017 | AV5: 16300 | AY5: 41368300002 | AZ5: 49000
B6: =SUM(B7:B13) -> 189050 | C6: =D6*12 -> 39204 | D6: 3267 | H6: =62997*0.12 -> 7559.64 | L6: =L5*0.3 -> 43001.94 | O6: 2200 | P6: child | Q6: 200 | R6: ABP | T6: 200 | AM6: 42125 | AO6: 42856 | AQ6: 43586 | AR6: 0 | AS6: 44317 | AT6: 15900 | AU6: 45047 | AV6: 16300 | AY6: 42246810208 | AZ6: 49000
B7: 81071 | C7: basic | D7: 67927 | E7: =D7*0.6 -> 40756.2 | I7: 1400000 | L7: =L5-L6 -> 100337.86 | O7: 2000 | P7: food | Q7: 2200 | R7: ABP | AB7: 1070140 | AC7: =0.09*AB7 -> 96312.6 | AD7: =SUM(AB7:AC7) -> 1166452.6 | AG7: Basic | AM7: 42156 | AN7: 7800 | AO7: 42887 | AQ7: 43617 | AR7: 0 | AS7: 44348 | AT7: 15700 | AU7: 45078 | AV7: 16300 | AY7: 41061151001 | AZ7: 49000
B8: 33000 | C8: rent | D8: 35000 | I8: =I7/11 -> 127272.73 | O8: 49672 | P8: telephone | Q8: 4000 | R8: ABP | T8: 4000 | Y8: =145523*3 -> 436569 | AA8: 145523 | AB8: 51468 | AC8: =0.09*AB8 -> 4632.12 | AD8: =SUM(AB8:AC8) -> 56100.12 | AG8: Gratuity | AM8: 42186 | AN8: 8300 | AO8: 42917 | AQ8: 43647 | AR8: 0 | AS8: 44378 | AT8: 15800 | AU8: 45108 | AV8: 16300 | AY8: 42773181631 | AZ8: 49000
A9: =SUM(B8:B13) -> 107979 | B9: 1400 | C9: bonus | D9: 1400 | O9: =SUM(O3:O8) -> 90472 | P9: per | Q9: 50476 | R9: ABP | T9: 50476 | Y9: 145523 | AA9: 9729 | AB9: 128412 | AC9: =AB9*0.09 -> 11557.08 | AD9: =SUM(AB9:AC9) -> 139969.08 | AG9: compPF | AM9: 42217 | AN9: 8300 | AO9: 42948 | AP9: 11000 | AQ9: 43678 | AS9: 44409 | AT9: 15800 | AU9: 45139 | AV9: 16300
A10: =A9*12 -> 1295748 | B10: 200 | C10: childEdu | D10: 200 | O10: =O9/2 -> 45236 | P10: PF | Q10: 9729 | W10: 1417499 | X10: 508850 | Y10: 24727 | AA10: 9729 | AD10: 1553610 | AG10: perPay | AM10: 42248 | AN10: 8000 | AO10: 42979 | AP10: 10500 | AQ10: 43709 | AR10: 18000 | AS10: 44440 | AT10: 15500 | AU10: 45170 | AV10: 16300 | AZ10: =SUM(AZ2:AZ8) -> 392000
B11: 2000 | C11: lta | D11: 2000 | H11: Previous | J11: Current | K11: perMonth | L11: pf | M11: hra | P11: gratuity | Q11: 3900 | W11: 1205140 | X11: 3415 | Y11: =2200*3 -> 6600 | AM11: 42278 | AN11: 8000 | AO11: 43009 | AP11: 10500 | AQ11: 43739 | AR11: 15000 | AS11: 44470 | AT11: 16000 | AU11: 45200 | AV11: 16300
B12: 2200 | C12: food | D12: 2200 | F12: 3960784 | G12: basic | H12: =74720*12 -> 896640 | I12: =H12*0.085 -> 76214.4 | J12: =SUM(H12:I12) -> 972854.4 | K12: =J12/12 -> 81071.2 | L12: =K12*0.12 -> 9728.544 | M12: =K12*0.4 -> 32428.48 | Q12: =SUM(Q1:Q11) -> 202679 | R12: =Q12*12 -> 2432148 | S12: =R12*0.4 -> 972859.2 | T12: =S12/12 -> 81071.6 | W12: 9502 | X12: =SUM(X10:X11) -> 512265 | Y12: =SUM(Y9:Y11) -> 176850 | AA12: 2619 | AE12: 162590 | AF12: 215490 | AM12: 42309 | AN12: 8000 | AO12: 43040 | AP12: 10900 | AQ12: 43770 | AS12: 44501 | AT12: 18000 | AU12: 45231 | AV12: 16300
B13: 69179 | C13: perPay | D13: 49672 | F13: 200000 | G13: retiral | H13: 150720 | I13: =H13*0.085 -> 12811.2 | J13: =SUM(H13:I13) -> 163531.2 | K13: =J13/12 -> 13627.6 | M13: basic | N13: 815128 | U13: =SUM(U15:U19) -> 2433111 | W13: 8077 | Y13: =Y12*3 -> 530550 | AA13: 3900 | AE13: 10701 | AF13: 10701 | AM13: 42339 | AN13: 8500 | AO13: 43070 | AP13: 10500 | AQ13: 43800 | AS13: 44531 | AT13: 13000 | AU13: 45261 | AV13: 16300
C14: =SUM(C2:C4) -> 2037812 | D14: =SUM(D7:D13) -> 158399 | F14: =SUM(F12:F13) -> 4160784 | G14: FEP | H14: 1194240 | I14: =H14*0.085 -> 101510.4 | J14: =SUM(H14:I14) -> 1295750.4 | K14: =J14/12 -> 107979.2 | L14: -40800 | N14: 1085664 | P14: =SUM(N13:N14) -> 1900792 | W14: =SUM(W10:W13) -> 2640218 | AA14: 2200 | AE14: 10701 | AF14: 10701 | AM14: 42370 | AN14: 9000 | AO14: 43101 | AP14: 10500 | AQ14: 43831 | AR14: 0 | AS14: 44562 | AT14: 15300 | AU14: 45292 | AV14: 16300
F15: 1400000 | H15: =SUM(H12:H14) -> 2241600 | J15: =SUM(J12:J14) -> 2432136 | K15: =SUM(K12,K14) -> 189050.4 | N15: 137020 | P15: 12 | R15: eps | S15: =1250*12 -> 15000 | U15: 2195163 | AA15: =SUM(AA8:AA14) -> 173700 | AE15: -1250 | AF15: -1250 | AM15: 42401 | AN15: 10500 | AO15: 43132 | AP15: 10900 | AQ15: 43862 | AR15: 29000 | AS15: 44593 | AT15: 15200 | AU15: 45323 | AV15: 16300
B16: 170040 | F16: =SUM(F14:F15) -> 5560784 | H16: =H15/12 -> 186800 | J16: =J15/12 -> 202678 | R16: takehome | S16: 1394288 | T16: tele | U16: 48000 | AA16: 16000 | AE16: 669 | AF16: 669 | AM16: 42430 | AO16: 43160 | AP16: 10600 | AQ16: 43891 | AR16: 0 | AS16: 44621 | AT16: 15000 | AU16: 45352 | AV16: 16500
B17: 666000 | R17: pf | S17: 116748 | T17: food | U17: 26400 | AA17: =SUM(AA15:AA16) -> 189700 | AE17: 2200 | AF17: 2200 | AM17: 42461 | AN17: 11200 | AO17: 43191 | AP17: 10700 | AQ17: 43922 | AR17: 27000 | AS17: 44652 | AT17: 15200 | AU17: 45383 | AV17: 17400
B18: 103496 | H18: =SUM(H12,H14) -> 2090880 | I18: =H18*0.066 -> 137998.08 | J18: =I18*0.3 -> 41399.424 | K18: =I18-J18 -> 96598.656 | L18: 134467 | N18: 97812 | R18: vpf | S18: 31428 | T18: gratuity | U18: =3900*12 -> 46800 | AE18: 4289 | AF18: 4289 | AM18: 42491 | AN18: 9700 | AO18: 43221 | AP18: 10600 | AQ18: 43952 | AR18: 14000 | AS18: 44682 | AT18: 15000 | AU18: 45413 | AV18: 17000
B19: 1811 | N19: 39208 | R19: gratuity | S19: =3900*12 -> 46800 | T19: comPF | U19: =9729*12 -> 116748 | AE19: 16300 | AF19: 16300 | AM19: 42522 | AN19: 10000 | AO19: 43252 | AP19: 0 | AQ19: 43983 | AR19: 14000 | AS19: 44713 | AT19: 16500 | AU19: 45444 | AV19: 17000
B20: 28699 | E20: 100000 | F20: 138.89 | G20: =E20/F20 -> 719.99424 | R20: comp.PF | S20: =8479*12 -> 101748 | AE20: =SUM(AE12:AE19) -> 206200 | AF20: =SUM(AF12:AF19) -> 259100 | AM20: 42552 | AN20: 10700 | AO20: 43282 | AP20: 21000 | AQ20: 44013 | AR20: 14000 | AS20: 44743 | AT20: 16400 | AU20: 45474 | AV20: 17100
B21: =SUM(B17:B20) -> 800006 | E21: =F21*G20 -> 101108.79 | F21: 140.43 | K21: 1907136 | M21: 2gb | N21: 2400 | O21: 200 | R21: food | S21: =12*2200 -> 26400 | X21: 40 | Y21: 16760 | Z21: =Y21*2.5 -> 41900 | AM21: 42583 | AN21: 10400 | AO21: 43313 | AQ21: 44044 | AR21: 0 | AS21: 44774 | AT21: 16400 | AU21: 45505 | AV21: 17200
B22: -18000 | G22: 8966 | H22: 9728 | K22: =K21*0.3 -> 572140.8 | M22: 1.5gb | N22: 2320 | O22: =N22/12 -> 193.33333 | R22: telephone | S22: =4000*12 -> 48000 | X22: 60 | Y22: 41900 | Z22: 806 | AM22: 42614 | AN22: 10000 | AO22: 43344 | AQ22: 44075 | AR22: 27000 | AS22: 44805 | AT22: 15800 | AU22: 45536 | AV22: 17000
B23: =SUM(B21:B22) -> 782006 | G23: 8966 | H23: 9728 | K23: =K21-K22 -> 1334995.2 | M23: 1gb | N23: 2266 | O23: =N23/12 -> 188.83333 | R23: tax | S23: 326383 | W23: PA | X23: PM | Y23: =SUM(Y21:Y22) -> 58660 | AM23: 42644 | AN23: 10000 | AO23: 43374 | AP23: 11000 | AQ23: 44105 | AR23: 14500 | AS23: 44835 | AT23: 16300 | AU23: 45566 | AV23: 17000
G24: -1250 | H24: -1250 | K24: 100338 | L24: 37 | S24: =SUM(S15:S23) -> 2106795 | W24: 2675350 | X24: =W24/12 -> 222945.83 | AA24: =SUM(AA25:AA33) -> 205755.2 | AB24: 10701 | AC24: 2200 | AD24: 4289 | AF24: basic | AG24: 1070140 | AH24: =AG24*0.09 -> 96312.6 | AI24: =SUM(AG24:AH24) -> 1166452.6 | AJ24: =AI24/12 -> 97204.383 | AM24: 42675 | AN24: 11000 | AO24: 43405 | AP24: 12000 | AQ24: 44136 | AR24: 13700 | AS24: 44866 | AT24: 16000 | AU24: 45597
B25: =SUM(B26:B38) -> 804898 | D25: 8151 | F25: =G25*12 -> 200184 | G25: =SUM(G22:G24) -> 16682 | H25: =SUM(H22:H24) -> 18206 | I25: =H25*12 -> 218472 | K25: =SUM(K23:K24) -> 1435333.2 | N25: 24 | O25: 365 | P25: =O25/N25 -> 15.208333 | Q25: 149 | T25: 89178 | U25: 89178 | V25: basic | W25: =W24*0.4 -> 1070140 | X25: =W25/12 -> 89178.333 | Y25: =X25*0.4 -> 35671.333 | AA25: 89178 | AB25: basic | AF25: variable | AG25: 1425322 | AH25: =AG25*0.09 -> 128278.98 | AI25: =SUM(AG25:AH25) -> 1553601 | AJ25: =AI25/12 -> 129466.75 | AM25: 42705 | AN25: 23000 | AO25: 43435 | AP25: 14900 | AQ25: 44166 | AR25: 13700 | AS25: 44896 | AT25: 16400 | AU25: 45627
A26: car | B26: 782606 | D26: 6901 | F26: =4110*12 -> 49320 | I26: =2600*12 -> 31200 | K26: =K25/12 -> 119611.1 | O26: 2400 | P26: =P25*Q25 -> 2266.0417 | Q26: =O26-P26 -> 133.95833 | V26: gratuity | W26: =(W25*4.81)/100 -> 51473.734 | X26: =W26/12 -> 4289.4778 | Z26: =SUM(W25,W28,W30,W31,W32,W33) -> 1780010 | AA26: =AA25*0.4 -> 35671.2 | AB26: HRA | AF26: Gratuity | AG26: 51474 | AH26: =AG26*0.09 -> 4632.66 | AI26: =SUM(AG26:AH26) -> 56106.66 | AJ26: =AI26/12 -> 4675.555 | AN26: =SUM(AN2:AN25) -> 189400 | AP26: =SUM(AP2:AP25) -> 178600 | AR26: =SUM(AR2:AR25) -> 258200 | AT26: =SUM(AT2:AT25) -> 362100 | AV26: =SUM(AV2:AV25) -> 364400
A27: accesso | B27: 3320 | I27: =SUM(I25:I26) -> 249672 | K27: 10000 | V27: PF | W27: =W25*0.12 -> 128416.8 | X27: =W27/12 -> 10701.4 | Y27: 2619 | Z27: =SUM(W26,W27) -> 179890.53 | AA27: 200 | AB27: child | AC27: HRA1 | AD27: 32400 | AF27: compPF | AG27: 128417 | AH27: =AG27*0.09 -> 11557.53 | AI27: =SUM(AG27:AH27) -> 139974.53 | AJ27: =AI27/12 -> 11664.544
A28: praveen | B28: 5000 | N28: 365 | O28: 336 | P28: =N28-O28 -> 29 | T28: 44500 | U28: 35500 | V28: HRA | W28: 535070 | X28: =X25*0.5 -> 44589.167 | Z28: =SUM(W29,W35) -> 28800 | AA28: 1400 | AB28: bonus | AC28: HRA2 | AD28: 35600 | AS28: =SUM(AN26:AX26) -> 1352700
A29: limbe | B29: 20 | F29: apr | G29: may | H29: jun | N29: 2121 | O29: 199 | P29: =SUM(N29:O29) -> 2320 | Q29: =P29-P26 -> 53.958333 | T29: 200 | U29: 200 | V29: child | W29: 2400 | X29: 200 | Z29: =SUM(Z26:Z28) -> 1988700.5 | AA29: 5000 | AB29: convey | AC29: Apr | AD29: 470.82 | AE29: 209 | AF29: 45089 | AI29: 3480113 | AN29: -600000 | AP29: =SUM(AI29:AN29) -> 2880113
A30: hoova | B30: 50 | C30: 150000 | F30: 15052 | G30: 15052 | H30: 15052 | J30: =31354*10 -> 313540 | T30: 1400 | U30: 1400 | V30: bonus | W30: 16800 | X30: 1400 | Z30: =W24-Z29 -> 686649.47 | AA30: 4167 | AB30: lta | AC30: may | AD30: 470.82 | AE30: 209 | AF30: 45119 | AH30: basic | AI30: =0.4*AI29 -> 1392045.2 | AJ30: =AI30/12 -> 116003.77 | AK30: 116004 | AL30: 116004 | AN30: 430200
A31: petrol | B31: 1000 | C31: 94062 | D31: 110000 | F31: 16302 | G31: 16302 | H31: 16302 | J31: =110845*10 -> 1108450 | T31: 5000 | U31: 5000 | V31: convey | W31: 60000 | X31: 5000 | Z31: =Z30/12 -> 57220.789 | AA31: 4000 | AB31: tele | AC31: june | AD31: 380.28 | AE31: 209 | AF31: 45156 | AH31: gratuity | AI31: =(4.81/100)*AI30 -> 66957.374 | AJ31: =(4.81/100)*AJ30 -> 5579.7812 | AK31: 5580
A32: tobacco | B32: 42 | O32: gratuity | P32: 4.81% of basic | R32: =(4.81*81071)/100 -> 3899.5151 | T32: 4167 | U32: 4167 | V32: lta | W32: 50000 | X32: 4167 | AA32: 66139 | AB32: perPay | AC32: july | AD32: 1178.82 | AE32: 209 | AF32: 45191 | AH32: PF | AI32: =AI30*0.12 -> 167045.42 | AJ32: =AJ30*0.12 -> 13920.452 | AK32: 13920 | AN32: =SUM(AI31:AI32) -> 234002.8
A33: napthaleen | B33: 35 | F33: 2000 | G33: 2000 | H33: 2000 | J33: 6000 | O33: basic salary is 40% of CTC | T33: 4000 | U33: 4000 | V33: tele | W33: 48000 | X33: 4000 | AC33: aug | AD33: 1152.22 | AE33: 209 | AF33: 45258 | AH33: remaining | AI33: =AI29-(AI30+AI31+AI32) -> 1854065 | AJ33: =AI33/12 -> 154505.42 | AK33: 58002 | AL33: 58002 | AV33: =SUM(AV34:AV40) -> 233203 | AW33: 17300 | AY33: =SUM(AV33:AX33) -> 250503
A34: junePetro | B34: 2010 | C34: 135100 | D34: 332538 | E34: 50000 | T34: 57221 | U34: 66306 | V34: PerPay | W34: 686652 | X34: 57221 | Y34: =X34-X27-Y27 -> 43900.6 | AC34: sep | AD34: 1178.82 | AE34: 666 | AF34: 44932 | AG34: =AI31*0.4 -> 26782.95 | AJ34: =SUM(AJ30:AJ33) -> 290009.42 | AK34: 200 | AL34: 200 | AV34: 174497
C35: 643000 | J35: PF | K35: 7560 | N35: 101000 | V35: food | W35: 26400 | X35: 2200 | AC35: Oct | AD35: 1178.82 | AE35: 209 | AK35: 3500 | AL35: 3500 | AV35: 11665
J36: PF1 | K36: 6310 | N36: -12500 | Y36: 195755 | AC36: Nov | AD36: 1178.82 | AK36: 5000 | AL36: 5000 | AV36: 11665
A37: zray | B37: 10815 | C37: 45523 | F37: 134467 | G37: 20792 | J37: VPF | K37: 16379 | N37: -50000 | S37: =SUM(T25,T28,T29,T30,T31,T32,T33,T34) -> 205666 | T37: -32000 | U37: =SUM(U25:U34) -> 205751 | V37: -10701 | W37: -2619 | X37: -200 | Y37: -33000 | AC37: dec | AD37: 1178.82 | AH37: 248271 | AK37: 4167 | AL37: 4167 | AV37: 2200
A38: tvsVictor | C38: 45161 | J38: PPF | K38: 12500 | AC38: jan | AH38: 153954 | AK38: 4000 | AL38: 4000 | AV38: 4676
A39: Timex | B39: 45255 | C39: CR2016 | K39: =SUM(K35:K38) -> 42749 | M39: 44652 | P39: 44652 | Q39: 44682 | R39: 44713 | S39: 44743 | T39: 44774 | U39: 44805 | V39: 44835 | W39: 44866 | X39: 44896 | Y39: 44927 | Z39: 44958 | AA39: 44986 | AC39: feb | AH39: =SUM(AH37:AH38) -> 402225 | AV39: 15000
A40: carKEy | C40: CR1616 | L40: takehome | M40: 143148 | O40: takehome | P40: 143148 | Q40: 143186 | R40: 143187 | S40: 155992 | T40: 145523 | U40: 145523 | V40: 145523 | W40: 145523 | X40: 171352 | Y40: 157043 | AC40: mar | AH40: -40000 | AK40: 79637 | AL40: 79637 | AV40: 13500
L41: PF+VPF | M41: 20827 | O41: unnati | Y41: 16300 | Z41: 16300 | AA41: 16300 | AH41: -50000 | AK41: =SUM(AK30:AK40) -> 290010 | AL41: =SUM(AL30:AL40) -> 270510 | AV41: 7350
L42: Gratuity | M42: 3900 | O42: PF | P42: 20827 | Q42: 20827 | R42: 20827 | S42: 20827 | T42: 20827 | U42: 20827 | V42: 20827 | W42: 20827 | X42: 20827 | Y42: 23032 | AD42: =SUM(AD29:AD40) -> 8368.24 | AE42: =SUM(AE29:AE40) -> 1920 | AH42: =SUM(AH39:AH41) -> 312225 | AK42: 252117 | AV42: 35850
B43: Plumbers | D43: Electrician | I43: 11665 | K43: 2614766 | L43: Unnati | M43: 15000 | O43: Gratuity | P43: 3900 | Q43: 3900 | R43: 3900 | S43: 3900 | T43: 3900 | U43: 3900 | V43: 3900 | W43: 3900 | X43: 3900 | Y43: 4289 | AV43: =AV42*12 -> 430200
A44: 1 | B44: Ganganna | D44: Basavaraj | I44: -1250 | L44: Expense | M44: -85000 | O44: food | P44: 2200 | Q44: 2200 | R44: 2200 | S44: 2200 | T44: 2200 | U44: 2200 | V44: 2200 | W44: 2200 | X44: 2200 | Y44: 2200
A45: 2 | B45: Basavaraj | D45: Anji | I45: =SUM(I43:I44) -> 10415 | P45: =SUM(P40:P44) -> 170075 | Q45: =SUM(Q40:Q44) -> 170113 | R45: =SUM(R40:R44) -> 170114 | S45: =SUM(S40:S44) -> 182919 | T45: =SUM(T40:T44) -> 172450 | U45: =SUM(U40:U44) -> 172450 | V45: =SUM(V40:V44) -> 172450 | W45: =SUM(W40:W44) -> 172450 | ... Y45: =SUM(Y40:Y44) -> 202864 | AI45: =SUM(AI30,AI33) -> 3246110.2
A46: 3 | B46: Shivanna | AI46: -75000
A47: 4 | B47: Vishnu | M47: =SUM(M40:M45) -> 97875 | T47: =SUM(P45:X45) -> 1581300 | AI47: =SUM(AI45:AI46) -> 3171110.2
A48: 5 | O48: CTC | P48: 202679 | Q48: 44986 | R48: 45017 | S48: 45047 | T48: 45078 | U48: 45108 | V48: 45139 | W48: 45170 | X48: 45200 | AI48: -800000
K49: =SUM(I48:I50) -> 0 | M49: 202679 | Q49: 196532 | R49: 196532 | S49: 196532 | T49: 196532 | U49: 196532 | V49: 196532 | W49: 196532 | X49: 196532 | AI49: =SUM(AI47:AI48) -> 2371110.2
M50: 963 | Q50: -30000 | R50: -30000 | S50: -30000 | T50: -30000 | U50: -30000 | V50: -30000 | W50: -30000 | X50: -30000 | AA50: =10701*2 -> 21402 | AB50: -1250 | AC50: =SUM(AA50:AB50) -> 20152 | AD50: 2880
M51: =SUM(M49:M50) -> 203642 | Q51: =SUM(Q49:Q50) -> 166532 | R51: =SUM(R49:R50) -> 166532 | AE51: =89178*0.075 -> 6688.35 | AH51: Income From | AI51: Income To | AJ51: Rate | AK51: Tax
AE52: =97204*0.0075 -> 729.03 | AH52: 0 | AI52: 400000 | AJ52: 0.0% of 400,000 | AK52: 0
AH53: 400001 | AI53: 800000 | AJ53: 5.0% of 399,999 | AK53: 20000
M54: 44287 | N54: 44317 | O54: 44348 | P54: 44378 | Q54: 44409 | R54: 44440 | S54: 44470 | T54: 44501 | U54: 44531 | V54: 44582 | W54: 44593 | X54: 44621 | Z54: PF int | AA54: ppf int | AC54: Savings | AD54: itax | AH54: 800001 | AI54: 1200000 | AJ54: 10.0% of 399,999 | AK54: 40000
L55: CTC | M55: 184800 | N55: 184800 | O55: 184800 | P55: 184800 | Q55: 184800 | R55: 184800 | S55: 184800 | T55: 184800 | U55: 320497 | V55: 200678 | W55: 200678 | X55: 224678 | AB55: =SUM(M55:X55) -> 2424931 | AH55: 1200001 | AI55: 1600000 | AJ55: 15.0% of 399,999 | AK55: 60000
L56: itax | M56: -22297 | N56: -22297 | O56: -22297 | P56: -22297 | Q56: -22297 | R56: -22297 | S56: -22297 | T56: -22297 | U56: -64633 | V56: -27314 | W56: -34804 | X56: -42286 | AD56: =SUM(M56:X56) -> -347413 | AH56: 1600001 | AI56: 2000000 | AJ56: 20.0% of 399,999 | AK56: 80000
L57: Unnati | M57: 16000 | N57: 15900 | O57: 15700 | P57: 15800 | Q57: 15800 | R57: 15500 | S57: 16000 | T57: 18000 | U57: 13000 | V57: 15300 | W57: 15200 | X57: 15000 | AD57: =SUM(Z59:AA59) -> 318391 | AH57: 2000001 | AI57: 2400000 | AJ57: 25.0% of 399,999 | AK57: 100000
C58: =67927*12 -> 815124 | D58: =C58*0.1 -> 81512.4 | E58: =C58+D58 -> 896636.4 | G58: =E58/12 -> 74719.7 | H58: =G58*0.12 -> 8966.364 | I58: =8966-1250 -> 7716 | K58: =G58*0.5 -> 37359.85 | L58: Expense | M58: -17379 | N58: -21222 | O58: -16847 | P58: -36777 | Q58: -32165 | R58: -16294 | S58: -83381 | T58: -17403 | U58: -18788 | V58: -22960 | W58: -17891 | X58: -24710 | AD58: =SUM(AD56:AD57) -> -29022 | AH58: 2400001 | AI58: 2986990 | AJ58: 30.0% of 586,989 | AK58: 176097
C59: 137020 | D59: =C59*0.1 -> 13702 | E59: =C59+D59 -> 150722 | G59: =E59/12 -> 12560.167 | I59: =G58*0.4 -> 29887.88 | M59: =SUM(M55:M58) -> 161124 | N59: =SUM(N55:N58) -> 157181 | O59: =SUM(O55:O58) -> 161356 | P59: =SUM(P55:P58) -> 141526 | Q59: =SUM(Q55:Q58) -> 146138 | R59: =SUM(R55:R58) -> 161709 | S59: =SUM(S55:S58) -> 95122 | T59: =SUM(T55:T58) -> 163100 | ... X59: =SUM(X55:X58) -> 172682 | Z59: 222779 | AA59: 95612 | AC59: =SUM(M59:AA59) -> 2257292 | AH59: Tax Payable on Total Income | AK59: 476098
C60: 1085664 | D60: =C60*0.1 -> 108566.4 | E60: =C60+D60 -> 1194230.4 | G60: =E60/12 -> 99519.2 | I60: =G58*0.5 -> 37359.85 | L60: PF+VPF | M60: -20917 | N60: -20917 | O60: -20917 | P60: -20917 | Q60: -20917 | R60: -20917 | S60: -20917 | T60: -20917 | U60: -20917 | V60: -18208 | W60: -18208 | X60: -18208
C61: =SUM(C58:C60) -> 2037808 | E61: =SUM(E58:E60) -> 2241588.8 | G61: =SUM(G58:G60) -> 186799.07 | I61: =G58*0.6 -> 44831.82 | L61: gratuity | M61: -3594 | N61: -3594 | O61: -3594 | P61: -3594 | Q61: -3594 | R61: -3594 | S61: -3594 | T61: -3594 | U61: -3594 | V61: -2983 | W61: -2983 | X61: -2983 | AC61: =AB55-AC59 -> 167639 | AF61: 173028 | AH61: Income From | AI61: Income To | AJ61: Rate | AK61: Tax
M62: =SUM(M59:M61) -> 136613 | N62: =SUM(N59:N61) -> 132670 | O62: =SUM(O59:O61) -> 136845 | P62: =SUM(P59:P61) -> 117015 | Q62: =SUM(Q59:Q61) -> 121627 | R62: =SUM(R59:R61) -> 137198 | S62: =SUM(S59:S61) -> 70611 | T62: =SUM(T59:T61) -> 138589 | ... X62: =SUM(X59:X61) -> 151491 | AH62: 0 | AI62: 400000 | AJ62: 0.0% of 400,000 | AK62: 0
AH63: 400001 | AI63: 800000 | AJ63: 5.0% of 399,999 | AK63: 20000
M64: 45017 | N64: 45047 | O64: 45078 | P64: 45108 | Q64: 45139 | R64: 45170 | S64: 45200 | T64: 45231 | U64: 45261 | AH64: 800001 | AI64: 1200000 | AJ64: 10.0% of 399,999 | AK64: 40000
C65: 67927 | D65: =C65*0.1 -> 6792.7 | E65: =C65+D65 -> 74719.7 | M65: 162634 | N65: 162634 | O65: 162546 | P65: 162634 | Q65: 162635 | R65: 162511 | S65: 162545 | T65: 162590 | U65: 210000 | Y65: 186850 | AH65: 1200001 | AI65: 1600000 | AJ65: 15.0% of 399,999 | AK65: 60000
A66: 2241601 | C66: =C65*0.5 -> 33963.5 | E66: =E65*0.5 -> 37359.85 | F66: basic | G66: 74720 | I66: -8966 | J66: =-8966+1250 -> -7716 | M66: 669 | N66: 669 | O66: 669 | P66: 669 | Q66: 669 | R66: 669 | S66: 669 | T66: 669 | U66: 669 | Y66: 37500 | AH66: 1600001 | AI66: 2000000 | AJ66: 20.0% of 399,999 | AK66: 80000
A67: =A66/12 -> 186800.08 | B67: =SUM(B68:B69) -> 150467 | F67: advance | G67: 1400 | I67: -19427 | K67: 36109 | M67: 20152 | N67: 20152 | O67: 20152 | P67: 20152 | Q67: 20152 | R67: 20152 | S67: 20152 | T67: 20152 | U67: 20152 | Y67: =SUM(Y65:Y66) -> 224350 | AH67: 2000001 | AI67: 2400000 | AJ67: 25.0% of 399,999 | AK67: 100000
B68: 16000 | F68: children | G68: 200 | I68: -200 | K68: 12500 | M68: 2200 | N68: 2200 | O68: 2200 | P68: 2200 | Q68: 2200 | R68: 2200 | S68: 2200 | T68: 2200 | U68: 2200 | Y68: -40000 | AH68: 2400001 | AI68: 3205460 | AJ68: 30.0% of 805,459 | AK68: 241638
B69: 134467 | C69: =SUM(B69,B74) -> 136667 | F69: HRA | G69: 37000 | I69: -21285 | M69: =SUM(M65:M68) -> 185655 | N69: =SUM(N65:N68) -> 185655 | O69: =SUM(O65:O68) -> 185567 | P69: =SUM(P65:P68) -> 185655 | Q69: =SUM(Q65:Q68) -> 185656 | R69: =SUM(R65:R68) -> 185532 | S69: =SUM(S65:S68) -> 185566 | T69: =SUM(T65:T68) -> 185611 | U69: =SUM(U65:U68) -> 233021 | V69: 166000 | Y69: =SUM(Y67:Y68) -> 184350
A70: pf | B70: 8966 | G70: 56720 | Y70: -9729
A71: comp | B71: 7716 | D71: 12560 | G71: =SUM(G66:G70) -> 170040 | I71: 134467 | J71: =G71-I71 -> 35573 | M71: 45383 | N71: 45413 | O71: 45444 | P71: 45474 | Q71: 45505 | R71: 45536 | S71: 45566 | T71: 45597 | U71: 45627 | V71: 45658 | W71: 45689 | X71: 45717 | Y71: -2619
A72: vpf | B72: 4110 | D72: -8966 | F72: food | G72: 2200 | I72: 8966 | J72: -1250 | K72: =SUM(I72:J72) -> 7716 | M72: 174470 | Y72: -200
A73: gratuity | B73: 3594 | D73: =SUM(D71:D72) -> 3594 | F73: lta | G73: 2000 | H73: =G73*0.7 -> 1400 | I73: 4110 | K73: =SUM(I74,K72) -> 155259 | M73: 22080 | Y73: =SUM(Y69:Y72) -> 171802
A74: food | B74: 2200 | F74: retirals | G74: 12560 | I74: =SUM(I71:I73) -> 147543 | M74: 2200
A75: lta | B75: 1400 | G75: =SUM(G71:G74) -> 186800 | I75: 16682 | J75: 12 | K75: =I75*J75 -> 200184
A76: pension | B76: 1250 | C76: cash | D76: 5250313 | Y76: 3222324
B77: =SUM(B69:B76) -> 163703 | C77: canarabank | D77: 788258 | F77: 713279 | I77: 4110 | K77: =I77*J75 -> 49320 | Y77: =Y76/12 -> 268527 | AC77: 2916130
A78: tax | B78: 22497 | C78: icici arbit | D78: 666880 | F78: 74979 | N78: =N79*0.4 -> 972853.2 | O78: =N78/12 -> 81071.1 | S78: 396000 | T78: =S78/12 -> 33000 | X78: basic | Y78: =0.4*Y77 -> 107410.8 | Z78: 107411 | AC78: =AC77/12 -> 243010.83
A79: tax | B79: 600 | C79: ashoka | D79: 50000 | F79: =SUM(F77:F78) -> 788258 | M79: yearly | N79: 2432133 | O79: monthly | P79: =N79/12 -> 202677.75 | S79: 2400 | X79: gratuity | Y79: =0.0481*Y78 -> 5166.4595
B80: =SUM(B77:B79) -> 186800 | C80: ipo | D80: 200000 | S80: 16800 | X80: PF | Y80: =0.12*Y78 -> 12889.296
C81: citi | D81: 384000 | H81: 140000 | M81: basic | N81: 972855 | P81: =N81/12 -> 81071.25 | Q81: 46794 | S81: 26400 | X81: HRA | Y81: =0.5*Y78 -> 53705.4 | Z81: 53705
A82: 163703 | C82: Unnati | D82: 1650000 | H82: 9729 | M82: FEP | N82: =SUM(S78:S83) -> 1295736 | P82: =N82/12 -> 107978 | S82: 24000 | U82: HRA | W82: receipt | X82: child | Y82: 200 | Z82: 200
A83: 15775 | C83: Silver | D83: 696000 | H83: 2983 | M83: Retirals | N83: =13629*12 -> 163548 | O83: =N83/12 -> 13629 | P83: 3900 | S83: 830136 | U83: child | W83: no | X83: bonus | Y83: 3000 | Z83: 3500
A84: =SUM(A82:A83) -> 179478 | C84: composite | D84: 715556 | H84: 9729 | P84: 9729 | U84: AdBonus | W84: no | X84: convey | Y84: 5000 | Z84: 5000
C85: sbi | D85: 150000 | H85: -1250 | U85: Food | W85: coupon | X85: lta | Y85: 4167 | Z85: 4167
C86: ppf | D86: 1121465 | H86: 2200 | U86: LTA | W86: receipt | X86: tele | Y86: 4000 | Z86: 4000
C87: gratuity | D87: 474178 | H87: 3900 | M87: salary | N87: 137333 | P87: 137333 | U87: bb&T | W87: 4000 | X87: PerPay | Y87: 70788 | Z87: 70288
C88: PF | D88: 2054513 | H88: =SUM(H81:H87) -> 167291 | I88: 12 | J88: =H88*I88 -> 2007492 | M88: pf | N88: 9729 | P88: 2200 | U88: convey | W88: 5000 | X88: food | Y88: 2200
C89: VPF | D89: 378600 | M89: vpf | N89: 2983 | O89: =SUM(N87:N91,N93,N94) -> 165873.5 | P89: =SUM(P87:P88) -> 139533 | U89: personal | W89: no | Y89: =SUM(Y78:Y88) -> 268526.96 | Z89: =SUM(Z78:Z88) -> 248271 | AA89: -39311 | AB89: =SUM(Z89:AA89) -> 208960
H90: marc | I90: carinsu | M90: comp.pf | N90: 8479 | P90: 15000 | Z90: -46051 | AB90: 12889
D91: =SUM(D76:D89) -> 14579763 | H91: apr | I91: ppf | J91: sahana | K91: propertytax | M91: food | N91: 2200 | V91: 2979253 | W91: =Y76-V91 -> 243071 | X91: =W91/12 -> 20255.917 | Y91: =SUM(Y78,Y81,Y82,Y83,Y84,Y85,Y86,Y87,Y88) -> 250471.2 | Z91: =SUM(Z89:Z90) -> 202220 | AB91: -1250
H92: may | M92: travel | N92: 2000 | Y92: =Y91*12 -> 3005654.4 | Z92: -12889 | AB92: =SUM(AB89:AB91) -> 220599
M93: gratuity | N93: 3899.5 | P93: =SUM(P90,N87) -> 152333 | V93: =SUM(Y79:Y80) -> 18055.755 | W93: =V93*12 -> 216669.07 | X93: =W91-W93 -> 26401.934 | Y93: =X93/12 -> 2200.1612 | Z93: =SUM(Z91:Z92) -> 189331
N94: 1250 | P94: -30000 | Y94: -75000 | Z94: 12889
N95: =SUM(N87:N94) -> 167873.5 | P95: =SUM(P93:P94) -> 122333 | Y95: =SUM(Y92,Y94) -> 2930654.4 | Z95: 12889
N96: 200 | Z96: -1250
B97: 2037820 | N97: 34604 | Z97: 2200
B98: 3.32 | C98: 62707 | E98: 30000 | F98: 30000 | G98: 0.1 | H98: =F98*G98 -> 3000 | I98: =H98/12 -> 250 | N98: =SUM(N95:N97) -> 202677.5
B99: =B97*0.0332 -> 67655.624 | E99: 30000 | F99: 30000
E100: 30000 | F100: 30000
...

Sheet Shares
A1: https://best1.bseindia.com/BSE/Login/index.jsp | M1: icici | N1: 42010 | O1: 10 | P1: 400 | Q1: 4000 | W1: holding comp
A2: Hdfc standard life | E2: 3294 | M2: HCL tech | N2: 42074 | O2: 5 | P2: 2200 | Q2: =O2*P2 -> 11000 | V2: britannia | W2: BBTC/BombayBurmah
A3: accounts login | E3: 11230 | M3: persistent | N3: 42068 | O3: 5 | P3: 2000 | Q3: 10000 | V3: SRF | W3: kama holding
A4: 27n02 | E4: 6000 | G4: =6*34 -> 204 | M4: gail | N4: 42766 | O4: 10 | P4: 500 | Q4: 5000 | V4: bharat forge | W4: kalyani investment | X4: pure holding comp
A5: Micr0service00# | E5: 2948 | M5: gail | N5: 42801 | O5: 5 | P5: 575 | Q5: 2875 | V5: UPL | W5: uniforce enterprise | X5: pure holding comp
M6: gail | N6: 43174 | O6: 10 | P6: 460 | Q6: 4600 | V6: chambal fert | W6: juari global | X6: pure holding comp
A7: trading login | M7: BPCL | N7: 42788 | O7: 10 | P7: 750 | Q7: 7500 | V7: century textiles, grasim | W7: Pilani investment | X7: pure holding comp
A8: Member ID: 6370 | M8: BPCL | N8: 42923 | O8: 10 | P8: 700 | Q8: 7000 | V8: CESC | W8: STEL holding | X8: pure holding comp
A9: User Name / User ID: 27N02-6370 | M9: BPCL | N9: 43445 | O9: 10 | P9: 330 | Q9: =O9*P9 -> 3300 | V9: JK cement | W9: florence invest
A10: Login Password: | C10: Honey00# | M10: HPCL | N10: 42923 | O10: 10 | P10: 550 | Q10: 5500 | V10: vardhaman textiles | W10: vardhaman holding
A11: Transaction Password: | C11: Honey11# | M11: HPCL | N11: 42788 | O11: 12 | P11: 600 | Q11: 7200 | V11: JSW steel | W11: nalwasons.com
M12: HPCL | N12: 43445 | O12: 33 | P12: 228 | Q12: =O12*P12 -> 7524
A13: SecurityName | B13: SecurityCode | C13: BookValue | D13: Buy Qty | E13: Buy Avg | F13: Buy Value | G13: Closing Rate | H13: Total Value | I13: UnRealized P&L | J13: dividend | M13: castrol | N13: 42801 | O13: 10 | P13: 450 | Q13: 4500
A14: BPCL | C14: 178 | D14: 190 | E14: 202 | F14: =D14*E14 -> 38380 | G14: 382 | H14: =D14*G14 -> 72580 | I14: =H14-F14 -> 34200 | J14: 16105 | M14: castrol | N14: 43445 | O14: 10 | P14: 155 | Q14: =O14*P14 -> 1550
A15: IOCL | C15: 129 | D15: 825 | E15: 75 | F15: =D15*E15 -> 61875 | G15: 175 | H15: =D15*G15 -> 144375 | I15: =H15-F15 -> 82500 | J15: 20247 | M15: coalIndia | N15: 42802 | O15: 20 | P15: 350 | Q15: 7000
A16: HPCL | C16: 216 | D16: 120 | E16: 174 | F16: =D16*E16 -> 20880 | G16: 458 | H16: =D16*G16 -> 54960 | I16: =H16-F16 -> 34080 | J16: 9385 | M16: coalIndia | N16: 43445 | O16: 10 | P16: 248 | Q16: =O16*P16 -> 2480
A17: OilIndia | C17: 306 | D17: 21 | E17: 153 | F17: =D17*E17 -> 3213 | G17: 426 | H17: =D17*G17 -> 8946 | I17: =H17-F17 -> 5733 | J17: 1212 | M17: coalIndia | N17: 43487 | O17: 10 | P17: 228 | Q17: =O17*P17 -> 2280
A18: ONGC | C18: 280 | D18: 40 | E18: 152.5 | F18: =D18*E18 -> 6100 | G18: 241 | H18: =D18*G18 -> 9640 | I18: =H18-F18 -> 3540 | J18: 1672 | M18: IOCL | N18: 43174 | O18: 10 | P18: 195 | Q18: 1950
A19: PetronetLNG | D19: 1 | E19: 208.5 | F19: =D19*E19 -> 208.5 | G19: 293 | H19: =D19*G19 -> 293 | I19: =H19-F19 -> 84.5 | J19: 21.5 | M19: IOCL | N19: 43445 | O19: 10 | P19: 142 | Q19: =O19*P19 -> 1420
A20: powerGrid | C20: 99 | D20: 24 | E20: 167 | F20: =D20*E20 -> 4008 | G20: 265 | H20: =D20*G20 -> 6360 | I20: =H20-F20 -> 2352 | J20: 916 | M20: ONGC | N20: 43175 | O20: 10 | P20: 183 | Q20: 1800
A21: PFC | C21: 333 | D21: 27 | E21: 84 | F21: =D21*E21 -> 2268 | G21: 374 | H21: =D21*G21 -> 10098 | I21: =H21-F21 -> 7830 | J21: 1479 | M21: ONGC | N21: 43445 | O21: 20 | P21: 142 | Q21: =O21*P21 -> 2840
A22: MIDHANI | D22: 20 | E22: 168 | F22: =D22*E22 -> 3360 | G22: 253 | H22: =D22*G22 -> 5060 | I22: =H22-F22 -> 1700 | J22: 126 | M22: oil india | N22: 43174 | O22: 5 | P22: 345 | Q22: =O22*P22 -> 1725
A23: GAIL | D23: 342 | E23: 96 | F23: =D23*E23 -> 32832 | G23: 187 | H23: =D23*G23 -> 63954 | I23: =H23-F23 -> 31122 | J23: 5580 | M23: oil india | N23: 43175 | O23: 5 | P23: 340 | Q23: =O23*P23 -> 1700
A24: coalIndia | C24: 160 | D24: 126 | E24: 226 | F24: =D24*E24 -> 28476 | G24: 405 | H24: =D24*G24 -> 51030 | I24: =H24-F24 -> 22554 | J24: 15113 | M24: KothaPro | N24: 43175 | O24: 10 | P24: 160 | Q24: 1600
A25: NSDL | D25: 18 | E25: 800 | F25: =D25*E25 -> 14400 | G25: 1166 | H25: =D25*G25 -> 20988 | I25: =H25-F25 -> 6588 | M25: HDFC life | N25: 43175 | O25: 10 | P25: 443
A26: TCS | D26: 2 | E26: 2725 | F26: =D26*E26 -> 5450 | G26: 4114 | H26: =D26*G26 -> 8228 | I26: =H26-F26 -> 2778 | J26: 914 | K26: =I26/D26 -> 1389 | M26: Motherson | N26: 43445 | O26: 10 | P26: 155 | Q26: =O26*P26 -> 1550
A27: INFOSYS LIMITED | D27: 30 | E27: 750 | F27: =D27*E27 -> 22500 | G27: 1961 | H27: =D27*G27 -> 58830 | I27: =H27-F27 -> 36330 | J27: 6765 | K27: =I27/D27 -> 1211 | M27: Motherson | N27: 44120 | O27: 10 | P27: 112 | Q27: =O27*P27 -> 1120
A28: HCL TECHNOLOGIES LTD | D28: 20 | E28: 550 | F28: =D28*E28 -> 11000 | G28: 1806 | H28: =D28*G28 -> 36120 | I28: =H28-F28 -> 25120 | J28: 6520 | K28: =I28/D28 -> 1256 | M28: Biocon | N28: 44118 | O28: 10 | P28: 460 | Q28: =O28*P28 -> 4600
A29: wipro | C29: 79 | D29: 180 | E29: 268 | F29: =D29*E29 -> 48240 | G29: 271 | H29: =D29*G29 -> 48780 | I29: =H29-F29 -> 540 | M29: Biocon
M30: caplinpoint | N30: 44116 | O30: 10 | P30: 560 | Q30: =O30*P30 -> 5600
A31: ITC | D31: 532 | E31: 269 | F31: =D31*E31 -> 143108 | G31: 315 | H31: =D31*G31 -> 167580 | I31: =H31-F31 -> 24472 | J31: 27052 | M31: laurus | N31: 44120 | O31: 10 | P31: 330 | Q31: =O31*P31 -> 3300
A32: Dabur | D32: 2 | E32: 531 | F32: =D32*E32 -> 1062 | G32: 632 | H32: =D32*G32 -> 1264 | I32: =H32-F32 -> 202 | J32: 11 | M32: laurus | N32: 44166 | O32: 100 | P32: 325 | Q32: =O32*P32 -> 32500
A33: Tata consumer Product | D33: 1 | E33: 706 | F33: =D33*E33 -> 706 | G33: 1207 | H33: =D33*G33 -> 1207 | I33: =H33-F33 -> 501 | J33: 32.65 | M33: indoco | N33: 44120 | O33: 10 | P33: 260 | Q33: =O33*P33 -> 2600
A34: HUL | D34: 1 | E34: 2115 | F34: =D34*E34 -> 2115 | G34: 2836 | H34: =D34*G34 -> 2836 | I34: =H34-F34 -> 721 | J34: 76 | M34: TCS | N34: 44141 | O34: 2 | P34: 2750 | Q34: =O34*P34 -> 5500
A35: PIDILITE INDUSTRIES LTD | D35: 20 | E35: 810 | F35: =D35*E35 -> 16200 | G35: 1444 | H35: =D35*G35 -> 28880 | I35: =H35-F35 -> 12680 | J35: 295 | K35: =I35/D35 -> 634 | N35: Mothewire | O35: 10 | P35: 1615 | Q35: =O35*P35 -> 16150
A36: ASIAN PAINTS LIMITED | D36: 4 | E36: 2250 | F36: =D36*E36 -> 9000 | G36: 2272 | H36: =D36*G36 -> 9088 | I36: =H36-F36 -> 88 | J36: 489.6 | K36: =I36/D36 -> 22 | N36: mothersonsumi | O36: 4 | P36: 2300 | Q36: =O36*P36 -> 9200
A37: Bikaji | D37: 2 | E37: 759 | F37: =D37*E37 -> 1518 | G37: 730 | H37: =D37*G37 -> 1460 | I37: =H37-F37 -> -58 | M37: sequent | N37: 44141 | O37: 10 | P37: 160 | Q37: =O37*P37 -> 1600
A38: Nestle | D38: 18 | E38: 1160 | F38: =D38*E38 -> 20880 | G38: 1286 | H38: =D38*G38 -> 23148 | I38: =H38-F38 -> 2268 | N38: 44141 | O38: 10 | P38: 2050 | Q38: =O38*P38 -> 20500
A39: Associated Alcohal | D39: 20 | E39: 955 | F39: =D39*E39 -> 19100 | G39: 1002 | H39: =D39*G39 -> 20040 | I39: =H39-F39 -> 940 | J39: 40 | K39: =I40/D40 -> 249 | M39: 360 | N39: 44166 | O39: 10 | P39: 575 | Q39: =O39*P39 -> 5750
A40: Allied Blenders | C40: IPO | D40: 53 | E40: 281 | F40: =D40*E40 -> 14893 | G40: 530 | H40: =D40*G40 -> 28090 | I40: =H40-F40 -> 13197 | J40: 191 | K40: =I41/D41 -> 1348
A41: radico | D41: 20 | E41: 2075 | F41: =D41*E41 -> 41500 | G41: 3423 | H41: =D41*G41 -> 68460 | I41: =H41-F41 -> 26960
A42: USL | D42: 153 | E42: 1052 | F42: =D42*E42 -> 160956 | G42: 1352 | H42: =D42*G42 -> 206856 | I42: =H42-F42 -> 45900 | J42: 344 | P42: Dividend
A43: Globus | D43: 20 | E43: 1250 | F43: =D43*E43 -> 25000 | G43: 942 | H43: =D43*G43 -> 18840 | I43: =H43-F43 -> -6160
A44: Piccadily Agro | D44: 45 | E44: 770 | F44: =D44*E44 -> 34650 | G44: 607 | H44: =D44*G44 -> 27315 | I44: =H44-F44 -> -7335
D45: 90 | E45: 570 | F45: =D45*E45 -> 51300
A46: Aster DM | D46: 20 | E46: 226 | F46: =D46*E46 -> 4520 | G46: 717 | H46: =D46*G46 -> 14340 | I46: =H46-F46 -> 9820 | J46: 2400 | K46: =I46/D46 -> 491
A47: Healthcare global | D47: 10 | E47: 279 | F47: =D47*E47 -> 2790 | G47: 572 | H47: =D47*G47 -> 5720 | I47: =H47-F47 -> 2930 | K47: =I47/D47 -> 293 | N47: 45050
A48: SYNGENE INTERNATIONAL LTD | D48: 347 | E48: 568 | F48: =D48*E48 -> 197096 | G48: 467 | H48: =D48*G48 -> 162049 | I48: =H48-F48 -> -35047 | J48: 780.75 | K48: =I48/D48 -> -101
A49: Jubiliant Ingrevia | D49: 180 | E49: 300 | F49: =D49*E49 -> 54000 | G49: 713 | H49: =D49*G49 -> 128340 | I49: =H49-F49 -> 74340 | J49: 2763 | K49: =I49/D49 -> 413
A50: CAPLIN POINT LAB LTD. | D50: 10 | E50: 560 | F50: =D50*E50 -> 5600 | G50: 2327 | H50: =D50*G50 -> 23270 | I50: =H50-F50 -> 17670 | J50: 115 | K50: =I50/D50 -> 1767 | Q50: recDate | R50: payDate | S50: AGM
A51: FDC | D51: 20 | E51: 268 | F51: =D51*E51 -> 5360 | G51: 594 | H51: =D51*G51 -> 11880 | I51: =H51-F51 -> 6520 | K51: =I51/D51 -> 326
A52: SuvenPharma | D52: 20 | E52: 482 | F52: =D52*E52 -> 9640 | G52: 483 | H52: =D52*G52 -> 9660 | I52: =H52-F52 -> 20 | J52: 240 | K52: =I52/D52 -> 1 | S52: 45924
A53: RPG life | D53: 3 | E53: 829 | F53: 2295 | G53: 2508 | H53: =D53*G53 -> 7524 | I53: =H53-F53 -> 5229 | J53: 36 | K53: =I53/D53 -> 1743 | O53: TCS
A54: IndocoRemidies | D54: 30 | E54: 279 | F54: =D54*E54 -> 8370 | G54: 236 | H54: =G54*D54 -> 7080 | I54: =H54-F54 -> -1290 | J54: 180 | K54: =I54/D54 -> -43
A55: LAURUS LABS LIMITED | D55: 436 | E55: 388 | F55: =D55*E55 -> 169168 | G55: 1373 | H55: =D55*G55 -> 598628 | I55: =H55-F55 -> 429460 | J55: 3188 | K55: =I55/D55 -> 985 | N55: 45953
A56: Strides Pharma | D56: 145 | E56: 769 | F56: =D56*E56 -> 111505 | G56: 1183 | H56: =D56*G56 -> 171535 | I56: =H56-F56 -> 60030 | J56: 555 | K56: =I56/D56 -> 414
A57: onesource speciality | D57: 72 | G57: 1849 | H57: =D57*G57 -> 133128 | N57: suru | O57: onward technology
A58: Biocon | D58: 10 | E58: 457 | F58: =D58*E58 -> 4570 | G58: 419 | H58: =D58*G58 -> 4190 | I58: =H58-F58 -> -380 | J58: 30 | K58: =I58/D58 -> -38 | N58: suru | O58: All E Technologies Ltd
M59: =22*2 -> 44
A60: RELIANCE INDUSTRIES LTD | D60: 56 | E60: 1216 | F60: =D60*E60 -> 68096 | G60: 1223 | H60: =D60*G60 -> 68488 | I60: =H60-F60 -> 392 | J60: 240 | K60: =I60/D60 -> 7 | M60: 45510
A61: jio financial | D61: 10 | E61: 93.58 | F61: =D61*E61 -> 935.8 | G61: 362 | H61: =D61*G61 -> 3620 | I61: =H61-F61 -> 2684.2 | K61: =I61/D61 -> 268.42
A62: IDFC LIMITED | D62: 10 | E62: 160 | F62: =D62*E62 -> 1600 | G62: 118 | H62: =D62*G62 -> 1180 | I62: =H62-F62 -> -420 | J62: 161.5 | K62: =I62/D62 -> -42 | M62: 45510
A63: IDFC FIRST BANK LIMITED | D63: 111 | E63: 77 | F63: =D63*E63 -> 8547 | G63: 90 | H63: =D63*G63 -> 9990 | I63: =H63-F63 -> 1443 | J63: 170 | K63: =I63/D63 -> 13
A64: ICICI BANK LTD. | C64: 436 | D64: 11 | E64: 364 | F64: =D64*E64 -> 4004 | G64: 1465 | H64: =D64*G64 -> 16115 | I64: =H64-F64 -> 12111 | J64: 377.5 | K64: =I64/D64 -> 1101 | S64: 9845904598
A65: HDFC LIFE INS CO LTD | D65: 10 | E65: 443 | F65: =D65*E65 -> 4430 | G65: 780 | H65: =D65*G65 -> 7800 | I65: =H65-F65 -> 3370 | J65: 72.3 | K65: =I65/D65 -> 337 | S65: 9620433281
A66: Tata Investment Corp | C66: 614 | D66: 40 | E66: 146 | F66: =D66*E66 -> 5840 | G66: 889 | H66: =D66*G66 -> 35560 | I66: =H66-F66 -> 29720 | J66: 412 | S66: 9341711885
A68: MOTHERSON SUMI SYSTEMS LT | D68: 45 | E68: 57 | F68: =D68*E68 -> 2565 | G68: 120 | H68: =D68*G68 -> 5400 | I68: =H68-F68 -> 2835 | J68: 30 | K68: =I68/D68 -> 63
A69: Motherson sumi wiring india | D69: 42 | E69: 0 | F69: =D69*E69 -> 0 | G69: 43.81 | H69: =D69*G69 -> 1840.02 | I69: =H69-F69 -> 1840.02 | J69: 31.2 | K69: =I69/D69 -> 43.81
A72: Heritage foods | D72: 20 | E72: 184 | F72: =D72*E72 -> 3680 | G72: 628 | H72: =D72*G72 -> 12560 | I72: =H72-F72 -> 8880 | J72: 50 | K72: =I72/D72 -> 444
A73: IFCI-9.16%-IV-15-2-27-C-PVT | D73: 4 | E73: 5000 | F73: =D73*E73 -> 20000 | G73: 13226 | H73: =D73*G73 -> 52904 | I73: =H73-F73 -> 32904 | K73: =I73/D73 -> 8226
A74: CASTROL INDIA LIMITED | D74: 53 | E74: 162 | F74: =D74*E74 -> 8586 | G74: 270 | H74: =D74*G74 -> 14310 | I74: =H74-F74 -> 5724 | J74: 1290 | K74: =I74/D74 -> 108 | L74: sold | M74: 45300
A76: SuvenLS | D76: 100 | E76: 99 | F76: =D76*E76 -> 9900 | G76: 132 | H76: =D76*G76 -> 13200 | I76: =H76-F76 -> 3300 | K76: =I76/D76 -> 33
A78: Jubiliant Pharmova | D78: 70 | E78: 735 | F78: =D78*E78 -> 51450 | G78: 850 | H78: =D78*G78 -> 59500 | I78: =H78-F78 -> 8050 | J78: 1400 | K78: =I78/D78 -> 115
F84: =SUM(F14:F81) -> 1609726.3
F85: -1530
E86: 1787915 | F86: =SUM(F84:F85) -> 1608196.3 | G86: =E86-F86 -> 179718.7 | J86: =SUM(J14:J81) -> 129109
A87: KOTHARI PRODUCTS LTD | D87: 10 | E87: 153 | F87: =D87*E87 -> 1530 | G87: 158 | H87: =D87*G87 -> 1580 | I87: =H87-F87 -> 50 | J87: 25 | K87: =I87/D87 -> 5
A88: JAYPEE INFRATECH LTD | D88: 100 | E88: 100 | F88: =D88*E88 -> 10000 | G88: 1.55 | H88: =D88*G88 -> 155 | I88: =H88-F88 -> -9845
A89: SEQUENT SCIENTIFIC LTD. | D89: 60 | E89: 209 | F89: =D89*E89 -> 12540 | G89: 208 | H89: =D89*G89 -> 12480 | I89: =H89-F89 -> -60 | K89: =I89/D89 -> -1

Sheet Dividend
C1: security | I1: Ductile Iron Pipes Industry | J1: https://twitter.com/FinMedium/status/1536372936902201344
A2: 42815 | B2: 42815 | C2: COAL INDIA LTD-- | F2: 375 | G2: 20*18.75rs | I2: Electric Resistance Welded | J2: https://twitter.com/FinMedium/status/1535644455327236102
A3: 42824 | B3: 42824 | C3: BHARAT PETROLE-- | F3: 120 | G3: 10*12rs | I3: Battery | J3: https://twitter.com/FinMedium/status/1533475302411685888
A4: 42824 | B4: 42824 | C4: HINDUSTAN PETR-- | F4: 76.8 | G4: 12*6.4rs | H4: 6.4 | I4: pharma | J4: generic
A5: 42825 | B5: 42825 | C5: COAL INDIA LTD-- | F5: 23 | G5: 20*1.15rs | I5: pharma | J5: branded generic
A6: 42888 | B6: 42888 | C6: HCL TECHNOLOGI-- | F6: 60 | G6: 20*3rs | I6: pharma | J6: API, CDMO
A7: 42906 | B7: 42906 | C7: CR FIN DIV DEC-- | F7: 45 | I7: pharma | J7: Hospital
A8: 42917 | B8: 42917 | C8: ICICI BANK LTD-- | F8: 25 | G8: 10*2.5rs | I8: pharma | J8: Diagnostic
A9: 42942 | B9: 42942 | C9: Persistent Sys-- | F9: 30 | I9: Seemless pipe
A10: 42947 | B10: 42947 | C10: IDFC LTD-- | F10: 2.5
A11: 42947 | B11: 42947 | C11: IDFC BANK LIMI-- | F11: 83.25
A12: 42958 | B12: 42958 | C12: HCL TECHNOLOGI-- | F12: 20 | G12: 20*1rs
A13: 42991 | B13: 42991 | C13: Castrol India-- | F13: 45 | G13: 10*4.5rs
A14: 42997 | B14: 42997 | C14: HINDUSTAN PETR-- | F14: 24.2 | G14: 22*1.1rs | H14: 1.1
A15: 43000 | B15: 43000 | C15: BHARAT PETROLE-- | F15: 10 | G15: 10*1rs
A16: 43011 | B16: 43011 | C16: GAIL (INDIA) L-- | F16: 54 | G16: 20*2.7rs
A17: 43048 | B17: 43048 | C17: HCL TECHNOLOGI-- | F17: 20 | G17: 20*1rs | I17: 109881 | J17: 45939
A18: 42404 | C18: HCL TECHNOLOGI-- | F18: 60 | G18: 20*3rs | I18: =1250*12 -> 15000 | J18: =SUM(I17,J17) -> 155820
A19: 42503 | C19: HCL TECHNOLOGI-- | F19: 60 | G19: 20*3rs | I19: =I17-I18 -> 94881
A20: 42601 | C20: HCL TECHNOLOGI-- | F20: 60 | G20: 20*3rs | I20: =SUM(I17,I19) -> 204762
A21: 42681 | C21: HCL TECHNOLOGI-- | F21: 60 | G21: 20*3rs | I21: 45939
A22: 42563 | C22: ICICI BANK LTD-- | F22: 50 | G22: 10*5rs | I22: =SUM(I20:I21) -> 250701
A23: 42580 | C23: IDFC BANK LIMI-- | F23: 3
A24: 42129 | C24: HCL TECHNOLOGI-- | F24: 40 | G24: 20*2rs
A25: 42233 | C25: HCL TECHNOLOGI-- | F25: 50 | G25: 20*2.5rs
A26: 42310 | C26: HCL TECHNOLOGI-- | F26: 50 | G26: 20*2.5rs
A27: 43130 | B27: 43130 | C27: GAIL (INDIA) L-- | F27: 153 | G27: 20*7.65rs
A28: 43136 | B28: 43136 | C28: HCL TECHNOLOGI-- | F28: 20 | G28: 20*1rs
A29: 43139 | B29: 43139 | C29: Persistent Sys-- | F29: 70
A30: 43164 | B30: 43164 | C30: BHARAT PETROLE-- | F30: 420 | G30: 30*14rs
A31: 43166 | B31: 43166 | C31: HINDUSTAN PETR-- | F31: 478.5 | G31: 33*14.5 | H31: 14.5
A32: 43182 | B32: 43182 | C32: COAL INDIA LTD-- | F32: 330 | G32: 20*16.5rs
A33: 43237 | B33: 43237 | C33: HCL TECHNOLOGI-- | F33: 20 | G33: 20*1rs
A34: 43238 | B34: 43238 | C34: Castrol India-- | F34: 50 | G34: 20*2.5rs
A35: 43314 | B35: 43314 | C35: Persistent Sys-- | F35: 30
A36: 43314 | B36: 43314 | C36: IDFC BANK LIMI-- | F36: 83.25
A37: 43315 | B37: 43315 | C37: IDFC LTD-- | F37: 7.5
A38: 43326 | B38: 43326 | C38: HCL TECHNOLOGI-- | F38: 20 | G38: 20*1rs
A39: 43333 | B39: 43333 | C39: Castrol India-- | F39: 45 | G39: 20*2.25rs
A40: 43346 | B40: 43346 | C40: HINDUSTAN PETR-- | F40: 82.5 | G40: 33*2.5rs | H40: 2.5
A41: 43347 | B41: 43347 | C41: INDIAN OIL COR-- | F41: 20 | G41: 10*2rs | H41: 2
A42: 43356 | B42: 43356 | C42: ICICI BANK LTD-- | F42: 16.5 | G42: 11*1.5rs
A43: 43364 | B43: 43364 | C43: BHARAT PETROLE-- | F43: 210 | G43: 30*7rs
A44: 43372 | B44: 43372 | C44: GAIL (INDIA) L-- | F44: 57.6 | G44: 40*1.44
A45: 43378 | B45: 43378 | C45: OIL INDIA LIMI-- | F45: 15 | G45: 15*1rs
A46: 43378 | B46: 43378 | C46: OIL AND NATURA-- | F46: 14 | G46: 10*1.35rs
A47: 43381 | B47: 43381 | C47: KOTHARI PRODUC-- | F47: 15 | G47: 15*1rs
A48: 43413 | B48: 43413 | C48: HCL TECHNOLOGI-- | F48: 20 | G48: 20*1rs
A49: 43462 | B49: 43462 | C49: INDIAN OIL COR-- | F49: 135 | G49: 20*6.75rs | H49: 6.75
A50: 43470 | B50: 43470 | C50: COAL INDIA LTD-- | F50: 218 | G50: 30*7.25rs
A51: 43493 | B51: 43493 | C51: INFOSYS LIMITE-- | F51: 120 | G51: 30*4rs
A52: 43507 | B52: 43507 | C52: Persistent Sys-- | F52: 80
A53: 43510 | B53: 43510 | C53: HCL TECHNOLOGI-- | F53: 20 | G53: 20*1rs
A54: 43516 | B54: 43516 | C54: HINDUSTAN PETR-- | F54: 429 | G54: 66*6.5rs | H54: 6.5
A55: 43518 | B55: 43518 | C55: GAIL (INDIA) L-- | F55: 250 | G55: 40*6.25rs
A56: 43529 | B56: 43529 | C56: BHARAT PETROLE-- | F56: 440 | G56: 40*11rs
A57: 43531 | C57: OIL AND NATURA-- | F57: 158 | G57: 30*5.25rs
A58: 43532 | C58: OIL INDIA LIMI-- | F58: 127.5 | G58: 15*8.5rs
A59: 43546 | C59: HDFC LIFE INSU | F59: 16.3 | G59: 10*1.63rs
A60: 43553 | C60: COAL INDIA LTD-- | F60: 234 | G60: 40*5.85rs
A61: 43554 | C61: INDIAN OIL COR-- | F61: 30 | G61: 20*1.5rs | H61: 1.5
A62: 43557 | C62: OIL AND NATURA-- | F62: 30 | G62: 30*1rs
A63: 43609 | C63: HCL TECHNOLOGI-- | F63: 20 | G63: 20*1rs
A64: 43606 | C64: Castrol India-- | F64: 82.5 | G64: 30*2.75rs
A65: 43679 | C65: Persistent Sys-- | F65: 30
A66: 43690 | C66: ICICI BANK LTD-- | F66: 11 | G66: 11*1rs
A67: 43698 | C67: MothersonSumi | F67: 15
A68: 43698 | C68: Castrol India-- | F68: 75 | G68: 30*2.5rs
A69: 43700 | C69: HINDUSTAN PETR-- | F69: 620 | G69: 66*9.4rs | H69: 9.4
A70: 43703 | C70: HCL TECHNOLOGI-- | F70: 20 | G70: 20*1rs
A71: 43705 | C71: OIL INDIA LIMI-- | F71: 26.25 | G71: 15*1.75rs
A72: 43711 | C72: INDIAN OIL COR-- | F72: 20 | G72: 20*1rs | H72: 1
A73: 43713 | C73: GAIL (INDIA) L-- | F73: 70.8 | G73: 40*1.77rs
A74: 43714 | C74: OIL AND NATURA-- | F74: 23 | G74: 30*0.75rs
A75: 43719 | C75: BHARAT PETROLE-- | F75: 320 | G75: 40*8rs
A76: 43742 | C76: IDFC LTD-- | F76: 25
A77: 43742 | C77: KOTHARI PRODUC-- | F77: 10
A78: 43768 | C78: INFOSYS LIMITE-- | F78: 240 | G78: 30*8rs
A79: 43777 | C79: HCL TECHNOLOGI-- | F79: 20 | G79: 20*1rs
A80: 43796 | C80: IDFC LTD-- | F80: 6.5
A81: 43865 | C81: HCL TECHNOLOGI-- | F81: 40 | G81: 20*2rs
A82: 43874 | C82: Persistent Sys-- | F82: 90
A83: 43889 | C83: GAIL (INDIA) L-- | F83: 512 | G83: 6.4*80
A84: 43889 | C84: OIL INDIA LIMI-- | F84: 135 | G84: 15*9rs
A85: 43907 | C85: MothersonSumi | F85: 15
A86: 43914 | C86: Persistent Sys-- | F86: 30
A87: 43916 | C87: COAL INDIA LTD-- | F87: 480 | G87: 40*12rs
A88: 43917 | C88: INDIAN OIL COR-- | F88: 85 | G88: 20*4.25rs | H88: 4.25
A89: 43917 | C89: BHARAT PETROLE-- | F89: 660 | G89: 40*16.5rs
A90: 43917 | C90: OIL AND NATURA-- | F90: 150 | G90: 30*5rs
A91: 44015 | C91: INFOSYS LIMITE-- | F91: 285 | G91: 30*9.5rs
A92: 44021 | C92: Castrol India-- | F92: 90 | G92: 30*3rs
A93: 44050 | C93: HCL TECHNOLOGI-- | F93: 40 | G93: 20*2rs
A94: 44093 | C94: HINDUSTAN PETR-- | F94: 643.5 | G94: 66*9.75rs | H94: 9.75
A95: 44109 | C95: HCL TECHNOLOGI-- | F95: 40 | G95: 20*2rs
A96: 44116 | C96: OIL INDIA LIMI-- | F96: 24 | G96: 15*1.6rs
A97: 44144 | C97: HCL TECHNOLOGI-- | F97: 80 | G97: 20*4rs
A98: 44146 | C98: INFOSYS LIMITE-- | F98: 360 | G98: 30*3rs
A99: 44154 | C99: LAURUS LABS LI | F99: 8
A100: 44159 | C100: Castrol India-- | F100: 75 | G100: 30*2.5rs
...

Sheet Pharma
A1: Laurus | F1: Syngene | K1: Neuland | P1: SeQuent | U1: Hikal | Z1: Jubiliant Pharma | AE1: SuvenPharma | AJ1: IndocoRemidies | AO1: ITC | AT1: UnitedSpirit | AY1: Praj Industries | BD1: Strides pharma
A2: DOP | B2: Qty | C2: Price | F2: DOP | G2: Qty | H2: Price | K2: DOP | L2: Qty | M2: Price | P2: DOP | Q2: Qty | R2: Price | U2: DOP | V2: Qty | W2: Price | Z2: DOP | AA2: Qty | AB2: Price | AE2: DOP | AF2: Qty | AG2: Price | AJ2: DOP | AK2: Qty | AL2: Price | AO2: DOP | AP2: Qty | AQ2: Price | AT2: DOP | AU2: Qty | AV2: Price | AY2: DOP | AZ2: Qty | BA2: Price | BD2: DOP | BE2: Qty | BF2: Price
A3: 44120 | B3: 10 | C3: 325 | D3: =B3*C3 -> 3250 | F3: 44166 | G3: 10 | H3: 569.7 | I3: =G3*H3 -> 5697 | K3: 44174 | L3: 10 | M3: 1130 | N3: =L3*M3 -> 11300 | P3: 44141 | Q3: 10 | R3: 155 | S3: =Q3*R3 -> 1550 | U3: 44253 | V3: 10 | W3: 164 | X3: =V3*W3 -> 1640 | Z3: 44251 | AA3: 10 | AB3: 776 | AC3: =AA3*AB3 -> 7760 | AE3: 44251 | AF3: 10 | AG3: 487 | AH3: =AF3*AG3 -> 4870 | AJ3: 44120 | AK3: 10 | AL3: 258 | AM3: =AK3*AL3 -> 2580 | AO3: 44251 | AP3: 10 | AQ3: 209 | AR3: =AP3*AQ3 -> 2090 | AT3: 44251 | AU3: 10 | AV3: 553 | AW3: =AU3*AV3 -> 5530 | AY3: 44335 | AZ3: 10 | BA3: 395 | BB3: =AZ3*BA3 -> 3950 | BD3: 44335 | BE3: 20 | BF3: 812 | BG3: =BE3*BF3 -> 16240
A4: 44161 | B4: 30 | C4: 298 | D4: =B4*C4 -> 8940 | F4: 44174 | G4: 10 | H4: 600.55 | I4: =G4*H4 -> 6005.5 | K4: 44186 | L4: 10 | M4: 1010 | N4: =L4*M4 -> 10100 | P4: 44186 | Q4: 10 | R4: 165 | S4: =Q4*R4 -> 1650 | U4: 44270 | V4: 10 | W4: 160 | X4: =V4*W4 -> 1600 | Z4: 44253 | AA4: 10 | AB4: 758 | AC4: =AA4*AB4 -> 7580 | AE4: 44253 | AF4: 10 | AG4: 480 | AH4: =AF4*AG4 -> 4800 | AJ4: 44174 | AK4: 10 | AL4: 299 | AM4: =AK4*AL4 -> 2990 | AO4: 44253 | AP4: 20 | AQ4: 206 | AR4: =AP4*AQ4 -> 4120 | AT4: 44253 | AU4: 10 | AV4: 545 | AW4: =AU4*AV4 -> 5450 | AY4: 44342 | AZ4: 10 | BA4: 366 | BB4: =AZ4*BA4 -> 3660 | BD4: 44344 | BE4: 10 | BF4: 804 | BG4: =BE4*BF4 -> 8040
A5: 44166 | B5: 100 | C5: 326 | D5: =B5*C5 -> 32600 | F5: 44186 | G5: 10 | H5: 590.15 | I5: =G5*H5 -> 5901.5 | K5: 44187 | L5: 10 | M5: 996 | N5: =L5*M5 -> 9960 | P5: 44251 | Q5: 10 | R5: 240 | S5: =Q5*R5 -> 2400 | X5: =SUM(X3:X4) -> 3240 | Z5: 44260 | AA5: 10 | AB5: 764 | AC5: =AA5*AB5 -> 7640 | AJ5: 44186 | AK5: 10 | AL5: 263 | AM5: =AK5*AL5 -> 2630 | AO5: 44270 | AP5: 10 | AQ5: 202 | AR5: =AP5*AQ5 -> 2020 | AT5: 44526 | AU5: 10 | AV5: 892 | AW5: =AU5*AV5 -> 8920 | AY5: 44344 | AZ5: 10 | BA5: 339 | BB5: =AZ5*BA5 -> 3390 | BD5: 44364 | BE5: 30 | BF5: 793 | BG5: =BE5*BF5 -> 23790 | BI5: =23717/30 -> 790.56667
A6: 44174 | B6: 10 | C6: 335 | D6: =B6*C6 -> 3350 | F6: 44187 | G6: 30 | H6: 576.05 | I6: =G6*H6 -> 17281.5 | P6: 44267 | Q6: 10 | R6: 238 | S6: =Q6*R6 -> 2380 | W6: 464 | X6: =20*464 -> 9280 | Z6: 44377 | AA6: 20 | AB6: 739 | AC6: =AA6*AB6 -> 14780 | AH6: =SUM(AH3:AH5) -> 9670 | AM6: =SUM(AM3:AM5) -> 8200 | AO6: 44349 | AP6: 100 | AQ6: 209 | AR6: =AP6*AQ6 -> 20900 | AT6: 44547 | AU6: 20 | AV6: 887 | AW6: =AU6*AV6 -> 17740 | AY6: 44332 | AZ6: 4 | BA6: 327 | BB6: =AZ6*BA6 -> 1308 | BD6: 44365 | BE6: 25 | BF6: 779 | BG6: =BE6*BF6 -> 19475
A7: 44186 | B7: 50 | C7: 333 | D7: =B7*C7 -> 16650 | F7: 44211 | G7: 50 | H7: 603.1 | I7: =G7*H7 -> 30155 | L7: =SUM(L3:L5) -> 30 | N7: =SUM(N3:N5) -> 31360 | P7: 44270 | Q7: 10 | R7: 229 | S7: =Q7*R7 -> 2290 | Z7: 44412 | AA7: 20 | AB7: 670 | AC7: =AA7*AB7 -> 13400 | AH7: =AH6/20 -> 483.5 | AO7: 44377 | AP7: 50 | AQ7: 204 | AR7: =AP7*AQ7 -> 10200 | AT7: 44550 | AU7: 20 | AV7: 868 | AW7: =AU7*AV7 -> 17360 | BD7: 44370 | BE7: 10 | BF7: 770 | BG7: =BE7*BF7 -> 7700
A8: 44187 | B8: 50 | C8: 331 | D8: =B8*C8 -> 16550 | F8: 44218 | G8: 50 | H8: 585 | I8: =G8*H8 -> 29250 | N8: =N7/L7 -> 1045.3333 | P8: 44270 | Q8: 10 | R8: 230 | S8: =Q8*R8 -> 2300 | AO8: 44526 | AP8: 20 | AQ8: 224 | AR8: =AP8*AQ8 -> 4480 | AT8: 44720 | AU8: 7 | AV8: 770.6 | AW8: =AU8*AV8 -> 5394.2 | BD8: 44404 | BE8: 20 | BF8: 757 | BG8: =BE8*BF8 -> 15140
A9: 44251 | B9: 10 | C9: 365 | D9: =B9*C9 -> 3650 | F9: 44251 | G9: 10 | H9: 562 | I9: =G9*H9 -> 5620 | M9: 2700 | N9: =L7*M9 -> 81000 | AA9: =SUM(AA3:AA7) -> 70 | AC9: =SUM(AC3:AC7) -> 51160 | AO9: 44529 | AP9: 10 | AQ9: 221 | AR9: =AP9*AQ9 -> 2210 | AT9: 44728 | AU9: 5 | AV9: 755 | AW9: =AU9*AV9 -> 3775 | BD9: 44405 | BE9: 20 | BF9: 744 | BG9: =BE9*BF9 -> 14880
A10: 44253 | B10: 20 | C10: 356 | D10: =B10*C10 -> 7120 | F10: 44253 | G10: 10 | H10: 557 | I10: =G10*H10 -> 5570 | Q10: =SUM(Q3:Q9) -> 60 | S10: =SUM(S3:S9) -> 12570 | AC10: =AC9/AA9 -> 730.85714 | AO10: 44536 | AP10: 30 | AQ10: 219 | AR10: =AP10*AQ10 -> 6570 | AT10: 44979 | AU10: 2 | AV10: 744.4 | AW10: =AU10*AV10 -> 1488.8 | BD10: 44456 | BE10: 10 | BF10: 619 | BG10: =BE10*BF10 -> 6190
A11: 44273 | B11: 10 | C11: 347 | D11: =B11*C11 -> 3470 | F11: 44257 | G11: 55 | H11: 555.5 | I11: =G11*H11 -> 30552.5 | N11: =N9-N7 -> 49640 | S11: =S10/Q10 -> 209.5 | AO11: 44676 | AP11: 10 | AQ11: 255 | AR11: =AP11*AQ11 -> 2550 | AT11: 44986 | AU11: 1 | AV11: 739.5 | AW11: =AU11*AV11 -> 739.5 | AZ11: =SUM(AZ3:AZ9) -> 34 | BB11: =SUM(BB3:BB10) -> 12308
A12: 44526 | B12: 10 | C12: 526 | D12: =B12*C12 -> 5260 | F12: 44260 | G12: 20 | H12: 544 | I12: =G12*H12 -> 10880 | AO12: 44697 | AP12: 3 | AQ12: 254 | AR12: =AP12*AQ12 -> 762 | AT12: 44995 | AU12: 1 | AV12: 738.8 | AW12: =AU12*AV12 -> 738.8 | BB12: =BB11/AZ11 -> 362
A13: 44529 | B13: 35 | C13: 509 | D13: =B13*C13 -> 17815 | F13: 44267 | G13: 20 | H13: 539.5 | I13: =G13*H13 -> 10790 | P13: Tata consumer | AO13: 44775 | AP13: 200 | AQ13: 308 | AR13: =AP13*AQ13 -> 61600 | AT13: 44985 | AU13: 20 | AV13: 1148 | AW13: =AU13*AV13 -> 22960 | BB13: 370.3 | BE13: =SUM(BE3:BE10) -> 145 | BG13: =SUM(BG3:BG10) -> 111455
A14: 44547 | B14: 40 | C14: 501 | D14: =B14*C14 -> 20040 | F14: 44270 | G14: 10 | H14: 540 | I14: =G14*H14 -> 5400 | P14: DOP | Q14: Qty | R14: Price | AO14: 45357 | AP14: 50 | AQ14: 409 | AR14: =AP14*AQ14 -> 20450 | BG14: =BG13/BE13 -> 768.65517
A15: 44550 | B15: 10 | C15: 483 | D15: =B15*C15 -> 4830 | F15: 44271 | G15: 10 | H15: 533 | I15: =G15*H15 -> 5330 | P15: 44690 | Q15: 1 | R15: 759 | S15: =Q15*R15 -> 759 | Z15: Jubiliant Ingrevia | AE15: SuvenLS | AU15: =SUM(AU3:AU14) -> 106 | AW15: =SUM(AW3:AW13) -> 90096.3 | BG15: 581
A16: 44579 | B16: 30 | C16: 505 | D16: =B16*C16 -> 15150 | F16: 44273 | G16: 35 | H16: 516 | I16: =G16*H16 -> 18060 | P16: 44693 | Q16: 1 | R16: 729 | S16: =Q16*R16 -> 729 | Z16: DOP | AA16: Qty | AB16: Price | AE16: DOP | AF16: Qty | AG16: Price | AW16: =AW15/AU15 -> 849.96509 | BG16: =135*BG15 -> 78435
A17: 44580 | B17: 21 | C17: 500 | D17: =B17*C17 -> 10500 | F17: 44277 | G17: 10 | H17: 496 | I17: =G17*H17 -> 4960 | P17: 44698 | Q17: 1 | R17: 723 | S17: =Q17*R17 -> 723 | Z17: 44278 | AA17: 180 | AB17: 300 | AC17: =AA17*AB17 -> 54000 | AE17: 44335 | AF17: 100 | AG17: 103 | AH17: =AF17*AG17 -> 10300 | BG17: =BG13-BG16 -> 33020
F18: 44690 | G18: 2 | H18: 565 | I18: =G18*H18 -> 1130 | P18: 44698 | Q18: 1 | R18: 724 | S18: =Q18*R18 -> 724 | AP18: =SUM(AP3:AP14) -> 513 | AR18: =SUM(AR3:AR14) -> 137952
F19: 44693 | G19: 2 | H19: 536 | I19: =G19*H19 -> 1072 | AR19: =AR18/AP18 -> 268.91228
F20: 44697 | G20: 1 | H20: 530 | I20: =G20*H20 -> 530 | S20: =AVERAGE(S15:S18) -> 733.75 | BE20: =145*300 -> 43500 | BF20: 111455 | BG20: =SUM(BE20:BF20) -> 154955
F21: 44697 | G21: 1 | H21: 528 | I21: =G21*H21 -> 528 | S21: 739.9 | Z21: Aster DM | AE21: FDC | AJ21: HealthCare | AO21: RPG life | BG21: =BG20/290 -> 534.32759
B22: =SUM(B3:B19) -> 436 | D22: =SUM(D3:D17) -> 169175 | F22: 44697 | G22: 1 | H22: 527 | I22: =G22*H22 -> 527 | P22: 44995 | Q22: 1 | R22: 704.6 | Z22: DOP | AA22: Qty | AB22: Price | AE22: DOP | AF22: Qty | AG22: Price | AJ22: DOP | AK22: Qty | AL22: Price | AO22: DOP | AP22: Qty | AQ22: Price
D23: =D22/B22 -> 388.01606 | Z23: 44978 | AA23: 5 | AB23: 230.75 | AE23: 44978 | AF23: 5 | AG23: 273.05 | AJ23: 44978 | AK23: 10 | AL23: 277.35 | AO23: 44978 | AP23: 1 | AQ23: 872.7
G24: =SUM(G3:G22) -> 347 | I24: =SUM(I3:I22) -> 195240 | Z24: 44979 | AA24: 5 | AB24: 226.7 | AE24: 44979 | AF24: 5 | AG24: 270 | AO24: 44979 | AP24: 1 | AQ24: 848.8
I25: =I24/G24 -> 562.6513 | Z25: 44986 | AA25: 10 | AB25: 220 | AE25: 44986 | AF25: 10 | AG25: 261.5 | AO25: 44995 | AP25: 1 | AQ25: 750.7
G26: =SUM(G8:G22) -> 237 | I26: =SUM(I8:I22) -> 130199.5 | J26: =I26/G26 -> 549.36498 | AA26: =SUM(AA23:AA25) -> 20 | AB26: =AVERAGE(AB23:AB25) -> 225.81667
G27: =SUM(G9:G22) -> 187 | I27: =SUM(I9:I22) -> 100949.5 | J27: =I27/G27 -> 539.8369
G28: =SUM(G7:G22) -> 287 | I28: =SUM(I7:I22) -> 160354.5 | J28: =I28/G28 -> 558.72648
A35: BPCL | F35: Castrol
A36: DOP | B36: Qty | C36: Price | F36: DOP | G36: Qty | H36: Price
A37: 42788 | B37: 10 | C37: 750 | D37: 7500 | F37: 42801 | G37: 10 | H37: 450 | I37: =G37*H37 -> 4500
A38: 42923 | B38: 10 | C38: 700 | D38: 7000 | F38: 43445 | G38: 10 | H38: 155 | I38: =G38*H38 -> 1550
A39: 43445 | B39: 10 | C39: 330 | D39: =B39*C39 -> 3300 | G39: 10 | H39: 0 | I39: 0
B40: 10 | C40: 0 | D40: 0 | F40: 44676 | G40: 10 | H40: 110 | I40: =G40*H40 -> 1100
A41: 44526 | B41: 40 | C41: 383 | D41: =B41*C41 -> 15320 | F41: 44690 | G41: 10 | H41: 110 | I41: 1100
A42: 44690 | B42: 10 | C42: 358 | D42: =B42*C42 -> 3580 | F42: 44693 | G42: 3 | H42: 100.7 | I42: =G42*H42 -> 302.1
A43: 44693 | B43: 2 | C43: 337.5 | D43: =B43*C43 -> 675
A44: 44697 | B44: 3 | C44: 335.2 | D44: =B44*C44 -> 1005.6 | G44: =SUM(G37:G43) -> 53 | I44: =SUM(I37:I43) -> 8552.1
I45: =I44/G44 -> 161.36038
B47: =SUM(B37:B46) -> 95 | D47: =SUM(D37:D46) -> 38380.6
D48: =D47/B47 -> 404.00632
Q51: 10
A52: Dabur | F52: Britannia | K52: Tata consumer | P52: RIL (1220)
A53: DOP | B53: Qty | C53: Price | F53: DOP | G53: Qty | H53: Price | K53: DOP | L53: Qty | M53: Price | P53: 44141 | Q53: 10 | R53: 1916 | S53: =Q53*R53 -> 19160
A54: 44659 | B54: 20 | C54: 565 | D54: =B54*C54 -> 11300 | F54: 44340 | G54: 10 | H54: 3385 | I54: =G54*H54 -> 33850 | K54: 44690 | L54: 1 | M54: 759 | N54: =L54*M54 -> 759 | P54: 45586 | Q54: 1 | R54: 2734 | S54: =Q54*R54 -> 2734
A55: 44686 | B55: 10 | C55: 534 | D55: =B55*C55 -> 5340 | F55: 44686 | G55: 7 | H55: 3337 | I55: =G55*H55 -> 23359 | K55: 44693 | L55: 1 | M55: 729 | N55: =L55*M55 -> 729 | P55: 45587 | Q55: 10 | R55: 2744 | S55: =Q55*R55 -> 27440
A56: 44690 | B56: 9 | C56: 509 | D56: =B56*C56 -> 4581 | F56: 44690 | G56: 2 | H56: 3250 | I56: =G56*H56 -> 6500 | K56: 44698 | L56: 1 | M56: 723 | N56: =L56*M56 -> 723 | P56: 45588 | Q56: 2 | R56: 2684 | S56: =Q56*R56 -> 5368
A57: 44697 | B57: 1 | C57: 498 | D57: =B57*C57 -> 498 | G57: =SUM(G54:G56) -> 19 | I57: =SUM(I54:I56) -> 63709 | K57: 44698 | L57: 1 | M57: 724 | N57: =L57*M57 -> 724 | P57: 45589 | Q57: 2 | R57: 2672 | S57: =Q57*R57 -> 5344
A58: 44697 | B58: 1 | C58: 497 | D58: =B58*C58 -> 497 | I58: =I57/G57 -> 3353.1053 | P58: 45590 | Q58: 3 | R58: 2664 | S58: =Q58*R58 -> 7992
A59: 44697 | B59: 1 | C59: 496 | D59: =B59*C59 -> 496 | G59: 19 | H59: 3400 | I59: =G59*H59 -> 64600 | N59: =AVERAGE(N54:N57) -> 733.75
A60: 44720 | B60: 1 | C60: 493 | D60: =B60*C60 -> 493 | I60: =I59-I57 -> 891 | N60: 739.9 | Q60: =SUM(Q53:Q58) -> 28 | S60: =SUM(S53:S58) -> 68038
A61: 44986 | B61: 1 | C61: 531.15 | D61: =B61*C61 -> 531.15 | S61: =S60/Q60 -> 2429.9286 | T61: 1214
E63: 540
A64: REC | F64: PowerGrid | K64: Petronet | P64: PFC | U64: ONGC
A65: 44722 | B65: 1 | C65: 117 | D65: =B65*C65 -> 117 | F65: 44693 | G65: 1 | H65: 235 | I65: =G65*H65 -> 235 | K65: 44693 | L65: 1 | M65: 208.5 | N65: =L65*M65 -> 208.5 | P65: 44332 | Q65: 2 | R65: 105 | S65: =Q65*R65 -> 210 | V65: 30 | W65: 155 | X65: =V65*W65 -> 4650
A66: 44725 | B66: 4 | C66: 115 | D66: =B66*C66 -> 460 | F66: 44720 | G66: 1 | H66: 224.5 | I66: =G66*H66 -> 224.5 | P66: 44363 | Q66: 20 | R66: 102.3 | S66: =Q66*R66 -> 2046 | U66: 44728 | V66: 10 | W66: 144 | X66: =V66*W66 -> 1440
A67: 44728 | B67: 10 | C67: 114 | D67: =B67*C67 -> 1140 | F67: 44721 | G67: 2 | H67: 222 | I67: =G67*H67 -> 444
A68: 44746 | B68: 10 | C68: 125.85 | D68: =B68*C68 -> 1258.5 | F68: 44728 | G68: 15 | H68: 220.8 | I68: =G68*H68 -> 3312 | V68: =SUM(V65:V66) -> 40 | X68: =SUM(X65:X66) -> 6090
B69: =SUM(B65:B68) -> 25 | C69: =25*128 -> 3200 | D69: =SUM(D65:D68) -> 2975.5 | X69: =X68/V68 -> 152.25
D70: =D69/B69 -> 119.02 | W70: =40*126 -> 5040
A72: 44789 | B72: 25 | C72: 136.5 | D72: =B72*C72 -> 3412.5 | E72: Sell
G73: =SUM(G65:G72) -> 19 | I73: =SUM(I65:I72) -> 4215.5 | Q73: =SUM(Q65:Q72) -> 22 | S73: =SUM(S65:S72) -> 2256
I74: =I73/G73 -> 221.86842 | S74: =S73/Q73 -> 102.54545
A75: GAIL | F75: CoalIndia | K75: IOCL | P75: HPCL | U75: OilIndia
B76: 74 | C76: 153.5 | D76: =B76*C76 -> 11359 | G76: 40 | H76: 294 | I76: =G76*H76 -> 11760 | L76: 20 | M76: 169 | N76: =L76*M76 -> 3380 | Q76: 66 | R76: 289 | S76: =Q76*R76 -> 19074 | U76: 43174 | V76: 5 | W76: 345 | X76: =V76*W76 -> 1725
A77: 44721 | B77: 10 | C77: 152 | D77: =B77*C77 -> 1520 | F77: 44721 | G77: 5 | H77: 199 | I77: =G77*H77 -> 995 | K77: 44721 | L77: 30 | M77: 118 | N77: =L77*M77 -> 3540 | P77: 44725 | Q77: 15 | R77: 227.8 | S77: =Q77*R77 -> 3417 | U77: 43175 | V77: 5 | W77: 340 | X77: =V77*W77 -> 1700
A78: 44722 | B78: 5 | C78: 149.5 | D78: =B78*C78 -> 747.5 | F78: 44722 | G78: 5 | H78: 197 | I78: =G78*H78 -> 985 | K78: 44722 | L78: 10 | M78: 117 | N78: =L78*M78 -> 1170 | P78: 44726 | Q78: 5 | R78: 217.06 | S78: =Q78*R78 -> 1085.3 | U78: 43186 | V78: 5 | W78: 0 | X78: 0
A79: 44725 | B79: 15 | C79: 146.5 | D79: =B79*C79 -> 2197.5 | F79: 44725 | G79: 16 | H79: 193 | I79: =G79*H79 -> 3088 | K79: 44725 | L79: 10 | M79: 114.2 | N79: =L79*M79 -> 1142 | P79: 44728 | Q79: 25 | R79: 215.3 | S79: =Q79*R79 -> 5382.5
A80: 44728 | B80: 10 | C80: 142.5 | D80: =B80*C80 -> 1425 | F80: 44728 | G80: 40 | H80: 186 | I80: =G80*H80 -> 7440 | K80: 44726 | L80: 2 | M80: 110.15 | N80: =L80*M80 -> 220.3
A81: 44809 | B81: 114 | C81: 136.6 | D81: =B81*C81 -> 15572.4 | F81: 44964 | G81: 10 | H81: 223 | I81: =G81*H81 -> 2230 | K81: 44728 | L81: 20 | M81: 108.8 | N81: =L81*M81 -> 2176 | Q81: 30 | R81: 224.3 | S81: =Q81*R81 -> 6729 | T81: =S81-S79 -> 1346.5 | V81: =SUM(V76:V80) -> 15 | X81: =SUM(X76:X80) -> 3425
K82: 44739 | L82: 258 | M82: 109.7 | N82: =L82*M82 -> 28302.6 | X82: =X81/V81 -> 228.33333
K83: 44740 | L83: 200 | M83: 109 | N83: =L83*M83 -> 21800 | Q83: =SUM(Q76:Q82) -> 141 | S83: =SUM(S76:S82) -> 35687.8
B84: =SUM(B76:B81) -> 228 | D84: =SUM(D76:D81) -> 32821.4 | S84: =S83/Q83 -> 253.10496
D85: =D84/B84 -> 143.95351
B86: 342 | D86: =D84/B86 -> 95.969006
G88: =SUM(G76:G81) -> 116 | I88: =SUM(I76:I81) -> 26498
I89: =I88/G88 -> 228.43103
A92: MIDHANI | F92: Globus | K92: Associated | P92: Piccadily
A93: 44721 | B93: 5 | C93: 171 | D93: =B93*C93 -> 855 | F93: 45554 | G93: 5 | H93: 1298 | I93: =G93*H93 -> 6490 | K93: 45554 | L93: 5 | M93: 979 | N93: =L93*M93 -> 4895 | P93: 45554 | Q93: 10 | R93: 780 | S93: =Q93*R93 -> 7800
A94: 44722 | B94: 5 | C94: 169 | D94: =B94*C94 -> 845 | F94: 45555 | G94: 5 | H94: 1294 | I94: =G94*H94 -> 6470 | L94: 5 | M94: 961 | N94: =L94*M94 -> 4805 | P94: 45554 | Q94: 5 | R94: 775 | S94: =Q94*R94 -> 3875
A95: 44725 | B95: 10 | C95: 166 | D95: =B95*C95 -> 1660 | F95: 45560 | G95: 10 | H95: 1223 | I95: =G95*H95 -> 12230 | L95: 5 | M95: 958 | N95: =L95*M95 -> 4790 | P95: 45554 | Q95: 10 | R95: 763 | S95: =Q95*R95 -> 7630
P96: 45555 | Q96: 10 | R96: 775 | S96: =Q96*R96 -> 7750
P97: 45561 | Q97: 10 | R97: 759 | S97: =Q97*R97 -> 7590
B98: =SUM(B93:B96) -> 20 | D98: =SUM(D93:D97) -> 3360
D99: =D98/B98 -> 168
A102: Radico | F102: USL (1050) | K102: wipro (558)
A103: 45554 | B103: 1 | C103: 2180 | D103: =B103*C103 -> 2180 | F103: 45559 | G103: 2 | H103: 1624 | I103: =G103*H103 -> 3248 | K103: 45586 | L103: 10 | M103: 551 | N103: =L103*M103 -> 5510
A104: 45555 | B104: 4 | C104: 2131 | D104: =B104*C104 -> 8524 | F104: 45560 | G104: 2 | H104: 1625 | I104: =G104*H104 -> 3250 | K104: 45587 | L104: 13 | M104: 557 | N104: =L104*M104 -> 7241
A105: 45560 | B105: 4 | C105: 2090 | D105: =B105*C105 -> 8360 | F105: 45562 | G105: 8 | H105: 1593 | I105: =G105*H105 -> 12744 | K105: 45589 | L105: 1 | M105: 556 | N105: =L105*M105 -> 556
A106: 45562 | B106: 5 | C106: 2084 | D106: =B106*C106 -> 10420 | F106: 45568 | G106: 4 | H106: 1561 | I106: =G106*H106 -> 6244 | K106: 45601 | L106: 10 | M106: 541 | N106: =L106*M106 -> 5410
A107: 45566 | B107: 3 | C107: 2023 | D107: =B107*C107 -> 6069 | F107: 45573 | G107: 3 | H107: 1516 | I107: =G107*H107 -> 4548 | K107: 45614 | L107: 1 | M107: 545 | N107: =L107*M107 -> 545
A108: 45573 | B108: 3 | C108: 1987 | D108: =B108*C108 -> 5961 | F108: 45575 | G108: 2 | H108: 1513 | I108: =G108*H108 -> 3026 | K108: 45628 | L108: 35 | M108: 0 | N108: =L108*M108 -> 0
F109: 45587 | G109: 13 | H109: 1491 | I109: =G109*H109 -> 19383 | K109: 45856 | L109: 55 | M109: 270 | N109: =L109*M109 -> 14850
F110: 45588 | G110: 5 | H110: 1476 | I110: =G110*H110 -> 7380
F111: 45589 | G111: 3 | H111: 1463 | I111: =G111*H111 -> 4389
F112: 45856 | G112: 5 | H112: 1365 | I112: =G112*H112 -> 6825 | L112: =SUM(L103:L109) -> 125 | N112: =SUM(N103:N109) -> 34112
B113: =SUM(B103:B112) -> 20 | D113: =SUM(D103:D111) -> 41514 | N113: =N112/L112 -> 272.896
D114: =D113/B113 -> 2075.7 | G114: 145 | I114: =SUM(I103:I112) -> 71037
I115: =I114/G114 -> 489.91034

Sheet usPw
A1: SBI | B1: Username | C1: Password
B2: susheelabhandari | C2: 3061sAN# | H2: EH1476 | I2: 1703815000 | K2: 124
B3: niranjana40 | C3: 3061sAN# | D3: Ninja06# | E3: 1078 | H3: lg5835 | I3: 6503815000 | K3: 60
A4: canarabank | B4: 100091921 | C4: Mumbai10# | D4: Nir | H4: EH6020 | I4: 5703815000 | K4: 185
B5: 100091939 | C5: Mumbai10# | D5: la | H5: LG12969 | I5: 5413815000 | J5: LQJG8068 | K5: 534
B6: 327068957 | C6: Mumbai10# | D6: Susheela | H6: LG12970 | I6: 2413815000 | K6: 166 | L6: niranjana970 | M6: 95od040
A7: Axis-sb | B7: niranjana40/961199961 | C7: Bangalore05#
A8: Trading | B8: 27n02 | C8: 05#Bangalore | H8: w-203554 | I8: Sunitha | J8: niranjana401 | L8: 1600210906
A9: comBackend | B9: 27N02 | C9: Ninja99# | H9: w-201681 | I9: Annapoornamma | J9: niranjana400 | K9: 95od040 | L9: 1600165842
A11: mfuonline | B11: niranjana40 | C11: 3061sAN$ | D11: L0litha05# | H11: 4269/25 | I11: 9-30-25 | J11: 1600165842
A12: jiraaf | B12: 9008255262 | C12: OTP | H12: 4269/25/1 | I12: 9-30-25/1 | J12: 1600210906
A13: ceridian | B13: 0108491116 | C13: 1033San# | H13: 923/a | I13: 8-71-24/1 | J13: 1600216766 | K13: 7875643915 | L13: 7271
A14: outlook | B14: niranjana40@hotmail.com | C14: Micr0service77# | H14: C1EH24819 | I14: 6560125000 | J14: niranjana405 | K14: FF
B15: latha.anantha@outlook.com | C15: Micr0service77# | H15: EH917 | I15: 5860125000 | K15: GF
B16: SahanaLKamble@outlook.com | C16: Micr0service77# | H16: W-291682080 | I16: waterbill
B17: susheelaabhandari@outlook.com | C17: Micr0service77#
A18: facebook | B18: niranjana40@gmail.com | C18: Saligrama08# | H18: 3507 | I18: 8-44-6(Niranjan) | J18: 1600238922 | K18: 9604273252 | L18: 11018
B19: latha.anantha@gmail.com | C19: Saligrama05# | H19: C1LG24237 | I19: 8778115000 | J19: niranjana407 | K19: shop
B20: kanirak8s@gmail.com | C20: Mysore05# | H20: C1EH34078 | I20: 6968115000 | J20: niranjana408 | K20: motor
A21: yahoo | B21: niranjana40@yahoo.com | C21: L0litha05# | H21: EH2410 | I21: 8098115000 | K21: GF
A22: gmail | B22: kambleanantha@gmail.com | C22: Bangalore05# | H22: EH29596 | I22: 8778115000 | K22: FF
B23: niranjan.kamble@gmail.com | C23: Vmware05# | H23: N-181853070 | I23: waterbill
B24: niranjanainvest@gmail.com | C24: Bangalore05#
B25: niranjana40@gmail.com | C25: Saligrama05# | H25: 4269 | J25: 1600165842 | L25: 7212
B26: niranjana.datta@gmail.com | C26: 95od040 | H26: 4269/25 | I26: 9-30-25/1 | J26: 1600210906 | L26: 1939
B27: latha.anantha@gmail.com | C27: Vmware05#
B28: SahanaLKamble@gmail.com | C28: L0litha05#
A30: po susheela | B30: 479223203 | C30: Saligrama05#
H32: sheethouse | I32: 9-42-10
A33: kaveri | B33: niranjana40@gmail.com | C33: YoP1ce7tUX | D33: f3u3aoWkWf | E33: pgb4IaC7iq | H33: LG26205 | I33: 7878015000 | J33: niranjana410
A34: irctc | B34: ndatta40 | C34: nac647 | H34: Jyothibakery | I34: 8-86-4(lakshman) | J34: 1600240227 | L34: 5590
A35: pgportal | B35: niranjana40 | C35: L0litha05# | H35: EH8739 | I35: 1133915000 | J35: niranjana411
A36: pf member | B36: 100260119784 | C36: Bangalore05# | H36: EH8738 | I36: 6323915000 | J36: niranjana412 | K36: 2nd floor
A37: csdl | B37: niranjana40 | C37: Bangalore77# | H37: EH42590 | I37: 4729522213 | J37: niranjana416
A38: opus | B38: niranjana40@gmail.com | C38: PA8Uw1lN
A39: LIC | B39: niranjana40 | C39: Saligrama08# | H39: bharat | I39: 1600907563 | K39: 4391523626
A40: MES | B40: 9008255262 | C40: L0litha05# | D40: https://meskkpu.edchemy.com/ | H40: cubbonpet | I40: 1600775883 | J40: 47-117-73/3 | K40: 2454721753
A41: bmrcl | B41: niranjana40@gmail.com | C41: Micr0service77#
I42: 786101134964
A43: jio | B43: niranjana40@yahoo.com | C43: 6360799936
B44: L0litha05#
A45: github | B45: https://github.com/niranjanadatta | C45: L0litha05#
A46: ITR | B46: CUGPS0461M | C46: Singapura05# | D46: Susheela
B47: CBYPL1591A | C47: Singapura05# | D47: latha
A49: LIC | B49: Policy #
B50: LIC Policy No. | C50: PREMIUM | D50: Sum assured | E50: Month | F50: StartDate | G50: Owner | H50: Maturity
A51: plan 88 | B51: 614014850 | C51: 3411 | D51: 100000 | E51: October | F51: 37082 | G51: Niranjan
A52: 108-25yrs | B52: 614014849 | C52: 7684 | D52: 100000 | E52: October | F52: 37082 | G52: Niranjan | H52: 46302
E55: 108-25
C56: 1 | D56: 37082
B57: 614010708 | C57: 2 | D57: 37447 | G57: 7271
C58: 3 | D58: 37812 | G58: 5590
C59: 4 | D59: 38178 | E59: 1 | F59: 50000 | G59: =SUM(G57:G58) -> 12861 | H59: =F59-G59 -> 37139
C60: 5 | D60: 38543
C61: 6 | D61: 38908
C62: 7 | D62: 39273
C63: 8 | D63: 39639 | E63: 1
C64: 9 | D64: 40004
C65: 10 | D65: 40369
C66: 11 | D66: 40734
C67: 12 | D67: 41100 | E67: 1
C68: 13 | D68: 41465
C69: 14 | D69: 41830
C70: 15 | D70: 42195 | E70: 1
C71: 16 | D71: 42561
C72: 17 | D72: 42926
C73: 18 | D73: 43291 | E73: 1
C74: 19 | D74: 43656

Sheet MF_usPw1
A1: HDFC | E1: Reliance | H1: Folio | I1: UserName | J1: Password | K1: Mpin | L1: inv Amount | M1: cur Value
A2: ~~~~~ | E2: niranjana40@gmail.com | G2: AdityaBirla | H2: 1035138323 | I2: niranjana40 | J2: Vmware05# | L2: 887909.31 | M2: 1166206.1 | O2: =M2-L2 -> 278296.81
A3: NIRANJANA40 | E3: Bangalore05# | G3: canara | H3: 1035138323 | I3: AMXPK8098D | J3: Nira#0708 | L3: 1189940 | M3: 1239464.9 | O3: =M3-L3 -> 49524.88
G4: Edelweiss | H4: 9021263714 | I4: AMXPK8098D | L4: 1189944 | M4: 1244624.9 | O4: =M4-L4 -> 54680.91
G5: Franklin | H5: 20788619 | I5: NIRANJANA401 | J5: L0litha06# | L5: 572786 | M5: 715214.27 | O5: =M5-L5 -> 142428.27
A6: tata | E6: birla | G6: HDFC | H6: 11813982 / 11 | I6: NIRANJANA40 | J6: B@ngalore10 | L6: 941985 | M6: 1178260.9 | O6: =M6-L6 -> 236275.88
A7: ~~~~ | G7: ICICI | H7: 9627534 | I7: niranjanainvest@gmail.com | J7: L0litha05# | L7: 1335262 | M7: 1571854.7 | O7: =M7-L7 -> 236592.73
A8: niranjana40@gmail.com | G8: Motilal | H8: 9042570574 | I8: AMXPK8098D | J8: OTP | K8: 1033 | L8: 1089945.5 | M8: 1190358 | O8: =M8-L8 -> 100412.5
A9: B@ng@l0re05# | G9: ParagParikh | H9: 12365905 | I9: mpin-1033 | L9: 1200000 | M9: 1471573 | O9: =M9-L9 -> 271573
E10: sundaram | G10: Quantum | H10: 9991575073 | I10: niranjanainvest@gmail.com | J10: B@ngalore05 | L10: 1561476 | M10: 2021397.4 | O10: =M10-L10 -> 459921.42
A11: birla | E11: niranjana40@gmail.com | G11: Nippon | H11: 404151011786 | I11: niranjana40@gmail.com | J11: L0litha05#
A12: ~~~~~~ | E12: L0litha05# | G12: sbi | H12: 17518549 | I12: niranjanainvest@gmail.com | J12: L0litha05#
A13: Vmware05# | G13: axis | H13: 91076308513
E14: bnp | G14: tata
A15: dspblackrock | E15: niranjana40@yahoo.com | G15: kotak
A16: ~~~~~~~~~~ | E16: L0litha05#
A17: NIRANJANA40
A18: L0litha05# | E18: quantum (24772)
L19: =SUM(L2:L10) -> 9969247.8 | M19: =SUM(M2:M10) -> 11798954
A20: canararobeco | M20: =M19-L19 -> 1829706.4
A21: ~~~~~~~~~~~~~
A22: Nira#0708 | E22: Principal
E23: niranjanainvest@gmail.com
A24: icici | E24: L0litha05# (76534 pin)
A25: ~~~~~~
A26: niranjanainvest@gmail.com
A27: L0litha05#
A29: dspblackrock
A30: ~~~~~~~
A31: NIRANJANA40
A32: L0litha05#
A34: Franklin
A35: ~~~~~~~~
A36: NIRANJANA401
A37: L0litha06#
A39: sbi MF
... A62: L0litha05#

Sheet Others
A1: Mantralaya | B1: kammasandra | C1: Nanjangud | D1: 1 | F1: Guru | H1: Ghati subramanya | I1: shivagange
A2: ganagapura | B2: DevarayanaDurga | C2: dharmasthala | D2: 2 | F2: Sringeri | H2: namada chilume | I2: devarayandurga | J2: Ghati | N2: kammasandra
A3: Sringeri | B3: savanaDurga | C3: mrigavadhe | D3: 3 | F3: Udupi Krishna | H3: Srirangapatna-ranganthaswamy | I3: namadaChilume | J3: DD hills | N3: seebi
A4: tirupati | B4: seebi narasimhaswamy | C4: Gokarna | D4: 4 | F4: gangapura | G4: 44587 | H4: mekedaatu/sangama | I4: kaidala | J4: himvad gopalswamy | N4: devarayanabetta
A5: Pandarapura | B5: Melukote | C5: Murdeshwar | D5: 5 | F5: Mantralaya | G5: 44633 | H5: aprameya | I5: seebi | J5: kalale | N5: melukote
A6: Udupi | B6: T.Narasipura-Gunja Narasimha | D6: 6 | F6: nava brindavana | G6: 44665 | H6: aprameya,Srirangapatna, keretonnur, Melukote | I6: goravanhalli | J6: nanjungud | N6: saligrama
B7: Uttaradi Mutt(bangalore) | D7: 7 | F7: Mulabagilu sripadaraja | G7: 44667 | H7: Adichunchungiri, hemmaragala, hedtale, kalale, nanjungud | I7: siddarabetta | J7: hemmaragala | N7: shantigrama
B8: Kukke - samputa Narasimha | D8: 8 | F8: Abburu | J8: hedtale | N8: savanadurga
A9: Kaigal falls | B9: HoleNarasipura | D9: 9 | F9: jenukal siddeshwara | I9: Kethanahalli Falls | J9: kanva | K9: channapatna | N9: holenarasipura
A10: Boranakanive Reservoir | B10: Sripadaraja mutt Mulbagilu | D10: 10 | F10: sakharayapatna | H10: Vighnasanthe, Hullekere, Mudigere | I10: primevideo | J10: abbur | K10: channapatna | N10: Mulabagilu
B11: marehalli malavalli SLN temple | D11: 11 | F11: KrishnaYogindraSaraswathi | H11: kondajji, doddagaddavalli, bylahalli | I11: Disney hotstar | J11: aprameya | K11: channapatna | N11: uttaradiMutt
A12: Hemmaragala | B12: Ugra NarasimhaMaddur | D12: 12 | F12: MukunduruSwamy | H12: Vighnasanthe, Nonavinakere, Aralaguppe, | I12: sony liv | J12: holeanjaneya | K12: Maddur | N12: samputaNarasimha
A13: Abburu | B13: Bichchale | D13: 13 | F13: Ananthashrama | I13: zee5 | J13: vaidyanatheshwara | K13: Maddur
A14: Kengal Anjaneya - narsimhaswamy | B14: Sugganahalli | D14: 14 | F14: Siddarudaru | H14: Haranahalli | I14: voot select | J14: ugraNarasimha | K14: Maddur
B15: Nagamangala yoga narasimha | D15: 15 | H15: belavadi | I15: voot kids | J15: netra narayana | K15: Maddur
B16: Shantigrama | D16: 16 | H16: arakere | I16: sun nxt | J16: karighatta | K16: srirangapatna
B17: Saligrama-mysore | D17: 17 | H17: javagal | I17: holchol | J17: nimishamba | K17: srirangapatna
A18: Sringeri | B18: Kote Betta Kambada Narasimha swamy Nagamangal | D18: 18 | H18: Shri koppara Lakshmi Narasimha devalaya | I18: discovery | J18: melukote | N18: ergonomic mouse/keyboard
B19: Hatyalu Narasimha | D19: 19 | H19: Shurpali (Shurpalaya) Shri Lakshmi Narasimha Temple | I19: Universal+ | J19: kere tonnuru | N19: beard trimmer
B20: nonavinakere gopalakrishna | D20: 20 | I20: Altbalaji | J20: nagamangala | N20: car dashcam
A21: Horanadu | B21: jalari lakshmi narasimha - chikkaballapur | D21: 21 | I21: ErosNow | J21: narasimha temple | K21: saligrama
A22: kolluru | B22: sriranganatha temple | C22: srirangapatna | D22: 22 | I22: lionsgate play | J22: keshava temple | K22: shantigrama
B23: manikarnika | C23: srirangapatna | D23: 23 | I23: shemaroo me | J23: narasimha temple | K23: shantigrama
A24: rangapura, bellary | B24: moola narasimha | C24: srirangapatna | D24: 24 | I24: jio cinema | J24: chunchunkatte
A25: Doddadalavatta | B25: bannerghatta | D25: 25 | I25: jio savaan | J25: seebi
A26: Sri Yoganarasimhaswamy, Sri Ramalakshmijanardhana Temple, Kadaba, Gubbi Taluka, Tumkur District. | B26: Nuggehalli Lakshmi Narasimha Temple | C26: trikoota | D26: 26 | J26: kalale
B27: Hariharapura | D27: 27 | J27: savanadurga
B28: Varaprada Balele Shri Lakshmi Narasimha Temple | D28: 28 | G28: 44794 | H28: kotebetta, nagamangala, karibetta, nimishamba | I28: arakalgudu | J28: mulabagilu
B29: Nagamangala soumyaKeshava | D29: 29 | I29: goruu | J29: shivagange
B30: ghati | D30: 30 | I30: holenarasipura | J30: siddarabetta
B31: narasimha temple Malleshwara | D31: 31 | I31: belavadi | J31: mavanur
B32: arkalagudu narasimha | D32: 32 | I32: javagal | J32: markonahalli Dam
B33: gorur narasimhaswamy temple | D33: 33 | I33: nuggehalli | J33: kotebetta
B34: Javagal | C34: trikoota | D34: 34 | I34: haranahalli | J34: Mudukuthore
B35: akkihebbalu lakshmi narasimha | D35: 35 | I35: attavara mudigere | J35: somanathapura
B36: kothnur + purandara + narasimha | D36: 36 | G36: 44829 | J36: Bannur
B37: gavimata, near ramamandir | D37: 37 | G37: 44829 | J37: Sugganahalli
B38: Haranahalli | D38: 38 | G38: 44829 | J38: Magadi Ranganatha
B39: TyagarajaNagara | D39: 39 | G39: 44829 | J39: Bhindiganavile
B40: Attiguppe | D40: 40 | G40: 44850 | J40: KRS venugopala
B41: balanganchi | D41: 41 | G41: 44870 | J41: Nuggehalli
B42: baggavalli | D42: 42 | G42: 11-13Nov2022 | J42: kaverikatte
B43: mudigere | D43: 43 | G43: 44773 | J43: Madyaranga
B44: Shri Gutte Lakshminarasimha Swamy | C44: doddaballapur | D44: 44 | J44: Prasanna meenakshi someshwara
B45: Bisalahalli | C45: chikkaballapur | D45: 45 | J45: Kote varadaraja
B46: Balareddyhalli | C46: chikkaballapur | D46: 46 | G46: 44919 | J46: Gunja Narasimha
B47: kadaripura | C47: mulabagilu | D47: 47 | G47: 44919
B48: Gopinatha Betta | C48: chikkaballapur | D48: 48
B49: banavara | D49: 49
A50: Heragu Kertinarayana Temple 13.057129708495383, 76.2665603724444 | B50: doddaballapur | C50: doddaballapur | D50: 50
A51: Sri Lakshmi Janardhana Swamy Temple 12.944078685989249, 75.9455546306843 | B51: narasimha temple Mirle | D51: 51 | H51: BR hills, MM Hills
H52: Shivanasamudra, Madhyaranga
H53: vidurashwatha, Lepakshi
A54: belavadi 13.282268174176117, 75.99566077250503 | H54: nelligere
H55: Halthi
H57: yoga narasimha temple nagamangala
H59: mooguruTripuraSundari
H60: GunjaNarasimha
H61: agastheshwara
C62: trikoota | H62: gargeshwari
C63: trikoota | H63: Kambaraya Hill
A65: devanahalli fort
A66: Jalari narasimhaswamy
A67: rangasthala | H67: I AM NOT FREE
A68: avalabetta | H68: Travelling Trekker
A69: gopinatha betta - narasimhaswamy temple(nandi hills) | H69: Not in Office
H71: kadu malleshwara
H72: bull temple
H73: gavi gangadhareshwara
H74: someshwara
B75: Yoga Madhava Temple, Settikere, 9HJ5+GGG, Settikere, Karnataka 572226 | H75: bannerghatta
B76: Sampige Srinivasa Temple | H76: gundanjaneya
B77: Lakshmi Janardhana Temple, Kadaba Amanikere
G78: 44542 | H78: talakaadu
G79: 44542 | H79: T.narasipura
B80: Hassan-Alur-singapura | C80: https://l.facebook.com/l.php?u=https%3A%2F%2Fmaps.app.goo.gl%2Fh2udoBdjUYVqAHmT7%3Ffbclid%3DIwAR3cM5dNWo75-4I4N3Whze-cMk0KVDiHkhmF4dlk-mPPyNSIGdngbtUniMU&h=AT27tDNctSA3F65W6tIp4ft5u-mO3NQhreQ53z8wDkaK9jjBoMmrF6JRMSTvGlwshA2gfg1wMPQ09X0wGYVFOI5iPB-65F3RQGUc8E8yWTD0XgjUG7tb1Nj0osuLFLNf3w&__tn__=R]-R&c[0]=AT1EjPV7Y_DcEgfi7Up7eatLz9g5Hq0Bzwn5tBQVkEiHtxkXsz1T_Rpz5Wc3TvSz5bpO4OIeMfp6anImqBnzZYXtmEfC9MnRZt6mrGm3bN6ZpsdeXDwdjJfFE7tY7SsuJNGZ7PYCj9SGKl6SP6-HjMqDE_qvw6I4XeYIEKpmrsr47xTHL2RY2RUdB_e8xfO7ny_7n-A26_UixetY_nIdVm67AMU | G80: 44542 | H80: nanjungud
B81: Sree Narayana(padma,Gada,Chakra,Shanka) ,Hampapura,K.R.Nagara tq,Mysore Dist | G81: 44542 | H81: bangalore
G83: 45039 | H83: nuggehalli, shantigrama, saligrama, mavanuru, chunchunkatte
B84: Sri Bhuvaneshwara Temple and Bala Tripura Sundari Sanctum Nagamangala Taluk | G84: 45046 | H84: kudur,sugganahalli,hebbur,hatyalu,aralguppe,nonavinakere,vighnasanthe

Sheet Sheet2
A1: Pay Elements | B1: Actuals | C1: Actuals | D1: Actuals | E1: Actuals | F1: Actuals | G1: Actuals | H1: Actuals | I1: Actuals | J1: Projected | K1: Projected | L1: Projected | M1: Projected | N1: Full Year | P1: Full Year
A2: Earnings | B2: 45748 | C2: 45778 | D2: 45809 | E2: 45839 | F2: 45870 | G2: 45901 | H2: 45931 | I2: 45962 | J2: 45992 | K2: 46023 | L2: 46054 | M2: 46082 | N2: Total Incl Projection | O2: Section 10 Exemptions (If applicable) | P2: Net of Deduction Taxable | R2: Income From | S2: Income To | T2: Rate | U2: Tax
A3: Basic | B3: 107411 | C3: 107411 | D3: 107411 | E3: 107411 | F3: 107411 | G3: 107411 | H3: 107411 | I3: 107411 | J3: 107411 | K3: 116004 | L3: 116004 | M3: 116004 | N3: =SUM(B3:M3) -> 1314711 | P3: 1288932 | R3: 0 | S3: 400000 | T3: 0.0% of 400,000 | U3: 0
A4: House Rent Allowance | B4: 53705 | C4: 53705 | D4: 53705 | E4: 53705 | F4: 53705 | G4: 53705 | H4: 53705 | I4: 53705 | J4: 53705 | K4: 58002 | L4: 58002 | M4: 58002 | N4: =SUM(B4:M4) -> 657351 | P4: 644460 | R4: 400001 | S4: 800000 | T4: 5.0% of 399,999 | U4: 20000
A5: Children Educn School | B5: 200 | C5: 200 | D5: 200 | E5: 200 | F5: 200 | G5: 200 | H5: 200 | I5: 200 | J5: 200 | K5: 200 | L5: 200 | M5: 200 | N5: =SUM(B5:M5) -> 2400 | P5: 2400 | R5: 800001 | S5: 1200000 | T5: 10.0% of 399,999 | U5: 40000
A6: Advance Bonus Exgratia | B6: 3500 | C6: 3500 | D6: 3500 | E6: 3500 | F6: 3500 | G6: 3500 | H6: 3500 | I6: 3500 | J6: 3500 | K6: 3500 | L6: 3500 | M6: 3500 | N6: =SUM(B6:M6) -> 42000 | P6: 42000 | R6: 1200001 | S6: 1600000 | T6: 15.0% of 399,999 | U6: 60000
A7: Conveyance | B7: 5000 | C7: 5000 | D7: 5000 | E7: 5000 | F7: 5000 | G7: 5000 | H7: 5000 | I7: 5000 | J7: 5000 | K7: 5000 | L7: 5000 | M7: 5000 | N7: =SUM(B7:M7) -> 60000 | P7: 60000 | R7: 1600001 | S7: 2000000 | T7: 20.0% of 399,999 | U7: 80000
A8: Leave Travel Concession | B8: 4167 | C8: 4167 | D8: 4167 | E8: 4167 | F8: 4167 | G8: 4167 | H8: 4167 | I8: 4167 | J8: 4167 | K8: 4167 | L8: 4167 | M8: 4167 | N8: =SUM(B8:M8) -> 50004 | P8: 50004 | R8: 2000001 | S8: 2400000 | T8: 25.0% of 399,999 | U8: 100000
A9: Telephone & Broadband Allowance | B9: 4000 | C9: 4000 | D9: 4000 | E9: 4000 | F9: 4000 | G9: 4000 | H9: 4000 | I9: 4000 | J9: 4000 | K9: 4000 | L9: 4000 | M9: 4000 | N9: =SUM(B9:M9) -> 48000 | P9: 48000 | R9: 2400001 | S9: 2986990 | T9: 30.0% of 586,989 | U9: 176097
A10: E Award | B10: 0 | C10: 2231 | D10: 0 | E10: 8700 | F10: 0 | G10: 0 | H10: 4523 | I10: 3846 | J10: 153954 | K10: 0 | L10: 0 | M10: 0 | N10: =SUM(B10:M10) -> 173254 | P10: 19300
A11: Personal Pay | B11: 70288 | C11: 70288 | D11: 70288 | E11: 70288 | F11: 70288 | G11: 70288 | H11: 70288 | I11: 70288 | J11: 70288 | K11: 77436 | L11: 77436 | M11: 77436 | N11: =SUM(B11:M11) -> 864900 | P11: 843456
A12: Total Earnings | B12: 248271 | C12: 250502 | D12: 248271 | E12: 256971 | F12: 248271 | G12: 248271 | H12: 252794 | I12: 252117 | J12: =SUM(J3:J11) -> 402225 | K12: =SUM(K3:K11) -> 268309 | L12: =SUM(L3:L11) -> 268309 | M12: =SUM(M3:M11) -> 268309 | N12: =SUM(B12:M12) -> 3212620 | O12: 0 | P12: =SUM(B12:M12) -> 3212620
A13: Deductions
A14: Provident Fund | B14: 12889 | C14: 12889 | D14: 12889 | E14: 12889 | F14: 12889 | G14: 12889 | H14: 12889 | I14: 12889 | J14: 12889 | K14: 13920 | L14: 13920 | M14: 13920 | N14: 154668 | P14: 154668
A15: Profession Tax | B15: 200 | C15: 200 | D15: 200 | E15: 200 | F15: 200 | G15: 200 | H15: 200 | I15: 200 | J15: 200 | K15: 200 | L15: 300 | M15: 200 | N15: 2500 | P15: 2500
A16: Income Tax | B16: 39111 | C16: 41494 | D16: 39242 | E16: 49302 | F16: 39404 | G16: 39502 | H16: 44321 | I16: 43754 | J16: 90000 | K16: 43754 | L16: 43754 | M16: 43754 | N16: =SUM(B16:M16) -> 557392 | P16: 495142
A17: Total Deductions | B17: 52200 | C17: 54583 | D17: 52331 | E17: 62391 | F17: 52493 | G17: 52591 | H17: 57410 | I17: 56843 | J17: =SUM(J14:J16) -> 103089 | K17: =SUM(K14:K16) -> 57874 | L17: =SUM(L14:L16) -> 57974 | M17: =SUM(M14:M16) -> 57874 | N17: 652210 | P17: 652210
A18: Net Earnings | B18: 196071 | C18: 195919 | D18: 195940 | E18: 194580 | F18: 195778 | G18: 195680 | H18: 195384 | I18: 195274 | J18: =J12-J17 -> 299136 | K18: =K12-K17 -> 210435 | L18: =L12-L17 -> 210335 | N18: 2346342 | O18: 0 | P18: 2346342
D22: 3222328 | F22: 3480113
D23: -144440 | F23: -234003
D24: =SUM(D22:D23) -> 3077888 | F24: =SUM(F22:F23) -> 3246110
D25: =D24/12 -> 256490.67 | F25: =F24/12 -> 270509.17
D27: =248272*12 -> 2979264
D28: =2200*12 -> 26400
D29: =SUM(D27:D28) -> 3005664

Sheet Sheet1
A1: aug | B1: 45505 | C1: 45506 | D1: 45507 | E1: 45508 | F1: 45509 | G1: 45510 | H1: 45511 | I1: 45512 | J1: 45513 | K1: 45514 | L1: 45515 | M1: 45516 | N1: 45517 | O1: 45518 | P1: 45519 | Q1: 45520 | R1: 45521 | S1: 45522 | T1: 45523 | U1: 45524 | V1: 45525 | W1: 45526 | X1: 45527 | Y1: 45528 | Z1: 45529 | AA1: 45530 | AB1: 45531 | AC1: 45532 | AD1: 45533 | AE1: 45534 | AF1: 45535
A2: sep | B2: 45536 | C2: 45537 | D2: 45538 | E2: 45539 | F2: 45540 | G2: 45541 | H2: 45542 | I2: 45543 | J2: 45544 | K2: 45545 | L2: 45546 | M2: 45547 | N2: 45548 | O2: 45549 | P2: 45550 | Q2: 45551 | R2: 45552 | S2: 45553 | T2: 45554 | U2: 45555 | V2: 45556 | W2: 45557 | X2: 45558 | Y2: 45559 | Z2: 45560 | AA2: 45561 | AB2: 45562 | AC2: 45563 | AD2: 45564 | AE2: 45565
A3: oct | B3: 45566 | C3: 45567 | D3: 45568 | E3: 45569 | F3: 45570 | G3: 45571 | H3: 45572 | I3: 45573 | J3: 45574 | K3: 45575 | L3: 45576 | M3: 45577 | N3: 45578 | O3: 45579 | P3: 45580 | Q3: 45581 | R3: 45582 | S3: 45583 | T3: 45584 | U3: 45585 | V3: 45586 | W3: 45587 | X3: 45588 | Y3: 45589 | Z3: 45590 | AA3: 45591 | AB3: 45592 | AC3: 45593 | AD3: 45594 | AE3: 45595 | AF3: 45596
A4: nov | B4: 45597 | C4: 45598 | D4: 45599 | E4: 45600 | F4: 45601 | G4: 45602 | H4: 45603 | I4: 45604 | J4: 45605 | K4: 45606 | L4: 45607 | M4: 45608 | N4: 45609 | O4: 45610 | P4: 45611 | Q4: 45612 | R4: 45613 | S4: 45614 | T4: 45615 | U4: 45616 | V4: 45617 | W4: 45618 | X4: 45619 | Y4: 45620 | Z4: 45621 | AA4: 45622 | AB4: 45623 | AC4: 45624 | AD4: 45625 | AE4: 45626
A5: dec | B5: 45627 | C5: 45628 | D5: 45629 | E5: 45630 | F5: 45631 | G5: 45632 | H5: 45633 | I5: 45634 | J5: 45635 | K5: 45636 | L5: 45637 | M5: 45638 | N5: 45639 | O5: 45640 | P5: 45641 | Q5: 45642 | R5: 45643 | S5: 45644 | T5: 45645 | U5: 45646 | V5: 45647 | W5: 45648 | X5: 45649 | Y5: 45650 | Z5: 45651 | AA5: 45652 | AB5: 45653 | AC5: 45654 | AD5: 45655 | AE5: 45656 | AF5: 45657 | AG5: 45658
C6: 1 | D6: 2 | E6: 3 | F6: 4 | G6: 5 | J6: 6 | K6: 7 | L6: 8 | M6: 9 | N6: 10 | Q6: 11 | R6: 12 | S6: 13 | T6: 14 | U6: 15 | X6: 16 | Y6: 17 | AA6: 18 | AB6: 19 | AE6: 20 | AF6: 21
A7: jan | B7: 45658 | C7: 45659 | D7: 45660 | E7: 45661 | F7: 45662 | G7: 45663 | H7: 45664 | I7: 45665 | J7: 45666 | K7: 45667 | L7: 45668 | M7: 45669 | N7: 45670 | O7: 45671 | P7: 45672 | Q7: 45673 | R7: 45674 | S7: 45675 | T7: 45676 | U7: 45677 | V7: 45678 | W7: 45679 | X7: 45680 | Y7: 45681 | Z7: 45682 | AA7: 45683 | AB7: 45684 | AC7: 45685 | AD7: 45686 | AE7: 45687 | AF7: 45688
A8: feb | B8: 45689 | C8: 45690 | D8: 45691 | E8: 45692 | F8: 45693 | G8: 45694 | H8: 45695 | I8: 45696 | J8: 45697 | K8: 45698 | L8: 45699 | M8: 45700 | N8: 45701 | O8: 45702 | P8: 45703 | Q8: 45704 | R8: 45705 | S8: 45706 | T8: 45707 | U8: 45708 | V8: 45709 | W8: 45710 | X8: 45711 | Y8: 45712 | Z8: 45713 | AA8: 45714 | AB8: 45715 | AC8: 45716
A9: Mar | B9: 45717 | C9: 45718 | D9: 45719 | E9: 45720 | F9: 45721 | G9: 45722 | H9: 45723 | I9: 45724 | J9: 45725 | K9: 45726 | L9: 45727 | M9: 45728 | N9: 45729 | O9: 45730 | P9: 45731 | Q9: 45732 | R9: 45733 | S9: 45734 | T9: 45735 | U9: 45736 | V9: 45737 | W9: 45738 | X9: 45739 | Y9: 45740 | Z9: 45741 | AA9: 45742 | AB9: 45743 | AC9: 45744 | AD9: 45745 | AE9: 45746 | AF9: 45747
C11: Britannia | I11: 45474 | J11: 45505 | K11: 45536 | L11: 45566 | M11: 45597 | N11: 45627 | O11: 45658 | P11: 45689 | Q11: 45717
C12: DObuy | D12: Qty | E12: BuyPrice | H12: FF | I12: 15000 | J12: 15000 | K12: 15000
C13: 44340 | D13: 10 | E13: 3385 | F13: =D13*E13 -> 33850 | H13: shop | I13: 6000 | J13: 6000 | K13: 6000
C14: 44686 | D14: 7 | E14: 3337 | F14: =D14*E14 -> 23359 | H14: GF | I14: 15270 | J14: 0 | K14: 15000
C15: 44690 | D15: 2 | E15: 3250 | F15: =D15*E15 -> 6500
D16: =SUM(D13:D15) -> 19 | F16: =SUM(F13:F15) -> 63709
C17: DOsale | D17: Qty | E17: saleVal
C18: 44734 | D18: 19 | E18: 3407 | F18: =D18*E18 -> 64733
O19: =2.5*83256 -> 208140
I20: 45507 | J20: 655 | K20: 0 | L20: 655000
C21: Dabur | I21: 45515 | J21: 668 | K21: 51 | L21: 668000
C22: DOP | D22: Qty | E22: Price | I22: 45517 | J22: 671 | K22: 98 | L22: 671000
C23: 44659 | D23: 20 | E23: 565 | F23: =D23*E23 -> 11300 | I23: 45519 | J23: 675 | K23: 38 | L23: 675000
C24: 44686 | D24: 10 | E24: 534 | F24: =D24*E24 -> 5340 | I24: 45521 | J24: 679 | K24: 0 | L24: 679000
C25: 44690 | D25: 9 | E25: 509 | F25: =D25*E25 -> 4581 | I25: 45523 | J25: 683 | K25: 73 | L25: 683000
C26: 44697 | D26: 1 | E26: 498 | F26: =D26*E26 -> 498 | I26: 45525 | J26: 687 | K26: 0 | L26: 687000
C27: 44697 | D27: 1 | E27: 497 | F27: =D27*E27 -> 497 | I27: 45527 | J27: 690 | K27: 8 | L27: 690000
C28: 44697 | D28: 1 | E28: 496 | F28: =D28*E28 -> 496 | I28: 45529 | J28: 694 | K28: 1 | L28: 694000
C29: 44720 | D29: 1 | E29: 493 | F29: =D29*E29 -> 493 | I29: 45531 | J29: 698 | K29: 9 | L29: 698000
D30: 43 | F30: =SUM(F23:F29) -> 23205 | I30: 45533 | J30: 702 | K30: 3 | L30: 702000
C31: DOsale | D31: Qty | E31: saleVal | I31: 45535
C32: 44748 | D32: 43 | E32: 540 | F32: =D32*E32 -> 23220 | I32: 45506
C35: REC
C36: 44722 | D36: 1 | E36: 117 | F36: =D36*E36 -> 117
C37: 44725 | D37: 4 | E37: 115 | F37: =D37*E37 -> 460
C38: 44728 | D38: 10 | E38: 114 | F38: =D38*E38 -> 1140
C39: 44746 | D39: 10 | E39: 125.85 | F39: =D39*E39 -> 1258.5
D40: 25 | F40: =SUM(F36:F39) -> 2975.5
C41: DOsale | D41: Qty | E41: saleVal
C42: 44789 | D42: 25 | E42: 136.5 | F42: =D42*E42 -> 3412.5
C45: Praj Industries
C46: DOP | D46: Qty | E46: Price
C47: 44335 | D47: 10 | E47: 395 | F47: =D47*E47 -> 3950
C48: 44342 | D48: 10 | E48: 366 | F48: =D48*E48 -> 3660
C49: 44344 | D49: 10 | E49: 339 | F49: =D49*E49 -> 3390
C50: 44332 | D50: 4 | E50: 327 | F50: =D50*E50 -> 1308
D51: 34 | F51: =SUM(F47:F50) -> 12308
C52: DOsale | D52: Qty | E52: saleVal
C53: 44748 | D53: 34 | E53: 370.3 | F53: =D53*E53 -> 12590.2
C56: Tata consumer
C57: DOP | D57: Qty | E57: Price
C58: 44690 | D58: 1 | E58: 759 | F58: =D58*E58 -> 759
C59: 44693 | D59: 1 | E59: 729 | F59: =D59*E59 -> 729
C60: 44698 | D60: 1 | E60: 723 | F60: =D60*E60 -> 723
C61: 44698 | D61: 1 | E61: 724 | F61: =D61*E61 -> 724
D62: 4 | F62: =SUM(F58:F61) -> 2935
C63: DOsale | D63: Qty | E63: saleVal
C64: 44748 | D64: 4 | E64: 739.9 | F64: =D64*E64 -> 2959.6
C67: GAIL
C68: DOP | D68: Qty | E68: Price
C69: 43174 | D69: 6 | E69: 454 | F69: =D69*E69 -> 2724
C70: DOsale | D70: Qty | E70: saleVal
C71: 44747 | D71: 6 | E71: 190 | F71: =D71*E71 -> 1140
C74: GLAND
C75: DOP | D75: Qty | E75: Price
C76: 44155 | D76: 60 | E76: 1500 | F76: 90000
C77: DOsale | D77: Qty | E77: saleVal
C78: 44763 | D78: 60 | E78: 2235 | F78: =D78*E78 -> 134100
C80: HIND PETRO
C81: DOP | D81: Qty | E81: Price
C82: 42923 | D82: 10 | E82: 515 | F82: =D82*E82 -> 5150
C83: 43445 | D83: 20 | E83: 225 | F83: =D83*E83 -> 4500
D84: 30 | F84: =SUM(F82:F83) -> 9650
C85: DOsale | D85: Qty | E85: saleVal
C86: 44734 | D86: 30 | E86: 224 | F86: =D86*E86 -> 6720
